Workbook
Name \a: #REF!
Name \a: #REF!
Name \p: #REF!
Name \p: #REF!
Name ____________z2: {"Sch00",#N/A,FALSE,"1";"Contents",#N/A,FALSE,"1"}
Name ____________z2: {"Sch00",#N/A,FALSE,"1";"Contents",#N/A,FALSE,"1"}
Name ___________z2: {"Sch00",#N/A,FALSE,"1";"Contents",#N/A,FALSE,"1"}
Name ___________z2: {"Sch00",#N/A,FALSE,"1";"Contents",#N/A,FALSE,"1"}
Name __________z2: {"Sch00",#N/A,FALSE,"1";"Contents",#N/A,FALSE,"1"}
Name __________z2: {"Sch00",#N/A,FALSE,"1";"Contents",#N/A,FALSE,"1"}
Name _________key1: #REF!
Name _________PL2: {#N/A,#N/A,FALSE,"Aging Summary";#N/A,#N/A,FALSE,"Ratio Analysis";#N/A,#N/A,FALSE,"Test 120 Day Accts";#N/A,#N/A,FALSE,"Tickmarks"}
Name _________PL2: {#N/A,#N/A,FALSE,"Aging Summary";#N/A,#N/A,FALSE,"Ratio Analysis";#N/A,#N/A,FALSE,"Test 120 Day Accts";#N/A,#N/A,FALSE,"Tickmarks"}
Name _________w2: {"HİZDAFİŞ",#N/A,FALSE,"YDYUKLE"}
Name _________w2: {"HİZDAFİŞ",#N/A,FALSE,"YDYUKLE"}
Name _________z2: {"Sch00",#N/A,FALSE,"1";"Contents",#N/A,FALSE,"1"}
Name _________z2: {"Sch00",#N/A,FALSE,"1";"Contents",#N/A,FALSE,"1"}
Name ________c: {"Fiesta Facer Page",#N/A,FALSE,"Q_C_S";"Fiesta Main Page",#N/A,FALSE,"V_L";"Fiesta 95BP Struct",#N/A,FALSE,"StructBP";"Fiesta Post 95BP Struct",#N/A,FALSE,"AdjStructBP"}
Name ________c: {"Fiesta Facer Page",#N/A,FALSE,"Q_C_S";"Fiesta Main Page",#N/A,FALSE,"V_L";"Fiesta 95BP Struct",#N/A,FALSE,"StructBP";"Fiesta Post 95BP Struct",#N/A,FALSE,"AdjStructBP"}
Name ________key1: #REF!
Name ________key1: #REF!
Name ________PL2: {#N/A,#N/A,FALSE,"Aging Summary";#N/A,#N/A,FALSE,"Ratio Analysis";#N/A,#N/A,FALSE,"Test 120 Day Accts";#N/A,#N/A,FALSE,"Tickmarks"}
Name ________PL2: {#N/A,#N/A,FALSE,"Aging Summary";#N/A,#N/A,FALSE,"Ratio Analysis";#N/A,#N/A,FALSE,"Test 120 Day Accts";#N/A,#N/A,FALSE,"Tickmarks"}
Name ________w1: #REF!
Name ________w1: #REF!
Name ________w2: {"HİZDAFİŞ",#N/A,FALSE,"YDYUKLE"}
Name ________w2: {"HİZDAFİŞ",#N/A,FALSE,"YDYUKLE"}
Name ________z2: {"Sch00",#N/A,FALSE,"1";"Contents",#N/A,FALSE,"1"}
Name ________z2: {"Sch00",#N/A,FALSE,"1";"Contents",#N/A,FALSE,"1"}
Name _______A1: {#N/A,#N/A,FALSE,"MALİTABLOLAR"}
Name _______A1: {#N/A,#N/A,FALSE,"MALİTABLOLAR"}
Name _______c: {"Fiesta Facer Page",#N/A,FALSE,"Q_C_S";"Fiesta Main Page",#N/A,FALSE,"V_L";"Fiesta 95BP Struct",#N/A,FALSE,"StructBP";"Fiesta Post 95BP Struct",#N/A,FALSE,"AdjStructBP"}
Name _______c: {"Fiesta Facer Page",#N/A,FALSE,"Q_C_S";"Fiesta Main Page",#N/A,FALSE,"V_L";"Fiesta 95BP Struct",#N/A,FALSE,"StructBP";"Fiesta Post 95BP Struct",#N/A,FALSE,"AdjStructBP"}
Name _______key1: #REF!
Name _______key1: #REF!
Name _______PL2: {#N/A,#N/A,FALSE,"Aging Summary";#N/A,#N/A,FALSE,"Ratio Analysis";#N/A,#N/A,FALSE,"Test 120 Day Accts";#N/A,#N/A,FALSE,"Tickmarks"}
Name _______PL2: {#N/A,#N/A,FALSE,"Aging Summary";#N/A,#N/A,FALSE,"Ratio Analysis";#N/A,#N/A,FALSE,"Test 120 Day Accts";#N/A,#N/A,FALSE,"Tickmarks"}
Name _______w1: #REF!
Name _______w1: #REF!
Name _______w2: {"HİZDAFİŞ",#N/A,FALSE,"YDYUKLE"}
Name _______w2: {"HİZDAFİŞ",#N/A,FALSE,"YDYUKLE"}
Name _______z2: {"Sch00",#N/A,FALSE,"1";"Contents",#N/A,FALSE,"1"}
Name _______z2: {"Sch00",#N/A,FALSE,"1";"Contents",#N/A,FALSE,"1"}
Name ______c: {"Fiesta Facer Page",#N/A,FALSE,"Q_C_S";"Fiesta Main Page",#N/A,FALSE,"V_L";"Fiesta 95BP Struct",#N/A,FALSE,"StructBP";"Fiesta Post 95BP Struct",#N/A,FALSE,"AdjStructBP"}
Name ______c: {"Fiesta Facer Page",#N/A,FALSE,"Q_C_S";"Fiesta Main Page",#N/A,FALSE,"V_L";"Fiesta 95BP Struct",#N/A,FALSE,"StructBP";"Fiesta Post 95BP Struct",#N/A,FALSE,"AdjStructBP"}
Name ______d: {"Fiesta Facer Page",#N/A,FALSE,"Q_C_S";"Fiesta Main Page",#N/A,FALSE,"V_L";"Fiesta 95BP Struct",#N/A,FALSE,"StructBP";"Fiesta Post 95BP Struct",#N/A,FALSE,"AdjStructBP"}
Name ______d: {"Fiesta Facer Page",#N/A,FALSE,"Q_C_S";"Fiesta Main Page",#N/A,FALSE,"V_L";"Fiesta 95BP Struct",#N/A,FALSE,"StructBP";"Fiesta Post 95BP Struct",#N/A,FALSE,"AdjStructBP"}
Name ______key1: #REF!
Name ______key1: #REF!
Name ______PL2: {#N/A,#N/A,FALSE,"Aging Summary";#N/A,#N/A,FALSE,"Ratio Analysis";#N/A,#N/A,FALSE,"Test 120 Day Accts";#N/A,#N/A,FALSE,"Tickmarks"}
Name ______PL2: {#N/A,#N/A,FALSE,"Aging Summary";#N/A,#N/A,FALSE,"Ratio Analysis";#N/A,#N/A,FALSE,"Test 120 Day Accts";#N/A,#N/A,FALSE,"Tickmarks"}
Name ______w1: #REF!
Name ______w1: #REF!
Name ______w2: {"HİZDAFİŞ",#N/A,FALSE,"YDYUKLE"}
Name ______w2: {"HİZDAFİŞ",#N/A,FALSE,"YDYUKLE"}
Name ______z2: {"Sch00",#N/A,FALSE,"1";"Contents",#N/A,FALSE,"1"}
Name ______z2: {"Sch00",#N/A,FALSE,"1";"Contents",#N/A,FALSE,"1"}
Name _____A1: {#N/A,#N/A,FALSE,"MALİTABLOLAR"}
Name _____A1: {#N/A,#N/A,FALSE,"MALİTABLOLAR"}
Name _____key1: #REF!

Sheet Consolidated ARR Rollforward
B2: Trio Mobil
B3: Consolidated ARR Rollforward
C5: =C6&" " &YEAR(C8) -> Q4 2021 | D5: =D6&" " &YEAR(D8) -> Q4 2022 | E5: =E6&" " &YEAR(E8) -> Q4 2023 | F5: =F6&" " &YEAR(F8) -> Q4 2024 | G5: =G6&" " &YEAR(G8) -> TTM 2025 | I5: =I6&" " &YEAR(I8) -> Q1 2021 | J5: =J6&" " &YEAR(J8) -> Q2 2021 | K5: =K6&" " &YEAR(K8) -> Q3 2021 | L5: =L6&" " &YEAR(L8) -> Q4 2021 | M5: =M6&" " &YEAR(M8) -> Q1 2022 | N5: =N6&" " &YEAR(N8) -> Q2 2022 | O5: =O6&" " &YEAR(O8) -> Q3 2022 | P5: =P6&" " &YEAR(P8) -> Q4 2022 | ... AB5: =AB6&" " &YEAR(AB8) -> Q4 2025 | AD5: =AD6&" " &YEAR(AD8) -> Q1 2021 | AE5: =AE6&" " &YEAR(AE8) -> Q1 2021 | AF5: =AF6&" " &YEAR(AF8) -> Q1 2021 | AG5: =AG6&" " &YEAR(AG8) -> Q2 2021 | AH5: =AH6&" " &YEAR(AH8) -> Q2 2021 | AI5: =AI6&" " &YEAR(AI8) -> Q2 2021 | AJ5: =AJ6&" " &YEAR(AJ8) -> Q3 2021 | AK5: =AK6&" " &YEAR(AK8) -> Q3 2021 | ... CK5: =CK6&" " &YEAR(CK8) -> Q4 2025
C6: Q4 | D6: Q4 | E6: Q4 | F6: Q4 | G6: TTM | I6: Q1 | J6: Q2 | K6: Q3 | L6: Q4 | M6: Q1 | N6: Q2 | O6: Q3 | P6: Q4 | Q6: Q1 | R6: Q2 | S6: Q3 | T6: Q4 | U6: Q1 | V6: Q2 | W6: Q3 | X6: Q4 | Y6: Q1 | Z6: Q2 | AA6: Q3 | AB6: Q4 | AD6: Q1 | AE6: Q1 | AF6: Q1 | AG6: Q2 | AH6: Q2 | AI6: Q2 | AJ6: Q3 | AK6: Q3 | AL6: Q3 | AM6: Q4 | AN6: Q4 | AO6: Q4 | AP6: Q1 | AQ6: Q1 | AR6: Q1 | AS6: Q2 | AT6: Q2 | AU6: Q2 | AV6: Q3 | AW6: Q3 | AX6: Q3 | AY6: Q4 | AZ6: Q4 | BA6: Q4 | BB6: Q1 | BC6: Q1 | BD6: Q1 | BE6: Q2 | BF6: Q2 | BG6: Q2 | BH6: Q3 | BI6: Q3 | BJ6: Q3 | BK6: Q4 | BL6: Q4 | BM6: Q4 | BN6: Q1 | BO6: Q1 | BP6: Q1 | BQ6: Q2 | BR6: Q2 | BS6: Q2 | BT6: Q3 | BU6: Q3 | BV6: Q3 | BW6: Q4 | BX6: Q4 | BY6: Q4 | BZ6: Q1 | CA6: Q1 | CB6: Q1 | CC6: Q2 | CD6: Q2 | CE6: Q2 | CF6: Q3 | CG6: Q3 | CH6: Q3 | CI6: Q4 | CJ6: Q4 | CK6: Q4
C7: =YEAR(C8) -> 2021 | D7: =YEAR(D8) -> 2022 | E7: =YEAR(E8) -> 2023 | F7: =YEAR(F8) -> 2024 | G7: =YEAR(G8) -> 2025 | I7: =YEAR(I8) -> 2021 | J7: =YEAR(J8) -> 2021 | K7: =YEAR(K8) -> 2021 | L7: =YEAR(L8) -> 2021 | M7: =YEAR(M8) -> 2022 | N7: =YEAR(N8) -> 2022 | O7: =YEAR(O8) -> 2022 | P7: =YEAR(P8) -> 2022 | ... AB7: =YEAR(AB8) -> 2025 | AD7: =YEAR(AD8) -> 2021 | AE7: =YEAR(AE8) -> 2021 | AF7: =YEAR(AF8) -> 2021 | AG7: =YEAR(AG8) -> 2021 | AH7: =YEAR(AH8) -> 2021 | AI7: =YEAR(AI8) -> 2021 | AJ7: =YEAR(AJ8) -> 2021 | AK7: =YEAR(AK8) -> 2021 | ... CK7: =YEAR(CK8) -> 2025
B8: Consolidated | C8: 44561 | D8: =EOMONTH(C8,12) -> 44926 | E8: =EOMONTH(D8,12) -> 45291 | F8: =EOMONTH(E8,12) -> 45657 | G8: =EOMONTH(F8,12) -> 46022 | I8: 44286 | J8: =EOMONTH(I8,3) -> 44377 | K8: =EOMONTH(J8,3) -> 44469 | L8: =EOMONTH(K8,3) -> 44561 | M8: =EOMONTH(L8,3) -> 44651 | N8: =EOMONTH(M8,3) -> 44742 | O8: =EOMONTH(N8,3) -> 44834 | P8: =EOMONTH(O8,3) -> 44926 | Q8: =EOMONTH(P8,3) -> 45016 | ... V8: =EOMONTH(U8,3) -> 45473 | W8: 45565 | X8: 45657 | Y8: 45747 | Z8: 45838 | AA8: 45930 | AB8: 46022 | AD8: 44227 | AE8: =EOMONTH(AD8,1) -> 44255 | AF8: =EOMONTH(AE8,1) -> 44286 | AG8: =EOMONTH(AF8,1) -> 44316 | AH8: =EOMONTH(AG8,1) -> 44347 | AI8: =EOMONTH(AH8,1) -> 44377 | AJ8: =EOMONTH(AI8,1) -> 44408 | AK8: =EOMONTH(AJ8,1) -> 44439 | AL8: =EOMONTH(AK8,1) -> 44469 | ... CK8: =EOMONTH(CJ8,1) -> 46022
B9: Beginning | C9: =I9 -> 715138.93 | D9: =+SUMIFS($AD$14:$CF$14,$AD$8:$CF$8,EOMONTH(D8,-12)) -> 3507271 | E9: =+SUMIFS($AD$14:$CF$14,$AD$8:$CF$8,EOMONTH(E8,-12)) -> 5002928.5 | F9: =+SUMIFS($AD$14:$CF$14,$AD$8:$CF$8,EOMONTH(F8,-12)) -> 8109284.5 | G9: =+SUMIFS($AD$14:$CL$14,$AD$8:$CL$8,EOMONTH(G8,-12)) -> 12126892 | I9: =AD9 -> 715138.93 | J9: =I14 -> 3495929.7 | K9: =J14 -> 3452428.7 | L9: =K14 -> 3577856.3 | M9: =L14 -> 3507271 | N9: =M14 -> 3631952.4 | O9: =N14 -> 4203281.2 | P9: =O14 -> 4549342.6 | Q9: =P14 -> 5002928.5 | ... AB9: =AA14 -> 15273205 | AD9: ='Industrial ARR Rollforward'!AD9+'Fleet ARR Rollforward'!AD9 -> 715138.93 | AE9: ='Industrial ARR Rollforward'!AE9+'Fleet ARR Rollforward'!AE9 -> 3529580 | AF9: ='Industrial ARR Rollforward'!AF9+'Fleet ARR Rollforward'!AF9 -> 3528617.5 | AG9: ='Industrial ARR Rollforward'!AG9+'Fleet ARR Rollforward'!AG9 -> 3495929.7 | AH9: ='Industrial ARR Rollforward'!AH9+'Fleet ARR Rollforward'!AH9 -> 3493397.3 | AI9: ='Industrial ARR Rollforward'!AI9+'Fleet ARR Rollforward'!AI9 -> 3449599.5 | AJ9: ='Industrial ARR Rollforward'!AJ9+'Fleet ARR Rollforward'!AJ9 -> 3452428.7 | AK9: ='Industrial ARR Rollforward'!AK9+'Fleet ARR Rollforward'!AK9 -> 3405075 | ... CK9: ='Industrial ARR Rollforward'!CK9+'Fleet ARR Rollforward'!CK9 -> 15617061
B10: (+) New | C10: =SUMIFS($I10:$W10,$I$7:$W$7,C$7) -> 3400161.7 | D10: =+SUM(OFFSET(INDEX($AD10:$CF10,MATCH(D$8,$AD$8:$CF$8,0)),,,,-12)) -> 1165365.2 | E10: =+SUM(OFFSET(INDEX($AD10:$CF10,MATCH(E$8,$AD$8:$CF$8,0)),,,,-12)) -> 1954185 | F10: =+SUM(OFFSET(INDEX($AD10:$CF10,MATCH(F$8,$AD$8:$CF$8,0)),,,,-12)) -> 1964300.1 | G10: =+SUM(OFFSET(INDEX($AD10:$CL10,MATCH(G$8,$AD$8:$CL$8,0)),,,,-12)) -> 3557396.4 | I10: =SUMIFS($AD10:$BT10,$AD$5:$BT$5,I$5) -> 2870278.7 | J10: =SUMIFS($AD10:$BT10,$AD$5:$BT$5,J$5) -> 101821.64 | K10: =SUMIFS($AD10:$BT10,$AD$5:$BT$5,K$5) -> 234100.68 | L10: =SUMIFS($AD10:$BT10,$AD$5:$BT$5,L$5) -> 193960.62 | M10: =SUMIFS($AD10:$BT10,$AD$5:$BT$5,M$5) -> 150751.61 | N10: =SUMIFS($AD10:$BT10,$AD$5:$BT$5,N$5) -> 493235.1 | O10: =SUMIFS($AD10:$BT10,$AD$5:$BT$5,O$5) -> 273237.78 | P10: =SUMIFS($AD10:$BT10,$AD$5:$BT$5,P$5) -> 248140.68 | ... V10: =SUMIFS($AD10:$BT10,$AD$5:$BT$5,V$5) -> 544603.79 | W10: =SUMIFS($AD10:$CF10,$AD$5:$CF$5,W$5) -> 310214.83 | X10: =SUMIFS($AD10:$CF10,$AD$5:$CF$5,X$5) -> 687632.42 | Y10: =SUMIFS($AD10:$CF10,$AD$5:$CF$5,Y$5) -> 1197487.5 | Z10: =SUMIFS($AD10:$CF10,$AD$5:$CF$5,Z$5) -> 721391.07 | AA10: =SUMIFS($AD10:$CL10,$AD$5:$CL$5,AA$5) -> 700150.82 | AB10: =SUMIFS($AD10:$CL10,$AD$5:$CL$5,AB$5) -> 938367.02 | AD10: ='Industrial ARR Rollforward'!AD10+'Fleet ARR Rollforward'!AD10 -> 2787519.2 | AE10: ='Industrial ARR Rollforward'!AE10+'Fleet ARR Rollforward'!AE10 -> 47145.806 | AF10: ='Industrial ARR Rollforward'!AF10+'Fleet ARR Rollforward'!AF10 -> 35613.696 | AG10: ='Industrial ARR Rollforward'!AG10+'Fleet ARR Rollforward'!AG10 -> 36724.558 | AH10: ='Industrial ARR Rollforward'!AH10+'Fleet ARR Rollforward'!AH10 -> 23508.482 | AI10: ='Industrial ARR Rollforward'!AI10+'Fleet ARR Rollforward'!AI10 -> 41588.602 | AJ10: ='Industrial ARR Rollforward'!AJ10+'Fleet ARR Rollforward'!AJ10 -> 41493.194 | AK10: ='Industrial ARR Rollforward'!AK10+'Fleet ARR Rollforward'!AK10 -> 69799.236 | ... CK10: ='Industrial ARR Rollforward'!CK10+'Fleet ARR Rollforward'!CK10 -> 620438.57
B11: (+) Upsell | C11: =SUMIFS($I11:$W11,$I$7:$W$7,C$7) -> 780822.36 | D11: =+SUM(OFFSET(INDEX($AD11:$CF11,MATCH(D$8,$AD$8:$CF$8,0)),,,,-12)) -> 1631159.5 | E11: =+SUM(OFFSET(INDEX($AD11:$CF11,MATCH(E$8,$AD$8:$CF$8,0)),,,,-12)) -> 2737333.3 | F11: =+SUM(OFFSET(INDEX($AD11:$CF11,MATCH(F$8,$AD$8:$CF$8,0)),,,,-12)) -> 4066096.9 | G11: =+SUM(OFFSET(INDEX($AD11:$CL11,MATCH(G$8,$AD$8:$CL$8,0)),,,,-12)) -> 3975848.5 | I11: =SUMIFS($AD11:$BT11,$AD$5:$BT$5,I$5) -> 210700.16 | J11: =SUMIFS($AD11:$BT11,$AD$5:$BT$5,J$5) -> 200174.51 | K11: =SUMIFS($AD11:$BT11,$AD$5:$BT$5,K$5) -> 193928.72 | L11: =SUMIFS($AD11:$BT11,$AD$5:$BT$5,L$5) -> 176018.97 | M11: =SUMIFS($AD11:$BT11,$AD$5:$BT$5,M$5) -> 296323.49 | N11: =SUMIFS($AD11:$BT11,$AD$5:$BT$5,N$5) -> 381620.55 | O11: =SUMIFS($AD11:$BT11,$AD$5:$BT$5,O$5) -> 389129.23 | P11: =SUMIFS($AD11:$BT11,$AD$5:$BT$5,P$5) -> 564086.24 | ... V11: =SUMIFS($AD11:$BT11,$AD$5:$BT$5,V$5) -> 925202.28 | W11: =SUMIFS($AD11:$CF11,$AD$5:$CF$5,W$5) -> 1192998.1 | X11: =SUMIFS($AD11:$CF11,$AD$5:$CF$5,X$5) -> 1083652.9 | Y11: =SUMIFS($AD11:$CF11,$AD$5:$CF$5,Y$5) -> 803756.37 | Z11: =SUMIFS($AD11:$CF11,$AD$5:$CF$5,Z$5) -> 961801.53 | AA11: =SUMIFS($AD11:$CL11,$AD$5:$CL$5,AA$5) -> 931449.09 | AB11: =SUMIFS($AD11:$CL11,$AD$5:$CL$5,AB$5) -> 1278841.5 | AD11: ='Industrial ARR Rollforward'!AD11+'Fleet ARR Rollforward'!AD11 -> 26921.853 | AE11: ='Industrial ARR Rollforward'!AE11+'Fleet ARR Rollforward'!AE11 -> 97821.273 | AF11: ='Industrial ARR Rollforward'!AF11+'Fleet ARR Rollforward'!AF11 -> 85957.034 | AG11: ='Industrial ARR Rollforward'!AG11+'Fleet ARR Rollforward'!AG11 -> 62860.023 | AH11: ='Industrial ARR Rollforward'!AH11+'Fleet ARR Rollforward'!AH11 -> 40405.751 | AI11: ='Industrial ARR Rollforward'!AI11+'Fleet ARR Rollforward'!AI11 -> 96908.734 | AJ11: ='Industrial ARR Rollforward'!AJ11+'Fleet ARR Rollforward'!AJ11 -> 35556.547 | AK11: ='Industrial ARR Rollforward'!AK11+'Fleet ARR Rollforward'!AK11 -> 76030.99 | ... CK11: ='Industrial ARR Rollforward'!CK11+'Fleet ARR Rollforward'!CK11 -> 703733.61
B12: (-) Downsell | C12: =SUMIFS($I12:$W12,$I$7:$W$7,C$7) -> -1052015.6 | D12: =+SUM(OFFSET(INDEX($AD12:$CF12,MATCH(D$8,$AD$8:$CF$8,0)),,,,-12)) -> -1059599.2 | E12: =+SUM(OFFSET(INDEX($AD12:$CF12,MATCH(E$8,$AD$8:$CF$8,0)),,,,-12)) -> -1431568.4 | F12: =+SUM(OFFSET(INDEX($AD12:$CF12,MATCH(F$8,$AD$8:$CF$8,0)),,,,-12)) -> -1745938.1 | G12: =+SUM(OFFSET(INDEX($AD12:$CL12,MATCH(G$8,$AD$8:$CL$8,0)),,,,-12)) -> -2572102.5 | I12: =SUMIFS($AD12:$BT12,$AD$5:$BT$5,I$5) -> -166909.06 | J12: =SUMIFS($AD12:$BT12,$AD$5:$BT$5,J$5) -> -247648.93 | K12: =SUMIFS($AD12:$BT12,$AD$5:$BT$5,K$5) -> -279208.16 | L12: =SUMIFS($AD12:$BT12,$AD$5:$BT$5,L$5) -> -358249.43 | M12: =SUMIFS($AD12:$BT12,$AD$5:$BT$5,M$5) -> -232750.12 | N12: =SUMIFS($AD12:$BT12,$AD$5:$BT$5,N$5) -> -269313.16 | O12: =SUMIFS($AD12:$BT12,$AD$5:$BT$5,O$5) -> -248194.16 | P12: =SUMIFS($AD12:$BT12,$AD$5:$BT$5,P$5) -> -309341.75 | ... V12: =SUMIFS($AD12:$BT12,$AD$5:$BT$5,V$5) -> -419609.58 | W12: =SUMIFS($AD12:$CF12,$AD$5:$CF$5,W$5) -> -464105.56 | X12: =SUMIFS($AD12:$CF12,$AD$5:$CF$5,X$5) -> -532318.63 | Y12: =SUMIFS($AD12:$CF12,$AD$5:$CF$5,Y$5) -> -492783.28 | Z12: =SUMIFS($AD12:$CF12,$AD$5:$CF$5,Z$5) -> -832564.65 | AA12: =SUMIFS($AD12:$CL12,$AD$5:$CL$5,AA$5) -> -542240.37 | AB12: =SUMIFS($AD12:$CL12,$AD$5:$CL$5,AB$5) -> -704514.24 | AD12: ='Industrial ARR Rollforward'!AD12+'Fleet ARR Rollforward'!AD12 -> 0 | AE12: ='Industrial ARR Rollforward'!AE12+'Fleet ARR Rollforward'!AE12 -> -86653.692 | AF12: ='Industrial ARR Rollforward'!AF12+'Fleet ARR Rollforward'!AF12 -> -80255.371 | AG12: ='Industrial ARR Rollforward'!AG12+'Fleet ARR Rollforward'!AG12 -> -80670.171 | AH12: ='Industrial ARR Rollforward'!AH12+'Fleet ARR Rollforward'!AH12 -> -83158.802 | AI12: ='Industrial ARR Rollforward'!AI12+'Fleet ARR Rollforward'!AI12 -> -83819.955 | AJ12: ='Industrial ARR Rollforward'!AJ12+'Fleet ARR Rollforward'!AJ12 -> -94771.847 | AK12: ='Industrial ARR Rollforward'!AK12+'Fleet ARR Rollforward'!AK12 -> -79940.719 | ... CK12: ='Industrial ARR Rollforward'!CK12+'Fleet ARR Rollforward'!CK12 -> -219376.25
B13: (-) Churn | C13: =SUMIFS($I13:$W13,$I$7:$W$7,C$7) -> -336836.35 | D13: =+SUM(OFFSET(INDEX($AD13:$CF13,MATCH(D$8,$AD$8:$CF$8,0)),,,,-12)) -> -241267.98 | E13: =+SUM(OFFSET(INDEX($AD13:$CF13,MATCH(E$8,$AD$8:$CF$8,0)),,,,-12)) -> -153594 | F13: =+SUM(OFFSET(INDEX($AD13:$CF13,MATCH(F$8,$AD$8:$CF$8,0)),,,,-12)) -> -266851.46 | G13: =+SUM(OFFSET(INDEX($AD13:$CL13,MATCH(G$8,$AD$8:$CL$8,0)),,,,-12)) -> -431411.92 | I13: =SUMIFS($AD13:$BT13,$AD$5:$BT$5,I$5) -> -133279.02 | J13: =SUMIFS($AD13:$BT13,$AD$5:$BT$5,J$5) -> -97848.237 | K13: =SUMIFS($AD13:$BT13,$AD$5:$BT$5,K$5) -> -23393.674 | L13: =SUMIFS($AD13:$BT13,$AD$5:$BT$5,L$5) -> -82315.421 | M13: =SUMIFS($AD13:$BT13,$AD$5:$BT$5,M$5) -> -89643.649 | N13: =SUMIFS($AD13:$BT13,$AD$5:$BT$5,N$5) -> -34213.632 | O13: =SUMIFS($AD13:$BT13,$AD$5:$BT$5,O$5) -> -68111.496 | P13: =SUMIFS($AD13:$BT13,$AD$5:$BT$5,P$5) -> -49299.206 | ... V13: =SUMIFS($AD13:$BT13,$AD$5:$BT$5,V$5) -> -81980.833 | W13: =SUMIFS($AD13:$CF13,$AD$5:$CF$5,W$5) -> -62722.562 | X13: =SUMIFS($AD13:$CF13,$AD$5:$CF$5,X$5) -> -68212.4 | Y13: =SUMIFS($AD13:$CF13,$AD$5:$CF$5,Y$5) -> -67179.706 | Z13: =SUMIFS($AD13:$CF13,$AD$5:$CF$5,Z$5) -> -108443.86 | AA13: =SUMIFS($AD13:$CL13,$AD$5:$CL$5,AA$5) -> -126511.48 | AB13: =SUMIFS($AD13:$CL13,$AD$5:$CL$5,AB$5) -> -129276.86 | AD13: ='Industrial ARR Rollforward'!AD13+'Fleet ARR Rollforward'!AD13 -> 0 | AE13: ='Industrial ARR Rollforward'!AE13+'Fleet ARR Rollforward'!AE13 -> -59275.933 | AF13: ='Industrial ARR Rollforward'!AF13+'Fleet ARR Rollforward'!AF13 -> -74003.086 | AG13: ='Industrial ARR Rollforward'!AG13+'Fleet ARR Rollforward'!AG13 -> -21446.843 | AH13: ='Industrial ARR Rollforward'!AH13+'Fleet ARR Rollforward'!AH13 -> -24553.26 | AI13: ='Industrial ARR Rollforward'!AI13+'Fleet ARR Rollforward'!AI13 -> -51848.134 | AJ13: ='Industrial ARR Rollforward'!AJ13+'Fleet ARR Rollforward'!AJ13 -> -29631.607 | AK13: ='Industrial ARR Rollforward'!AK13+'Fleet ARR Rollforward'!AK13 -> 25632.697 | ... CK13: ='Industrial ARR Rollforward'!CK13+'Fleet ARR Rollforward'!CK13 -> -65234.183
B14: Ending ARR | C14: =SUM(C9:C13) -> 3507271 | D14: =SUM(D9:D13) -> 5002928.5 | E14: =SUM(E9:E13) -> 8109284.5 | F14: =SUM(F9:F13) -> 12126892 | G14: =SUM(G9:G13) -> 16656622 | I14: =SUM(I9:I13) -> 3495929.7 | J14: =SUM(J9:J13) -> 3452428.7 | K14: =SUM(K9:K13) -> 3577856.3 | L14: =SUM(L9:L13) -> 3507271 | M14: =SUM(M9:M13) -> 3631952.4 | N14: =SUM(N9:N13) -> 4203281.2 | O14: =SUM(O9:O13) -> 4549342.6 | P14: =SUM(P9:P13) -> 5002928.5 | ... AB14: =SUM(AB9:AB13) -> 16656622 | AD14: =SUM(AD9:AD13) -> 3529580 | AE14: =SUM(AE9:AE13) -> 3528617.5 | AF14: =SUM(AF9:AF13) -> 3495929.7 | AG14: =SUM(AG9:AG13) -> 3493397.3 | AH14: =SUM(AH9:AH13) -> 3449599.5 | AI14: =SUM(AI9:AI13) -> 3452428.7 | AJ14: =SUM(AJ9:AJ13) -> 3405075 | AK14: =SUM(AK9:AK13) -> 3496597.2 | ... CK14: =SUM(CK9:CK13) -> 16656622
B15: % YoY Growth | D15: =D14/C14-1 -> 0.4264448 | E15: =E14/D14-1 -> 0.62090752 | F15: =F14/E14-1 -> 0.49543303 | G15: =G14/G9-1 -> 0.37352774 | M15: =M14/I14-1 -> 0.038908854 | N15: =N14/J14-1 -> 0.2174853 | O15: =O14/K14-1 -> 0.27152747 | P15: =P14/L14-1 -> 0.4264448 | Q15: =Q14/M14-1 -> 0.47648599 | R15: =R14/N14-1 -> 0.43537867 | S15: =S14/O14-1 -> 0.57533454 | T15: =T14/P14-1 -> 0.62090752 | ... AB15: =AB14/X14-1 -> 0.37352774 | AP15: =AP14/AD14-1 -> -0.0060375599 | AQ15: =AQ14/AE14-1 -> 0.0016579198 | AR15: =AR14/AF14-1 -> 0.038908854 | AS15: =AS14/AG14-1 -> 0.093750555 | AT15: =AT14/AH14-1 -> 0.1731266 | AU15: =AU14/AI14-1 -> 0.2174853 | AV15: =AV14/AJ14-1 -> 0.27888057 | AW15: =AW14/AK14-1 -> 0.25071161 | ... CK15: =CK14/BY14-1 -> 0.37352774
B17: Gross Retention (c only) | D17: =1+D13/D9 -> 0.9312092 | E17: =1+E13/E9 -> 0.96929918 | F17: =1+F13/F9 -> 0.96709309 | G17: =1+G13/G9 -> 0.96442519 | J17: =1+J13*4/J9 -> 0.88804325 | K17: =1+K13*4/K9 -> 0.97289598 | L17: =1+L13*4/L9 -> 0.90797236 | M17: =1+M13*4/M9 -> 0.89776251 | N17: =1+N13*4/N9 -> 0.96231929 | O17: =1+O13*4/O9 -> 0.93518255 | P17: =1+P13*4/P9 -> 0.95665378 | Q17: =1+Q13*4/Q9 -> 0.99036981 | ... AB17: =1+AB13*4/AB9 -> 0.96614283 | AE17: =1+AE13*12/AE9 -> 0.79847144 | AF17: =1+AF13*12/AF9 -> 0.74833287 | AG17: =1+AG13*12/AG9 -> 0.92638235 | AH17: =1+AH13*12/AH9 -> 0.91565828 | AI17: =1+AI13*12/AI9 -> 0.81963773 | AJ17: =1+AJ13*12/AJ9 -> 0.89700605 | AK17: =1+AK13*12/AK9 -> 1.0903335 | AL17: =1+AL13*12/AL9 -> 0.93343895 | ... CK17: =1+CK13*12/CK9 -> 0.94987468
B18: Gross Retention (c + d) | D18: =1+SUM(D12:D13)/D9 -> 0.6290942 | E18: =1+SUM(E12:E13)/E9 -> 0.68315311 | F18: =1+SUM(F12:F13)/F9 -> 0.75179196 | G18: =1+SUM(G12:G13)/G9 -> 0.75232611 | J18: =1+SUM(J12:J13)*4/J9 -> 0.60468638 | K18: =1+SUM(K12:K13)*4/K9 -> 0.64940411 | L18: =1+SUM(L12:L13)*4/L9 -> 0.50745384 | M18: =1+SUM(M12:M13)*4/M9 -> 0.63231383 | N18: =1+SUM(N12:N13)*4/N9 -> 0.665715 | O18: =1+SUM(O12:O13)*4/O9 -> 0.69899168 | P18: =1+SUM(P12:P13)*4/P9 -> 0.68466568 | Q18: =1+SUM(Q12:Q13)*4/Q9 -> 0.68589102 | ... AB18: =1+SUM(AB12:AB13)*4/AB9 -> 0.78163297 | AE18: =1+SUM(AE12:AE13)*12/AE9 -> 0.50386293 | AF18: =1+SUM(AF12:AF13)*12/AF9 -> 0.47540318 | AG18: =1+SUM(AG12:AG13)*12/AG9 -> 0.64947689 | AH18: =1+SUM(AH12:AH13)*12/AH9 -> 0.63000351 | AI18: =1+SUM(AI12:AI13)*12/AI9 -> 0.52805621 | AJ18: =1+SUM(AJ12:AJ13)*12/AJ9 -> 0.56759674 | AK18: =1+SUM(AK12:AK13)*12/AK9 -> 0.80861031 | AL18: =1+SUM(AL12:AL13)*12/AL9 -> 0.57481968 | ... CK18: =1+SUM(CK12:CK13)*12/CK9 -> 0.78130806
B19: Net Retention | D19: =1+SUM(D11:D13)/D9 -> 1.0941736 | E19: =1+SUM(E11:E13)/E9 -> 1.2302993 | F19: =1+SUM(F11:F13)/F9 -> 1.2532045 | G19: =1+SUM(G11:G13)/G9 -> 1.08018 | J19: =1+SUM(J11:J13)*4/J9 -> 0.8337236 | K19: =1+SUM(K11:K13)*4/K9 -> 0.87409083 | L19: =1+SUM(L11:L13)*4/L9 -> 0.70424091 | M19: =1+SUM(M11:M13)*4/M9 -> 0.97026717 | N19: =1+SUM(N11:N13)*4/N9 -> 1.0860075 | O19: =1+SUM(O11:O13)*4/O9 -> 1.0693016 | P19: =1+SUM(P11:P13)*4/P9 -> 1.1806373 | Q19: =1+SUM(Q11:Q13)*4/Q9 -> 1.0127338 | ... AB19: =1+SUM(AB11:AB13)*4/AB9 -> 1.1165572 | AE19: =1+SUM(AE11:AE13)*12/AE9 -> 0.8364394 | AF19: =1+SUM(AF11:AF13)*12/AF9 -> 0.76772289 | AG19: =1+SUM(AG11:AG13)*12/AG9 -> 0.8652479 | AH19: =1+SUM(AH11:AH13)*12/AH9 -> 0.76879935 | AI19: =1+SUM(AI11:AI13)*12/AI9 -> 0.8651692 | AJ19: =1+SUM(AJ11:AJ13)*12/AJ9 -> 0.69118468 | AK19: =1+SUM(AK11:AK13)*12/AK9 -> 1.076555 | AL19: =1+SUM(AL11:AL13)*12/AL9 -> 0.85740706 | ... CK19: =1+SUM(CK11:CK13)*12/CK9 -> 1.3220502
B21: Net New ARR | C21: =SUM(C10:C13) -> 2792132.1 | D21: =SUM(D10:D13) -> 1495657.5 | E21: =SUM(E10:E13) -> 3106355.9 | F21: =SUM(F10:F13) -> 4017607.4 | G21: =SUM(G10:G13) -> 4529730.5 | I21: =SUM(I10:I13) -> 2780790.8 | J21: =SUM(J10:J13) -> -43501.015 | K21: =SUM(K10:K13) -> 125427.56 | L21: =SUM(L10:L13) -> -70585.261 | M21: =SUM(M10:M13) -> 124681.33 | N21: =SUM(N10:N13) -> 571328.85 | O21: =SUM(O10:O13) -> 346061.35 | P21: =SUM(P10:P13) -> 453585.96 | ... AB21: =SUM(AB10:AB13) -> 1383417.4 | AD21: =SUM(AD10:AD13) -> 2814441.1 | AE21: =SUM(AE10:AE13) -> -962.54568 | AF21: =SUM(AF10:AF13) -> -32687.728 | AG21: =SUM(AG10:AG13) -> -2532.4328 | AH21: =SUM(AH10:AH13) -> -43797.828 | AI21: =SUM(AI10:AI13) -> 2829.2464 | AJ21: =SUM(AJ10:AJ13) -> -47353.713 | AK21: =SUM(AK10:AK13) -> 91522.205 | ... CK21: =SUM(CK10:CK13) -> 1039561.8
B22: New + Upsell | C22: =SUM(C10:C11) -> 4180984 | D22: =SUM(D10:D11) -> 2796524.7 | E22: =SUM(E10:E11) -> 4691518.3 | F22: =SUM(F10:F11) -> 6030396.9 | G22: =SUM(G10:G11) -> 7533244.9 | I22: =SUM(I10:I11) -> 3080978.9 | J22: =SUM(J10:J11) -> 301996.15 | K22: =SUM(K10:K11) -> 428029.4 | L22: =SUM(L10:L11) -> 369979.59 | M22: =SUM(M10:M11) -> 447075.1 | N22: =SUM(N10:N11) -> 874855.65 | O22: =SUM(O10:O11) -> 662367.01 | P22: =SUM(P10:P11) -> 812226.92 | ... AB22: =SUM(AB10:AB11) -> 2217208.5 | AD22: =SUM(AD10:AD11) -> 2814441.1 | AE22: =SUM(AE10:AE11) -> 144967.08 | AF22: =SUM(AF10:AF11) -> 121570.73 | AG22: =SUM(AG10:AG11) -> 99584.581 | AH22: =SUM(AH10:AH11) -> 63914.233 | AI22: =SUM(AI10:AI11) -> 138497.34 | AJ22: =SUM(AJ10:AJ11) -> 77049.741 | AK22: =SUM(AK10:AK11) -> 145830.23 | ... CK22: =SUM(CK10:CK11) -> 1324172.2
B24: Customer Count
B25: Beginning Logos | C25: =I25 -> 25 | D25: =C28 -> 9604 | E25: =D28 -> 10605 | F25: =E28 -> 11462 | G25: =+SUMIFS($AD$28:$CL$28,$AD$8:$CL$8,EOMONTH(G8,-12)) -> 12072 | I25: =AD25 -> 25 | J25: =I28 -> 8903 | K25: =J28 -> 8977 | L25: =K28 -> 9254 | M25: =L28 -> 9604 | N25: =M28 -> 9825 | O25: =N28 -> 10242 | P25: =O28 -> 10420 | Q25: =P28 -> 10605 | ... AB25: =AA28 -> 12217 | AD25: ='Industrial ARR Rollforward'!AD25+'Fleet ARR Rollforward'!AD25 -> 25 | AE25: ='Industrial ARR Rollforward'!AE25+'Fleet ARR Rollforward'!AE25 -> 8886 | AF25: ='Industrial ARR Rollforward'!AF25+'Fleet ARR Rollforward'!AF25 -> 8876 | AG25: ='Industrial ARR Rollforward'!AG25+'Fleet ARR Rollforward'!AG25 -> 8903 | AH25: ='Industrial ARR Rollforward'!AH25+'Fleet ARR Rollforward'!AH25 -> 8913 | AI25: ='Industrial ARR Rollforward'!AI25+'Fleet ARR Rollforward'!AI25 -> 8897 | AJ25: ='Industrial ARR Rollforward'!AJ25+'Fleet ARR Rollforward'!AJ25 -> 8977 | AK25: ='Industrial ARR Rollforward'!AK25+'Fleet ARR Rollforward'!AK25 -> 8978 | ... CK25: ='Industrial ARR Rollforward'!CK25+'Fleet ARR Rollforward'!CK25 -> 12206
B26: (+) New | C26: =SUMIFS($I26:$W26,$I$7:$W$7,C$7) -> 11058 | D26: =SUMIFS($I26:$W26,$I$7:$W$7,D$7) -> 2296 | E26: =SUMIFS($I26:$W26,$I$7:$W$7,E$7) -> 2230 | F26: =SUMIFS($I26:$AC26,$I$7:$AC$7,F$7) -> 2898 | G26: =+SUM(OFFSET(INDEX($AD26:$CL26,MATCH(G$8,$AD$8:$CL$8,0)),,,,-12)) -> 3156 | I26: =SUMIFS($AD26:$BT26,$AD$5:$BT$5,I$5) -> 9184 | J26: =SUMIFS($AD26:$BT26,$AD$5:$BT$5,J$5) -> 446 | K26: =SUMIFS($AD26:$BT26,$AD$5:$BT$5,K$5) -> 696 | L26: =SUMIFS($AD26:$BT26,$AD$5:$BT$5,L$5) -> 732 | M26: =SUMIFS($AD26:$BT26,$AD$5:$BT$5,M$5) -> 559 | N26: =SUMIFS($AD26:$BT26,$AD$5:$BT$5,N$5) -> 666 | O26: =SUMIFS($AD26:$BT26,$AD$5:$BT$5,O$5) -> 550 | P26: =SUMIFS($AD26:$BT26,$AD$5:$BT$5,P$5) -> 521 | ... V26: =SUMIFS($AD26:$BT26,$AD$5:$BT$5,V$5) -> 680 | W26: =SUMIFS($AD26:$CF26,$AD$5:$CF$5,W$5) -> 703 | X26: =SUMIFS($AD26:$CF26,$AD$5:$CF$5,X$5) -> 799 | Y26: =SUMIFS($AD26:$CF26,$AD$5:$CF$5,Y$5) -> 689 | Z26: =SUMIFS($AD26:$CF26,$AD$5:$CF$5,Z$5) -> 744 | AA26: =SUMIFS($AD26:$CL26,$AD$5:$CL$5,AA$5) -> 838 | AB26: =SUMIFS($AD26:$CL26,$AD$5:$CL$5,AB$5) -> 885 | AD26: ='Industrial ARR Rollforward'!AD26+'Fleet ARR Rollforward'!AD26 -> 8861 | AE26: ='Industrial ARR Rollforward'!AE26+'Fleet ARR Rollforward'!AE26 -> 152 | AF26: ='Industrial ARR Rollforward'!AF26+'Fleet ARR Rollforward'!AF26 -> 171 | AG26: ='Industrial ARR Rollforward'!AG26+'Fleet ARR Rollforward'!AG26 -> 146 | AH26: ='Industrial ARR Rollforward'!AH26+'Fleet ARR Rollforward'!AH26 -> 103 | AI26: ='Industrial ARR Rollforward'!AI26+'Fleet ARR Rollforward'!AI26 -> 197 | AJ26: ='Industrial ARR Rollforward'!AJ26+'Fleet ARR Rollforward'!AJ26 -> 166 | AK26: ='Industrial ARR Rollforward'!AK26+'Fleet ARR Rollforward'!AK26 -> 222 | ... CK26: ='Industrial ARR Rollforward'!CK26+'Fleet ARR Rollforward'!CK26 -> 294
B27: (-) Cancel | C27: =SUMIFS($I27:$W27,$I$7:$W$7,C$7) -> -1479 | D27: =SUMIFS($I27:$W27,$I$7:$W$7,D$7) -> -1295 | E27: =SUMIFS($I27:$W27,$I$7:$W$7,E$7) -> -1373 | F27: =SUMIFS($I27:$AC27,$I$7:$AC$7,F$7) -> -2288 | G27: =+SUM(OFFSET(INDEX($AD27:$CL27,MATCH(G$8,$AD$8:$CL$8,0)),,,,-12)) -> -3021 | I27: =SUMIFS($AD27:$BT27,$AD$5:$BT$5,I$5) -> -306 | J27: =SUMIFS($AD27:$BT27,$AD$5:$BT$5,J$5) -> -372 | K27: =SUMIFS($AD27:$BT27,$AD$5:$BT$5,K$5) -> -419 | L27: =SUMIFS($AD27:$BT27,$AD$5:$BT$5,L$5) -> -382 | M27: =SUMIFS($AD27:$BT27,$AD$5:$BT$5,M$5) -> -338 | N27: =SUMIFS($AD27:$BT27,$AD$5:$BT$5,N$5) -> -249 | O27: =SUMIFS($AD27:$BT27,$AD$5:$BT$5,O$5) -> -372 | P27: =SUMIFS($AD27:$BT27,$AD$5:$BT$5,P$5) -> -336 | ... V27: =SUMIFS($AD27:$BT27,$AD$5:$BT$5,V$5) -> -460 | W27: =SUMIFS($AD27:$CF27,$AD$5:$CF$5,W$5) -> -648 | X27: =SUMIFS($AD27:$CF27,$AD$5:$CF$5,X$5) -> -797 | Y27: =SUMIFS($AD27:$CF27,$AD$5:$CF$5,Y$5) -> -723 | Z27: =SUMIFS($AD27:$CF27,$AD$5:$CF$5,Z$5) -> -642 | AA27: =SUMIFS($AD27:$CL27,$AD$5:$CL$5,AA$5) -> -761 | AB27: =SUMIFS($AD27:$CL27,$AD$5:$CL$5,AB$5) -> -895 | AD27: ='Industrial ARR Rollforward'!AD27+'Fleet ARR Rollforward'!AD27 -> 0 | AE27: ='Industrial ARR Rollforward'!AE27+'Fleet ARR Rollforward'!AE27 -> -162 | AF27: ='Industrial ARR Rollforward'!AF27+'Fleet ARR Rollforward'!AF27 -> -144 | AG27: ='Industrial ARR Rollforward'!AG27+'Fleet ARR Rollforward'!AG27 -> -136 | AH27: ='Industrial ARR Rollforward'!AH27+'Fleet ARR Rollforward'!AH27 -> -119 | AI27: ='Industrial ARR Rollforward'!AI27+'Fleet ARR Rollforward'!AI27 -> -117 | AJ27: ='Industrial ARR Rollforward'!AJ27+'Fleet ARR Rollforward'!AJ27 -> -165 | AK27: ='Industrial ARR Rollforward'!AK27+'Fleet ARR Rollforward'!AK27 -> -121 | ... CK27: ='Industrial ARR Rollforward'!CK27+'Fleet ARR Rollforward'!CK27 -> -293
B28: Ending Logos | C28: =SUM(C25:C27) -> 9604 | D28: =SUM(D25:D27) -> 10605 | E28: =SUM(E25:E27) -> 11462 | F28: =SUM(F25:F27) -> 12072 | G28: =SUM(G25:G27) -> 12207 | I28: =SUM(I25:I27) -> 8903 | J28: =SUM(J25:J27) -> 8977 | K28: =SUM(K25:K27) -> 9254 | L28: =SUM(L25:L27) -> 9604 | M28: =SUM(M25:M27) -> 9825 | N28: =SUM(N25:N27) -> 10242 | O28: =SUM(O25:O27) -> 10420 | P28: =SUM(P25:P27) -> 10605 | ... AB28: =SUM(AB25:AB27) -> 12207 | AD28: =SUM(AD25:AD27) -> 8886 | AE28: =SUM(AE25:AE27) -> 8876 | AF28: =SUM(AF25:AF27) -> 8903 | AG28: =SUM(AG25:AG27) -> 8913 | AH28: =SUM(AH25:AH27) -> 8897 | AI28: =SUM(AI25:AI27) -> 8977 | AJ28: =SUM(AJ25:AJ27) -> 8978 | AK28: =SUM(AK25:AK27) -> 9079 | ... CK28: =SUM(CK25:CK27) -> 12207
B30: Logo Retention | C30: =1+C27/C28 -> 0.84600167 | D30: =1+D27/D28 -> 0.87788779 | E30: =1+E27/E28 -> 0.88021288 | F30: =1+F27/F28 -> 0.81047051 | G30: =1+G27/G28 -> 0.75251905 | J30: =1+J27*4/J25 -> 0.83286533 | K30: =1+K27*4/K25 -> 0.81330066 | L30: =1+L27*4/L25 -> 0.83488221 | M30: =1+M27*4/M25 -> 0.85922532 | N30: =1+N27*4/N25 -> 0.89862595 | O30: =1+O27*4/O25 -> 0.85471588 | P30: =1+P27*4/P25 -> 0.87101727 | Q30: =1+Q27*4/Q25 -> 0.87854785 | ... AB30: =1+AB27*4/AB25 -> 0.7069657 | AE30: =1+AE27*12/AE25 -> 0.7812289 | AF30: =1+AF27*12/AF25 -> 0.80531771 | AG30: =1+AG27*12/AG25 -> 0.816691 | AH30: =1+AH27*12/AH25 -> 0.83978458 | AI30: =1+AI27*12/AI25 -> 0.842194 | AJ30: =1+AJ27*12/AJ25 -> 0.77943634 | AK30: =1+AK27*12/AK25 -> 0.83827133 | AL30: =1+AL27*12/AL25 -> 0.82420971 | ... CK30: =1+CK27*12/CK25 -> 0.71194495
B32: Avg. ARR / Cust | C32: =C14/C28 -> 365.18857 | D32: =D14/D28 -> 471.75187 | E32: =E14/E28 -> 707.49297 | F32: =F14/F28 -> 1004.547 | G32: =G14/G28 -> 1364.514 | I32: =I14/I28 -> 392.66873 | J32: =J14/J28 -> 384.58602 | K32: =K14/K28 -> 386.62808 | L32: =L14/L28 -> 365.18857 | M32: =M14/M28 -> 369.66436 | N32: =N14/N28 -> 410.39653 | O32: =O14/O28 -> 436.59718 | P32: =P14/P28 -> 471.75187 | ... AB32: =AB14/AB28 -> 1364.514 | AE32: =AE14/AE28 -> 397.54591 | AF32: =AF14/AF28 -> 392.66873 | AG32: =AG14/AG28 -> 391.94405 | AH32: =AH14/AH28 -> 387.72614 | AI32: =AI14/AI28 -> 384.58602 | AJ32: =AJ14/AJ28 -> 379.26877 | AK32: =AK14/AK28 -> 385.13022 | AL32: =AL14/AL28 -> 386.62808 | ... CK32: =CK14/CK28 -> 1364.514
B33: Avg. ARR / New | C33: =C10/C26 -> 307.48433 | D33: =D10/D26 -> 507.56323 | E33: =E10/E26 -> 876.31614 | F33: =F10/F26 -> 677.81231 | G33: =G10/G26 -> 1127.1852 | I33: =I10/I26 -> 312.53035 | J33: =J10/J26 -> 228.29965 | K33: =K10/K26 -> 336.35154 | L33: =L10/L26 -> 264.97353 | M33: =M10/M26 -> 269.68088 | N33: =N10/N26 -> 740.59324 | O33: =O10/O26 -> 496.79596 | P33: =P10/P26 -> 476.2777 | ... AB33: =AB10/AB26 -> 1060.3017 | AE33: =AE10/AE26 -> 310.16978 | AF33: =AF10/AF26 -> 208.26723 | AG33: =AG10/AG26 -> 251.53807 | AH33: =AH10/AH26 -> 228.23769 | AI33: =AI10/AI26 -> 211.10965 | AJ33: =AJ10/AJ26 -> 249.959 | AK33: =AK10/AK26 -> 314.41098 | AL33: =AL10/AL26 -> 398.72807 | ... CK33: =CK10/CK26 -> 2110.3353
B34: Avg. ARR / Churn | C34: =IFERROR(C13/C27,"NA") -> 227.74601 | D34: =IFERROR(D13/D27,"NA") -> 186.30732 | E34: =IFERROR(E13/E27,"NA") -> 111.86745 | F34: =IFERROR(F13/F27,"NA") -> 116.63088 | G34: =IFERROR(G13/G27,"NA") -> 142.80434 | I34: =IFERROR(I13/I27,"NA") -> 435.55235 | J34: =IFERROR(J13/J27,"NA") -> 263.03289 | K34: =IFERROR(K13/K27,"NA") -> 55.832157 | L34: =IFERROR(L13/L27,"NA") -> 215.48539 | M34: =IFERROR(M13/M27,"NA") -> 265.2179 | N34: =IFERROR(N13/N27,"NA") -> 137.40415 | O34: =IFERROR(O13/O27,"NA") -> 183.09542 | P34: =IFERROR(P13/P27,"NA") -> 146.72383 | ... AB34: =IFERROR(AB13/AB27,"NA") -> 144.44342 | AE34: =IFERROR(AE13/AE27,"NA") -> 365.90082 | AF34: =IFERROR(AF13/AF27,"NA") -> 513.91032 | AG34: =IFERROR(AG13/AG27,"NA") -> 157.69738 | AH34: =IFERROR(AH13/AH27,"NA") -> 206.32992 | AI34: =IFERROR(AI13/AI27,"NA") -> 443.14644 | AJ34: =IFERROR(AJ13/AJ27,"NA") -> 179.58549 | AK34: =IFERROR(AK13/AK27,"NA") -> -211.84047 | AL34: =IFERROR(AL13/AL27,"NA") -> 145.82529 | ... CK34: =IFERROR(CK13/CK27,"NA") -> 222.64226
C36: =C37&" " &YEAR(C39) -> Q4 2021 | D36: =D37&" " &YEAR(D39) -> Q4 2022 | E36: =E37&" " &YEAR(E39) -> Q4 2023 | F36: =F37&" " &YEAR(F39) -> Q4 2024 | G36: =G37&" " &YEAR(G39) -> TTM 2025 | I36: =I37&" " &YEAR(I39) -> Q1 2021 | J36: =J37&" " &YEAR(J39) -> Q2 2021 | K36: =K37&" " &YEAR(K39) -> Q3 2021 | L36: =L37&" " &YEAR(L39) -> Q4 2021 | M36: =M37&" " &YEAR(M39) -> Q1 2022 | N36: =N37&" " &YEAR(N39) -> Q2 2022 | O36: =O37&" " &YEAR(O39) -> Q3 2022 | P36: =P37&" " &YEAR(P39) -> Q4 2022 | ... AB36: =AB37&" " &YEAR(AB39) -> Q4 2025 | AD36: =AD37&" " &YEAR(AD39) -> Q1 2021 | AE36: =AE37&" " &YEAR(AE39) -> Q1 2021 | AF36: =AF37&" " &YEAR(AF39) -> Q1 2021 | AG36: =AG37&" " &YEAR(AG39) -> Q2 2021 | AH36: =AH37&" " &YEAR(AH39) -> Q2 2021 | AI36: =AI37&" " &YEAR(AI39) -> Q2 2021 | AJ36: =AJ37&" " &YEAR(AJ39) -> Q3 2021 | AK36: =AK37&" " &YEAR(AK39) -> Q3 2021 | ... CK36: =CK37&" " &YEAR(CK39) -> Q4 2025
C37: Q4 | D37: Q4 | E37: Q4 | F37: Q4 | G37: TTM | I37: =+I6 -> Q1 | J37: =+J6 -> Q2 | K37: =+K6 -> Q3 | L37: =+L6 -> Q4 | M37: =+M6 -> Q1 | N37: =+N6 -> Q2 | O37: =+O6 -> Q3 | P37: =+P6 -> Q4 | ... AB37: =+AB6 -> Q4 | AD37: =+AD6 -> Q1 | AE37: =+AE6 -> Q1 | AF37: =+AF6 -> Q1 | AG37: =+AG6 -> Q2 | AH37: =+AH6 -> Q2 | AI37: =+AI6 -> Q2 | AJ37: =+AJ6 -> Q3 | AK37: =+AK6 -> Q3 | ... CK37: =+CK6 -> Q4
C38: =YEAR(C39) -> 2021 | D38: =YEAR(D39) -> 2022 | E38: =YEAR(E39) -> 2023 | F38: =YEAR(F39) -> 2024 | G38: =YEAR(G39) -> 2025 | I38: =+I7 -> 2021 | J38: =+J7 -> 2021 | K38: =+K7 -> 2021 | L38: =+L7 -> 2021 | M38: =+M7 -> 2022 | N38: =+N7 -> 2022 | O38: =+O7 -> 2022 | P38: =+P7 -> 2022 | ... AB38: =+AB7 -> 2025 | AD38: =+AD7 -> 2021 | AE38: =+AE7 -> 2021 | AF38: =+AF7 -> 2021 | AG38: =+AG7 -> 2021 | AH38: =+AH7 -> 2021 | AI38: =+AI7 -> 2021 | AJ38: =+AJ7 -> 2021 | AK38: =+AK7 -> 2021 | ... CK38: =+CK7 -> 2025
B39: Consolidated Sales Efficiency | C39: =+C8 -> 44561 | D39: =+D8 -> 44926 | E39: =+E8 -> 45291 | F39: =+F8 -> 45657 | G39: =+G8 -> 46022 | I39: =+I8 -> 44286 | J39: =+J8 -> 44377 | K39: =+K8 -> 44469 | L39: =+L8 -> 44561 | M39: =+M8 -> 44651 | N39: =+N8 -> 44742 | O39: =+O8 -> 44834 | P39: =+P8 -> 44926 | ... AB39: =+AB8 -> 46022 | AD39: =+AD8 -> 44227 | AE39: =+AE8 -> 44255 | AF39: =+AF8 -> 44286 | AG39: =+AG8 -> 44316 | AH39: =+AH8 -> 44347 | AI39: =+AI8 -> 44377 | AJ39: =+AJ8 -> 44408 | AK39: =+AK8 -> 44439 | ... CK39: =+CK8 -> 46022
B41: Customer Lifetime Value
B42: New + Upsell | C42: =SUM(C10:C11) -> 4180984 | D42: =SUM(D10:D11) -> 2796524.7 | E42: =SUM(E10:E11) -> 4691518.3 | F42: =SUM(F10:F11) -> 6030396.9 | G42: =SUM(G10:G11) -> 7533244.9 | I42: =SUM(I10:I11) -> 3080978.9 | J42: =SUM(J10:J11) -> 301996.15 | K42: =SUM(K10:K11) -> 428029.4 | L42: =SUM(L10:L11) -> 369979.59 | M42: =SUM(M10:M11) -> 447075.1 | N42: =SUM(N10:N11) -> 874855.65 | O42: =SUM(O10:O11) -> 662367.01 | P42: =SUM(P10:P11) -> 812226.92 | ... AB42: =SUM(AB10:AB11) -> 2217208.5 | AD42: =SUM(AD10:AD11) -> 2814441.1 | AE42: =SUM(AE10:AE11) -> 144967.08 | AF42: =SUM(AF10:AF11) -> 121570.73 | AG42: =SUM(AG10:AG11) -> 99584.581 | AH42: =SUM(AH10:AH11) -> 63914.233 | AI42: =SUM(AI10:AI11) -> 138497.34 | AJ42: =SUM(AJ10:AJ11) -> 77049.741 | AK42: =SUM(AK10:AK11) -> 145830.23 | ... CK42: =SUM(CK10:CK11) -> 1324172.2
B43: Gross Margin | C43: 0.7049489 | D43: =+'Industrial ARR Rollforward'!D43 -> 0.72510895 | E43: =+'Industrial ARR Rollforward'!E43 -> 0.75651534 | F43: =+'Industrial ARR Rollforward'!F43 -> 0.77942405 | G43: =+'Industrial ARR Rollforward'!G43 -> 0.75533729 | I43: =AVERAGEIFS($AD43:$BT43,$AD$36:$BT$36,I$36) -> 0.70331208 | J43: =AVERAGEIFS($AD43:$BT43,$AD$36:$BT$36,J$36) -> 0.75287296 | K43: =AVERAGEIFS($AD43:$BT43,$AD$36:$BT$36,K$36) -> 0.73170588 | L43: =AVERAGEIFS($AD43:$BT43,$AD$36:$BT$36,L$36) -> 0.76169227 | M43: =AVERAGEIFS($AD43:$BT43,$AD$36:$BT$36,M$36) -> 0.72432258 | N43: =AVERAGEIFS($AD43:$BT43,$AD$36:$BT$36,N$36) -> 0.70519993 | O43: =AVERAGEIFS($AD43:$BT43,$AD$36:$BT$36,O$36) -> 0.72702076 | P43: =AVERAGEIFS($AD43:$BT43,$AD$36:$BT$36,P$36) -> 0.73995139 | ... V43: =AVERAGEIFS($AD43:$BT43,$AD$36:$BT$36,V$36) -> 0.78066093 | W43: =AVERAGEIFS($AD43:$CF43,$AD$36:$CF$36,W$36) -> 0.77526965 | X43: =AVERAGEIFS($AD43:$CF43,$AD$36:$CF$36,X$36) -> 0.78768385 | Y43: =AVERAGEIFS($AD43:$CF43,$AD$36:$CF$36,Y$36) -> 0.76892265 | Z43: =AVERAGEIFS($AD43:$CF43,$AD$36:$CF$36,Z$36) -> 0.75446338 | AA43: =AVERAGEIFS($AD43:$CL43,$AD$36:$CL$36,AA$36) -> 0.75623831 | AB43: =AVERAGEIFS($AD43:$CL43,$AD$36:$CL$36,AB$36) -> 0.74171109 | AD43: =+'Cons TrioMobil | Monthly'!O24 -> 0.66228422 | AE43: =+'Cons TrioMobil | Monthly'!P24 -> 0.72075982 | AF43: =+'Cons TrioMobil | Monthly'!Q24 -> 0.72689219 | AG43: =+'Cons TrioMobil | Monthly'!R24 -> 0.78612543 | AH43: =+'Cons TrioMobil | Monthly'!S24 -> 0.74211799 | AI43: =+'Cons TrioMobil | Monthly'!T24 -> 0.73037545 | AJ43: =+'Cons TrioMobil | Monthly'!U24 -> 0.7471152 | AK43: =+'Cons TrioMobil | Monthly'!V24 -> 0.6971837 | ... CK43: =+'Cons TrioMobil | Monthly'!BV24 -> 0.72957513
B44: Gross Profit | C44: =C43*C42 -> 2947380.1 | D44: =D43*D42 -> 2027785.1 | E44: =E43*E42 -> 3549205.6 | F44: =F43*F42 -> 4700236.4 | G44: =G43*G42 -> 5690140.8 | I44: =I43*I42 -> 2166889.7 | J44: =J43*J42 -> 227364.73 | K44: =K43*K42 -> 313191.63 | L44: =L43*L42 -> 281810.59 | M44: =M43*M42 -> 323826.59 | N44: =N43*N42 -> 616948.15 | O44: =O43*O42 -> 481554.57 | P44: =P43*P42 -> 601008.44 | ... AB44: =AB43*AB42 -> 1644528.2 | AD44: =AD43*AD42 -> 1863959.9 | AE44: =AE43*AE42 -> 104486.45 | AF44: =AF43*AF42 -> 88368.814 | AG44: =AG43*AG42 -> 78285.972 | AH44: =AH43*AH42 -> 47431.902 | AI44: =AI43*AI42 -> 101155.05 | AJ44: =AJ43*AJ42 -> 57565.033 | AK44: =AK43*AK42 -> 101670.46 | ... CK44: =CK43*CK42 -> 966083.1
B46: Logo Retention | C46: =C30 -> 0.84600167 | D46: =D30 -> 0.87788779 | E46: =E30 -> 0.88021288 | F46: =F30 -> 0.81047051 | G46: =G30 -> 0.75251905 | J46: =J30 -> 0.83286533 | K46: =K30 -> 0.81330066 | L46: =L30 -> 0.83488221 | M46: =M30 -> 0.85922532 | N46: =N30 -> 0.89862595 | O46: =O30 -> 0.85471588 | P46: =P30 -> 0.87101727 | Q46: =Q30 -> 0.87854785 | ... AB46: =AB30 -> 0.7069657 | AE46: =AE30 -> 0.7812289 | AF46: =AF30 -> 0.80531771 | AG46: =AG30 -> 0.816691 | AH46: =AH30 -> 0.83978458 | AI46: =AI30 -> 0.842194 | AJ46: =AJ30 -> 0.77943634 | AK46: =AK30 -> 0.83827133 | AL46: =AL30 -> 0.82420971 | ... CK46: =CK30 -> 0.71194495
B47: Implied Customer Years (Calculated) | C47: =IF(C46=100%,100,IFERROR(1/(1-C46),"NA")) -> 6.4935767 | D47: =IF(D46=100%,100,IFERROR(1/(1-D46),"NA")) -> 8.1891892 | E47: =IF(E46=100%,100,IFERROR(1/(1-E46),"NA")) -> 8.3481428 | F47: =IF(F46=100%,100,IFERROR(1/(1-F46),"NA")) -> 5.2762238 | G47: =IF(G46=100%,100,IFERROR(1/(1-G46),"NA")) -> 4.040715 | J47: =IF(J46=100%,100,IFERROR(1/(1-J46),"NA")) -> 5.9831989 | K47: =IF(K46=100%,100,IFERROR(1/(1-K46),"NA")) -> 5.3562053 | L47: =IF(L46=100%,100,IFERROR(1/(1-L46),"NA")) -> 6.0562827 | M47: =IF(M46=100%,100,IFERROR(1/(1-M46),"NA")) -> 7.1035503 | N47: =IF(N46=100%,100,IFERROR(1/(1-N46),"NA")) -> 9.8644578 | O47: =IF(O46=100%,100,IFERROR(1/(1-O46),"NA")) -> 6.8830645 | P47: =IF(P46=100%,100,IFERROR(1/(1-P46),"NA")) -> 7.7529762 | Q47: =IF(Q46=100%,100,IFERROR(1/(1-Q46),"NA")) -> 8.2336957 | ... AB47: =IF(AB46=100%,100,IFERROR(1/(1-AB46),"NA")) -> 3.4125698 | AE47: =IF(AE46=100%,100,IFERROR(1/(1-AE46),"NA")) -> 4.5709877 | AF47: =IF(AF46=100%,100,IFERROR(1/(1-AF46),"NA")) -> 5.1365741 | AG47: =IF(AG46=100%,100,IFERROR(1/(1-AG46),"NA")) -> 5.4552696 | AH47: =IF(AH46=100%,100,IFERROR(1/(1-AH46),"NA")) -> 6.2415966 | AI47: =IF(AI46=100%,100,IFERROR(1/(1-AI46),"NA")) -> 6.3368946 | AJ47: =IF(AJ46=100%,100,IFERROR(1/(1-AJ46),"NA")) -> 4.5338384 | AK47: =IF(AK46=100%,100,IFERROR(1/(1-AK46),"NA")) -> 6.1831956 | AL47: =IF(AL46=100%,100,IFERROR(1/(1-AL46),"NA")) -> 5.6885965 | ... CK47: =IF(CK46=100%,100,IFERROR(1/(1-CK46),"NA")) -> 3.4715586
B48: Implied Customer Years (Capped) | C48: =MIN(C47,5) -> 5 | D48: =MIN(D47,5) -> 5 | E48: =MIN(E47,5) -> 5 | F48: =MIN(F47,5) -> 5 | G48: =MIN(G47,5) -> 4.040715 | J48: =MIN(J47,5) -> 5 | K48: =MIN(K47,5) -> 5 | L48: =MIN(L47,5) -> 5 | M48: =MIN(M47,5) -> 5 | N48: =MIN(N47,5) -> 5 | O48: =MIN(O47,5) -> 5 | P48: =MIN(P47,5) -> 5 | Q48: =MIN(Q47,5) -> 5 | ... AB48: =MIN(AB47,5) -> 3.4125698 | AE48: =MIN(AE47,5) -> 4.5709877 | AF48: =MIN(AF47,5) -> 5 | AG48: =MIN(AG47,5) -> 5 | AH48: =MIN(AH47,5) -> 5 | AI48: =MIN(AI47,5) -> 5 | AJ48: =MIN(AJ47,5) -> 4.5338384 | AK48: =MIN(AK47,5) -> 5 | AL48: =MIN(AL47,5) -> 5 | ... CK48: =MIN(CK47,5) -> 3.4715586
B49: CLTV | C49: =C48*C44 -> 14736901 | D49: =D48*D44 -> 10138925 | E49: =E48*E44 -> 17746028 | F49: =F48*F44 -> 23501182 | G49: =G48*G44 -> 22992237 | J49: =J48*J44 -> 1136823.7 | K49: =K48*K44 -> 1565958.1 | L49: =L48*L44 -> 1409053 | M49: =M48*M44 -> 1619132.9 | N49: =N48*N44 -> 3084740.7 | O49: =O48*O44 -> 2407772.8 | P49: =P48*P44 -> 3005042.2 | Q49: =Q48*Q44 -> 2777959 | ... AB49: =AB48*AB44 -> 5612067.2 | AE49: =AE48*AE44 -> 477606.26 | AF49: =AF48*AF44 -> 441844.07 | AG49: =AG48*AG44 -> 391429.86 | AH49: =AH48*AH44 -> 237159.51 | AI49: =AI48*AI44 -> 505775.27 | AJ49: =AJ48*AJ44 -> 260990.56 | AK49: =AK48*AK44 -> 508352.29 | AL49: =AL48*AL44 -> 770150.18 | ... CK49: =CK48*CK44 -> 3353814.1
B51: CAC % | C51: 1 | D51: 1 | E51: 1 | F51: 1 | G51: 1 | J51: =AVERAGEIFS($AD51:$BT51,$AD$36:$BT$36,J$36) -> 1 | K51: =AVERAGEIFS($AD51:$BT51,$AD$36:$BT$36,K$36) -> 1 | L51: =AVERAGEIFS($AD51:$BT51,$AD$36:$BT$36,L$36) -> 1 | M51: =AVERAGEIFS($AD51:$BT51,$AD$36:$BT$36,M$36) -> 1 | N51: =AVERAGEIFS($AD51:$BT51,$AD$36:$BT$36,N$36) -> 1 | O51: =AVERAGEIFS($AD51:$BT51,$AD$36:$BT$36,O$36) -> 1 | P51: =AVERAGEIFS($AD51:$BT51,$AD$36:$BT$36,P$36) -> 1 | Q51: =AVERAGEIFS($AD51:$BT51,$AD$36:$BT$36,Q$36) -> 1 | ... V51: =AVERAGEIFS($AD51:$BT51,$AD$36:$BT$36,V$36) -> 1 | W51: =AVERAGEIFS($AD51:$CF51,$AD$36:$CF$36,W$36) -> 1 | X51: =AVERAGEIFS($AD51:$CF51,$AD$36:$CF$36,X$36) -> 1 | Y51: =AVERAGEIFS($AD51:$CF51,$AD$36:$CF$36,Y$36) -> 1 | Z51: =AVERAGEIFS($AD51:$CF51,$AD$36:$CF$36,Z$36) -> 1 | AA51: =AVERAGEIFS($AD51:$CL51,$AD$36:$CL$36,AA$36) -> 1 | AB51: =AVERAGEIFS($AD51:$CL51,$AD$36:$CL$36,AB$36) -> 1 | AE51: 1 | AF51: 1 | AG51: 1 | AH51: 1 | AI51: 1 | AJ51: 1 | AK51: 1 | AL51: 1 | AM51: 1 | AN51: 1 | AO51: 1 | AP51: 1 | AQ51: 1 | AR51: 1 | AS51: 1 | AT51: 1 | AU51: 1 | AV51: 1 | AW51: 1 | AX51: 1 | AY51: 1 | AZ51: 1 | BA51: 1 | BB51: 1 | BC51: 1 | BD51: 1 | BE51: 1 | BF51: 1 | BG51: 1 | BH51: 1 | BI51: 1 | BJ51: 1 | BK51: 1 | BL51: 1 | BM51: 1 | BN51: 1 | BO51: 1 | BP51: 1 | BQ51: 1 | BR51: 1 | BS51: 1 | BT51: 1 | BU51: 1 | BV51: 1 | BW51: 1 | BX51: 1 | BY51: 1 | BZ51: 1 | CA51: 1 | CB51: 1 | CC51: 1 | CD51: 1 | CE51: 1 | CF51: 1 | CG51: 1 | CH51: 1 | CI51: 1 | CJ51: 1 | CK51: 1
B52: CAC (S&M) | C52: =SUMIFS($I52:$W52,$I$7:$W$7,C$7) -> 1358009.1 | D52: =+SUM(OFFSET(INDEX($AD52:$CF52,MATCH(D$8,$AD$8:$CF$8,0)),,,,-12)) -> 3078221.8 | E52: =+SUM(OFFSET(INDEX($AD52:$CF52,MATCH(E$8,$AD$8:$CF$8,0)),,,,-12)) -> 4902032.3 | F52: =+SUM(OFFSET(INDEX($AD52:$CF52,MATCH(F$8,$AD$8:$CF$8,0)),,,,-12)) -> 7682944.2 | G52: =+SUM(OFFSET(INDEX($AD52:$CL52,MATCH(G$8,$AD$8:$CL$8,0)),,,,-12)) -> 9331910.9 | J52: =SUMIFS($AD52:$BT52,$AD$5:$BT$5,J$5) -> 339406.01 | K52: =SUMIFS($AD52:$BT52,$AD$5:$BT$5,K$5) -> 470819.37 | L52: =SUMIFS($AD52:$BT52,$AD$5:$BT$5,L$5) -> 547783.73 | M52: =SUMIFS($AD52:$BT52,$AD$5:$BT$5,M$5) -> 621543.1 | N52: =SUMIFS($AD52:$BT52,$AD$5:$BT$5,N$5) -> 727199.85 | O52: =SUMIFS($AD52:$BT52,$AD$5:$BT$5,O$5) -> 828847.02 | P52: =SUMIFS($AD52:$BT52,$AD$5:$BT$5,P$5) -> 900631.81 | Q52: =SUMIFS($AD52:$BT52,$AD$5:$BT$5,Q$5) -> 998575.32 | ... V52: =SUMIFS($AD52:$BT52,$AD$5:$BT$5,V$5) -> 1917227.3 | W52: =SUMIFS($AD52:$CF52,$AD$5:$CF$5,W$5) -> 1883458.9 | X52: =SUMIFS($AD52:$CF52,$AD$5:$CF$5,X$5) -> 2023606.5 | Y52: =SUMIFS($AD52:$CF52,$AD$5:$CF$5,Y$5) -> 2055356.6 | Z52: =SUMIFS($AD52:$CF52,$AD$5:$CF$5,Z$5) -> 2201652.3 | AA52: =SUMIFS($AD52:$CL52,$AD$5:$CL$5,AA$5) -> 2273406.4 | AB52: =SUMIFS($AD52:$CL52,$AD$5:$CL$5,AB$5) -> 2801495.5 | AE52: ='Cons TrioMobil | Monthly'!P256*-1*AE51 -> 109663.83 | AF52: ='Cons TrioMobil | Monthly'!Q256*-1*AF51 -> 125645.8 | AG52: ='Cons TrioMobil | Monthly'!R256*-1*AG51 -> 106252.42 | AH52: ='Cons TrioMobil | Monthly'!S256*-1*AH51 -> 101359.73 | AI52: ='Cons TrioMobil | Monthly'!T256*-1*AI51 -> 131793.86 | AJ52: ='Cons TrioMobil | Monthly'!U256*-1*AJ51 -> 122824.17 | AK52: ='Cons TrioMobil | Monthly'!V256*-1*AK51 -> 145946.4 | AL52: ='Cons TrioMobil | Monthly'!W256*-1*AL51 -> 202048.8 | ... CK52: ='Cons TrioMobil | Monthly'!BV256*-1*CK51 -> 1020522.6
B53: CAC / New Logo | C53: =C52/C26 -> 122.80784 | D53: =D52/D26 -> 1340.6889 | E53: =E52/E26 -> 2198.2208 | F53: =F52/F26 -> 2651.1195 | G53: =G52/G26 -> 2956.8792 | J53: =J52/J26 -> 761.00003 | K53: =K52/K26 -> 676.46462 | L53: =L52/L26 -> 748.33843 | M53: =M52/M26 -> 1111.8839 | N53: =N52/N26 -> 1091.8917 | O53: =O52/O26 -> 1506.9946 | P53: =P52/P26 -> 1728.6599 | Q53: =Q52/Q26 -> 1739.6783 | ... AB53: =AB52/AB26 -> 3165.5317 | AE53: =AE52/AE26 -> 721.47256 | AF53: =AF52/AF26 -> 734.77077 | AG53: =AG52/AG26 -> 727.7563 | AH53: =AH52/AH26 -> 984.07506 | AI53: =AI52/AI26 -> 669.00437 | AJ53: =AJ52/AJ26 -> 739.90462 | AK53: =AK52/AK26 -> 657.41624 | AL53: =AL52/AL26 -> 656.0026 | ... CK53: =CK52/CK26 -> 3471.1654
B55: LTV-CAC | D55: =D49/D52 -> 3.2937605 | E55: =E49/E52 -> 3.6201369 | F55: =F49/F52 -> 3.0588771 | G55: =G49/G52 -> 2.4638295 | J55: =J49/J52 -> 3.3494506 | K55: =K49/K52 -> 3.3260274 | L55: =L49/L52 -> 2.5722797 | M55: =M49/M52 -> 2.6050211 | N55: =N49/N52 -> 4.2419436 | O55: =O49/O52 -> 2.9049665 | P55: =P49/P52 -> 3.3365934 | Q55: =Q49/Q52 -> 2.7819223 | ... AB55: =AB49/AB52 -> 2.0032397 | AE55: =AE49/AE52 -> 4.355185 | AF55: =AF49/AF52 -> 3.5165844 | AG55: =AG49/AG52 -> 3.6839618 | AH55: =AH49/AH52 -> 2.3397804 | AI55: =AI49/AI52 -> 3.8376239 | AJ55: =AJ49/AJ52 -> 2.1249121 | AK55: =AK49/AK52 -> 3.4831436 | AL55: =AL49/AL52 -> 3.8117038 | ... CK55: =CK49/CK52 -> 3.2863691
B56: Payback (months) | D56: =(D52/D44)*12 -> 18.216261 | E56: =(E52/E44)*12 -> 16.573959 | F56: =(F52/F44)*12 -> 19.615041 | G56: =(G52/G44)*12 -> 19.680169 | J56: =(J52/J44)*12 -> 17.913386 | K56: =(K52/K44)*12 -> 18.039539 | L56: =(L52/L44)*12 -> 23.325613 | M56: =(M52/M44)*12 -> 23.032443 | N56: =(N52/N44)*12 -> 14.14446 | O56: =(O52/O44)*12 -> 20.654283 | P56: =(P52/P44)*12 -> 17.982413 | Q56: =(Q52/Q44)*12 -> 21.56782 | ... AB56: =(AB52/AB44)*12 -> 20.442305 | AE56: =AE52/AE44*12 -> 12.594609 | AF56: =AF52/AF44*12 -> 17.06201 | AG56: =AG52/AG44*12 -> 16.286814 | AH56: =AH52/AH44*12 -> 25.643432 | AI56: =AI52/AI44*12 -> 15.634675 | AJ56: =AJ52/AJ44*12 -> 25.603911 | AK56: =AK52/AK44*12 -> 17.225819 | AL56: =AL52/AL44*12 -> 15.740992 | ... CK56: =CK52/CK44*12 -> 12.676209
B58: Check
B60: Ending ARR | C60: 0 | D60: =+INDEX('MRR Schedule Summary'!$B$50:$BK$50,MATCH(D$8,'MRR Schedule Summary'!$B$76:$BK$76,0))*12-D14 -> 0 | E60: =+INDEX('MRR Schedule Summary'!$B$50:$BK$50,MATCH(E$8,'MRR Schedule Summary'!$B$76:$BK$76,0))*12-E14 -> 0 | F60: =+INDEX('MRR Schedule Summary'!$B$50:$BK$50,MATCH(F$8,'MRR Schedule Summary'!$B$76:$BK$76,0))*12-F14 -> 0 | G60: =+INDEX('MRR Schedule Summary'!$B$50:$BK$50,MATCH(G$8,'MRR Schedule Summary'!$B$76:$BK$76,0))*12-G14 -> 0 | I60: =+INDEX('MRR Schedule Summary'!$B$50:$BK$50,MATCH(I$8,'MRR Schedule Summary'!$B$76:$BK$76,0))*12-I14 -> 0 | J60: =+INDEX('MRR Schedule Summary'!$B$50:$BK$50,MATCH(J$8,'MRR Schedule Summary'!$B$76:$BK$76,0))*12-J14 -> 0 | K60: =+INDEX('MRR Schedule Summary'!$B$50:$BK$50,MATCH(K$8,'MRR Schedule Summary'!$B$76:$BK$76,0))*12-K14 -> 0 | L60: =+INDEX('MRR Schedule Summary'!$B$50:$BK$50,MATCH(L$8,'MRR Schedule Summary'!$B$76:$BK$76,0))*12-L14 -> 0 | M60: =+INDEX('MRR Schedule Summary'!$B$50:$BK$50,MATCH(M$8,'MRR Schedule Summary'!$B$76:$BK$76,0))*12-M14 -> 0 | N60: =+INDEX('MRR Schedule Summary'!$B$50:$BK$50,MATCH(N$8,'MRR Schedule Summary'!$B$76:$BK$76,0))*12-N14 -> 0 | O60: =+INDEX('MRR Schedule Summary'!$B$50:$BK$50,MATCH(O$8,'MRR Schedule Summary'!$B$76:$BK$76,0))*12-O14 -> 0 | P60: =+INDEX('MRR Schedule Summary'!$B$50:$BK$50,MATCH(P$8,'MRR Schedule Summary'!$B$76:$BK$76,0))*12-P14 -> 0 | ... AB60: =+INDEX('MRR Schedule Summary'!$B$50:$BK$50,MATCH(AB$8,'MRR Schedule Summary'!$B$76:$BK$76,0))*12-AB14 -> 0 | AD60: =+INDEX('MRR Schedule Summary'!$B$50:$BK$50,MATCH(AD$8,'MRR Schedule Summary'!$B$76:$BK$76,0))*12-AD14 -> 0 | AE60: =+INDEX('MRR Schedule Summary'!$B$50:$BK$50,MATCH(AE$8,'MRR Schedule Summary'!$B$76:$BK$76,0))*12-AE14 -> 0 | AF60: =+INDEX('MRR Schedule Summary'!$B$50:$BK$50,MATCH(AF$8,'MRR Schedule Summary'!$B$76:$BK$76,0))*12-AF14 -> 0 | AG60: =+INDEX('MRR Schedule Summary'!$B$50:$BK$50,MATCH(AG$8,'MRR Schedule Summary'!$B$76:$BK$76,0))*12-AG14 -> 0 | AH60: =+INDEX('MRR Schedule Summary'!$B$50:$BK$50,MATCH(AH$8,'MRR Schedule Summary'!$B$76:$BK$76,0))*12-AH14 -> 0 | AI60: =+INDEX('MRR Schedule Summary'!$B$50:$BK$50,MATCH(AI$8,'MRR Schedule Summary'!$B$76:$BK$76,0))*12-AI14 -> 0 | AJ60: =+INDEX('MRR Schedule Summary'!$B$50:$BK$50,MATCH(AJ$8,'MRR Schedule Summary'!$B$76:$BK$76,0))*12-AJ14 -> 0 | AK60: =+INDEX('MRR Schedule Summary'!$B$50:$BK$50,MATCH(AK$8,'MRR Schedule Summary'!$B$76:$BK$76,0))*12-AK14 -> 0 | ... CK60: =+INDEX('MRR Schedule Summary'!$B$50:$BK$50,MATCH(CK$8,'MRR Schedule Summary'!$B$76:$BK$76,0))*12-CK14 -> 1.6763806e-08
B61: Ending Logos | C61: 0 | D61: =+INDEX('MRR Schedule Summary'!$B$58:$BK$58,MATCH(D$8,'MRR Schedule Summary'!$B$76:$BK$76,0))-D28 -> 0 | E61: =+INDEX('MRR Schedule Summary'!$B$58:$BK$58,MATCH(E$8,'MRR Schedule Summary'!$B$76:$BK$76,0))-E28 -> 0 | F61: =+INDEX('MRR Schedule Summary'!$B$58:$BK$58,MATCH(F$8,'MRR Schedule Summary'!$B$76:$BK$76,0))-F28 -> 0 | G61: =+INDEX('MRR Schedule Summary'!$B$58:$BK$58,MATCH(G$8,'MRR Schedule Summary'!$B$76:$BK$76,0))-G28 -> 0 | I61: =+INDEX('MRR Schedule Summary'!$B$58:$BK$58,MATCH(I$8,'MRR Schedule Summary'!$B$76:$BK$76,0))-I28 -> 0 | J61: =+INDEX('MRR Schedule Summary'!$B$58:$BK$58,MATCH(J$8,'MRR Schedule Summary'!$B$76:$BK$76,0))-J28 -> 0 | K61: =+INDEX('MRR Schedule Summary'!$B$58:$BK$58,MATCH(K$8,'MRR Schedule Summary'!$B$76:$BK$76,0))-K28 -> 0 | L61: =+INDEX('MRR Schedule Summary'!$B$58:$BK$58,MATCH(L$8,'MRR Schedule Summary'!$B$76:$BK$76,0))-L28 -> 0 | M61: =+INDEX('MRR Schedule Summary'!$B$58:$BK$58,MATCH(M$8,'MRR Schedule Summary'!$B$76:$BK$76,0))-M28 -> 0 | N61: =+INDEX('MRR Schedule Summary'!$B$58:$BK$58,MATCH(N$8,'MRR Schedule Summary'!$B$76:$BK$76,0))-N28 -> 0 | O61: =+INDEX('MRR Schedule Summary'!$B$58:$BK$58,MATCH(O$8,'MRR Schedule Summary'!$B$76:$BK$76,0))-O28 -> 0 | P61: =+INDEX('MRR Schedule Summary'!$B$58:$BK$58,MATCH(P$8,'MRR Schedule Summary'!$B$76:$BK$76,0))-P28 -> 0 | ... AB61: =+INDEX('MRR Schedule Summary'!$B$58:$BK$58,MATCH(AB$8,'MRR Schedule Summary'!$B$76:$BK$76,0))-AB28 -> 0 | AD61: =+INDEX('MRR Schedule Summary'!$B$58:$BK$58,MATCH(AD$8,'MRR Schedule Summary'!$B$76:$BK$76,0))-AD28 -> 0 | AE61: =+INDEX('MRR Schedule Summary'!$B$58:$BK$58,MATCH(AE$8,'MRR Schedule Summary'!$B$76:$BK$76,0))-AE28 -> 0 | AF61: =+INDEX('MRR Schedule Summary'!$B$58:$BK$58,MATCH(AF$8,'MRR Schedule Summary'!$B$76:$BK$76,0))-AF28 -> 0 | AG61: =+INDEX('MRR Schedule Summary'!$B$58:$BK$58,MATCH(AG$8,'MRR Schedule Summary'!$B$76:$BK$76,0))-AG28 -> 0 | AH61: =+INDEX('MRR Schedule Summary'!$B$58:$BK$58,MATCH(AH$8,'MRR Schedule Summary'!$B$76:$BK$76,0))-AH28 -> 0 | AI61: =+INDEX('MRR Schedule Summary'!$B$58:$BK$58,MATCH(AI$8,'MRR Schedule Summary'!$B$76:$BK$76,0))-AI28 -> 0 | AJ61: =+INDEX('MRR Schedule Summary'!$B$58:$BK$58,MATCH(AJ$8,'MRR Schedule Summary'!$B$76:$BK$76,0))-AJ28 -> 0 | AK61: =+INDEX('MRR Schedule Summary'!$B$58:$BK$58,MATCH(AK$8,'MRR Schedule Summary'!$B$76:$BK$76,0))-AK28 -> 0 | ... CK61: =+INDEX('MRR Schedule Summary'!$B$58:$BK$58,MATCH(CK$8,'MRR Schedule Summary'!$B$76:$BK$76,0))-CK28 -> 0
B62: S&M | D62: =+SUM(OFFSET(INDEX($AD52:$CF52,MATCH(D$8,$AD$8:$CF$8,0)),,,,-12))-D52 -> 0 | E62: =+SUM(OFFSET(INDEX($AD52:$CF52,MATCH(E$8,$AD$8:$CF$8,0)),,,,-12))-E52 -> 0 | F62: =+SUM(OFFSET(INDEX($AD52:$CF52,MATCH(F$8,$AD$8:$CF$8,0)),,,,-12))-F52 -> 0 | G62: =+SUM(OFFSET(INDEX($AD52:$CL52,MATCH(G$8,$AD$8:$CL$8,0)),,,,-12))-G52 -> 0 | J62: =J52-SUMIFS($AD52:$BT52,$AD$36:$BT$36,J$36) -> 0 | K62: =K52-SUMIFS($AD52:$BT52,$AD$36:$BT$36,K$36) -> 0 | L62: =L52-SUMIFS($AD52:$BT52,$AD$36:$BT$36,L$36) -> 0 | M62: =M52-SUMIFS($AD52:$BT52,$AD$36:$BT$36,M$36) -> 0 | N62: =N52-SUMIFS($AD52:$BT52,$AD$36:$BT$36,N$36) -> 0 | O62: =O52-SUMIFS($AD52:$BT52,$AD$36:$BT$36,O$36) -> 0 | P62: =P52-SUMIFS($AD52:$BT52,$AD$36:$BT$36,P$36) -> 0 | Q62: =Q52-SUMIFS($AD52:$BT52,$AD$36:$BT$36,Q$36) -> 0 | ... V62: =V52-SUMIFS($AD52:$BT52,$AD$36:$BT$36,V$36) -> 0 | W62: =W52-SUMIFS($AD52:$CF52,$AD$36:$CF$36,W$36) -> 0 | X62: =X52-SUMIFS($AD52:$CF52,$AD$36:$CF$36,X$36) -> 0 | Y62: =Y52-SUMIFS($AD52:$CF52,$AD$36:$CF$36,Y$36) -> 0 | Z62: =Z52-SUMIFS($AD52:$CF52,$AD$36:$CF$36,Z$36) -> 0 | AA62: =AA52-SUMIFS($AD52:$CL52,$AD$36:$CL$36,AA$36) -> 0 | AB62: =AB52-SUMIFS($AD52:$CL52,$AD$36:$CL$36,AB$36) -> 0 | AE62: =('Cons TrioMobil | Monthly'!P256*-1*AE51)-AE52 -> 0 | AF62: =('Cons TrioMobil | Monthly'!Q256*-1*AF51)-AF52 -> 0 | AG62: =('Cons TrioMobil | Monthly'!R256*-1*AG51)-AG52 -> 0 | AH62: =('Cons TrioMobil | Monthly'!S256*-1*AH51)-AH52 -> 0 | AI62: =('Cons TrioMobil | Monthly'!T256*-1*AI51)-AI52 -> 0 | AJ62: =('Cons TrioMobil | Monthly'!U256*-1*AJ51)-AJ52 -> 0 | AK62: =('Cons TrioMobil | Monthly'!V256*-1*AK51)-AK52 -> 0 | AL62: =('Cons TrioMobil | Monthly'!W256*-1*AL51)-AL52 -> 0 | ... CK62: =('Cons TrioMobil | Monthly'!BV256*-1*CK51)-CK52 -> 0
B63: Payback Period | D63: =((D44/12)*D56)-D52 -> 0 | E63: =((E44/12)*E56)-E52 -> 0 | F63: =((F44/12)*F56)-F52 -> 0 | G63: =((G44/12)*G56)-G52 -> 0 | J63: =((J44/12)*J56)-J52 -> 0 | K63: =((K44/12)*K56)-K52 -> 0 | L63: =((L44/12)*L56)-L52 -> 0 | M63: =((M44/12)*M56)-M52 -> 0 | N63: =((N44/12)*N56)-N52 -> 0 | O63: =((O44/12)*O56)-O52 -> 0 | P63: =((P44/12)*P56)-P52 -> 0 | Q63: =((Q44/12)*Q56)-Q52 -> 0 | ... AB63: =((AB44/12)*AB56)-AB52 -> 0 | AE63: =((AE44/12)*AE56)-AE52 -> 0 | AF63: =((AF44/12)*AF56)-AF52 -> 0 | AG63: =((AG44/12)*AG56)-AG52 -> 0 | AH63: =((AH44/12)*AH56)-AH52 -> 0 | AI63: =((AI44/12)*AI56)-AI52 -> 0 | AJ63: =((AJ44/12)*AJ56)-AJ52 -> 0 | AK63: =((AK44/12)*AK56)-AK52 -> 0 | AL63: =((AL44/12)*AL56)-AL52 -> 0 | ... CK63: =((CK44/12)*CK56)-CK52 -> 0
AD65: 44197 | AE65: =+EDATE(AD65,1) -> 44228 | AF65: =+EDATE(AE65,1) -> 44256 | AG65: =+EDATE(AF65,1) -> 44287 | AH65: =+EDATE(AG65,1) -> 44317 | AI65: =+EDATE(AH65,1) -> 44348 | AJ65: =+EDATE(AI65,1) -> 44378 | AK65: =+EDATE(AJ65,1) -> 44409 | AL65: =+EDATE(AK65,1) -> 44440 | ... CK65: =+EDATE(CJ65,1) -> 45992
G66: =+SUM(BZ10:CE11) -> 3684436.5
G67: =+'Cons TrioMobil | Monthly'!BY24 -> 0.75533729
G68: =+G66*G67 -> 2782992.3
G70: =+SUM(BZ27:CE27) -> -1365
G71: =1+G70/G28 -> 0.88817891
G72: 5
F73: LTV | G73: =+G68*G72 -> 13914961
F74: CAC | G74: =+SUM(BZ52:CE52) -> 4257009
F75: YTD LTV CAC | G75: =+G73/G74 -> 3.2687179

Sheet Industrial ARR Rollforward
B2: Trio Mobil
B3: Industrial ARR Rollforward
C5: =C6&" " &YEAR(C8) -> Q4 2021 | D5: =D6&" " &YEAR(D8) -> Q4 2022 | E5: =E6&" " &YEAR(E8) -> Q4 2023 | F5: =F6&" " &YEAR(F8) -> Q4 2024 | G5: =G6&" " &YEAR(G8) -> TTM 2025 | I5: =I6&" " &YEAR(I8) -> Q1 2021 | J5: =J6&" " &YEAR(J8) -> Q2 2021 | K5: =K6&" " &YEAR(K8) -> Q3 2021 | L5: =L6&" " &YEAR(L8) -> Q4 2021 | M5: =M6&" " &YEAR(M8) -> Q1 2022 | N5: =N6&" " &YEAR(N8) -> Q2 2022 | O5: =O6&" " &YEAR(O8) -> Q3 2022 | P5: =P6&" " &YEAR(P8) -> Q4 2022 | ... AB5: =AB6&" " &YEAR(AB8) -> Q4 2025 | AD5: =AD6&" " &YEAR(AD8) -> Q1 2021 | AE5: =AE6&" " &YEAR(AE8) -> Q1 2021 | AF5: =AF6&" " &YEAR(AF8) -> Q1 2021 | AG5: =AG6&" " &YEAR(AG8) -> Q2 2021 | AH5: =AH6&" " &YEAR(AH8) -> Q2 2021 | AI5: =AI6&" " &YEAR(AI8) -> Q2 2021 | AJ5: =AJ6&" " &YEAR(AJ8) -> Q3 2021 | AK5: =AK6&" " &YEAR(AK8) -> Q3 2021 | ... CK5: =CK6&" " &YEAR(CK8) -> Q4 2025
C6: Q4 | D6: Q4 | E6: Q4 | F6: Q4 | G6: TTM | I6: Q1 | J6: Q2 | K6: Q3 | L6: Q4 | M6: Q1 | N6: Q2 | O6: Q3 | P6: Q4 | Q6: Q1 | R6: Q2 | S6: Q3 | T6: Q4 | U6: Q1 | V6: Q2 | W6: Q3 | X6: Q4 | Y6: Q1 | Z6: Q2 | AA6: Q3 | AB6: Q4 | AD6: Q1 | AE6: Q1 | AF6: Q1 | AG6: Q2 | AH6: Q2 | AI6: Q2 | AJ6: Q3 | AK6: Q3 | AL6: Q3 | AM6: Q4 | AN6: Q4 | AO6: Q4 | AP6: Q1 | AQ6: Q1 | AR6: Q1 | AS6: Q2 | AT6: Q2 | AU6: Q2 | AV6: Q3 | AW6: Q3 | AX6: Q3 | AY6: Q4 | AZ6: Q4 | BA6: Q4 | BB6: Q1 | BC6: Q1 | BD6: Q1 | BE6: Q2 | BF6: Q2 | BG6: Q2 | BH6: Q3 | BI6: Q3 | BJ6: Q3 | BK6: Q4 | BL6: Q4 | BM6: Q4 | BN6: Q1 | BO6: Q1 | BP6: Q1 | BQ6: Q2 | BR6: Q2 | BS6: Q2 | BT6: Q3 | BU6: Q3 | BV6: Q3 | BW6: Q4 | BX6: Q4 | BY6: Q4 | BZ6: Q1 | CA6: Q1 | CB6: Q1 | CC6: Q2 | CD6: Q2 | CE6: Q2 | CF6: Q3 | CG6: Q3 | CH6: Q3 | CI6: Q4 | CJ6: Q4 | CK6: Q4
C7: =YEAR(C8) -> 2021 | D7: =YEAR(D8) -> 2022 | E7: =YEAR(E8) -> 2023 | F7: =YEAR(F8) -> 2024 | G7: =YEAR(G8) -> 2025 | I7: =YEAR(I8) -> 2021 | J7: =YEAR(J8) -> 2021 | K7: =YEAR(K8) -> 2021 | L7: =YEAR(L8) -> 2021 | M7: =YEAR(M8) -> 2022 | N7: =YEAR(N8) -> 2022 | O7: =YEAR(O8) -> 2022 | P7: =YEAR(P8) -> 2022 | ... AB7: =YEAR(AB8) -> 2025 | AD7: =YEAR(AD8) -> 2021 | AE7: =YEAR(AE8) -> 2021 | AF7: =YEAR(AF8) -> 2021 | AG7: =YEAR(AG8) -> 2021 | AH7: =YEAR(AH8) -> 2021 | AI7: =YEAR(AI8) -> 2021 | AJ7: =YEAR(AJ8) -> 2021 | AK7: =YEAR(AK8) -> 2021 | ... CK7: =YEAR(CK8) -> 2025
B8: Industrial ARR | C8: 44561 | D8: =EOMONTH(C8,12) -> 44926 | E8: =EOMONTH(D8,12) -> 45291 | F8: =EOMONTH(E8,12) -> 45657 | G8: =EOMONTH(F8,12) -> 46022 | I8: 44286 | J8: =EOMONTH(I8,3) -> 44377 | K8: =EOMONTH(J8,3) -> 44469 | L8: =EOMONTH(K8,3) -> 44561 | M8: =EOMONTH(L8,3) -> 44651 | N8: =EOMONTH(M8,3) -> 44742 | O8: =EOMONTH(N8,3) -> 44834 | P8: =EOMONTH(O8,3) -> 44926 | Q8: =EOMONTH(P8,3) -> 45016 | ... W8: =EOMONTH(V8,3) -> 45565 | X8: 45657 | Y8: 45747 | Z8: 45838 | AA8: 45930 | AB8: 46022 | AD8: 44227 | AE8: =EOMONTH(AD8,1) -> 44255 | AF8: =EOMONTH(AE8,1) -> 44286 | AG8: =EOMONTH(AF8,1) -> 44316 | AH8: =EOMONTH(AG8,1) -> 44347 | AI8: =EOMONTH(AH8,1) -> 44377 | AJ8: =EOMONTH(AI8,1) -> 44408 | AK8: =EOMONTH(AJ8,1) -> 44439 | AL8: =EOMONTH(AK8,1) -> 44469 | ... CK8: =EOMONTH(CJ8,1) -> 46022
B9: Beginning | C9: =I9 -> 715138.93 | D9: =+SUMIFS($AD$14:$CL$14,$AD$8:$CL$8,EOMONTH(D8,-12)) -> 1014969.7 | E9: =+SUMIFS($AD$14:$CL$14,$AD$8:$CL$8,EOMONTH(E8,-12)) -> 2187670.7 | F9: =+SUMIFS($AD$14:$CL$14,$AD$8:$CL$8,EOMONTH(F8,-12)) -> 3967064.8 | G9: =+SUMIFS($AD$14:$CL$14,$AD$8:$CL$8,EOMONTH(G8,-12)) -> 5192351 | I9: =AD9 -> 715138.93 | J9: =I14 -> 781715.86 | K9: =J14 -> 775623.44 | L9: =K14 -> 922160.71 | M9: =L14 -> 1014969.7 | N9: =M14 -> 1168916.7 | O9: =N14 -> 1625005.3 | P9: =O14 -> 1863009.7 | Q9: =P14 -> 2187670.7 | ... AB9: =AA14 -> 6791032.2 | AD9: =+'MRR Schedule Summary'!C25*12 -> 715138.93 | AE9: =AD14 -> 746844.43 | AF9: =AE14 -> 757828.4 | AG9: =AF14 -> 781715.86 | AH9: =AG14 -> 781152.3 | AI9: =AH14 -> 785449.27 | AJ9: =AI14 -> 775623.44 | AK9: =AJ14 -> 772449.02 | AL9: =AK14 -> 810237.35 | ... CK9: =CJ14 -> 7060296.9
B10: (+) New | C10: =SUMIFS($I10:$W10,$I$7:$W$7,C$7) -> 196329.34 | D10: =+SUM(OFFSET(INDEX($AD10:$CL10,MATCH(D$8,$AD$8:$CL$8,0)),,,,-12)) -> 689518.12 | E10: =+SUM(OFFSET(INDEX($AD10:$CL10,MATCH(E$8,$AD$8:$CL$8,0)),,,,-12)) -> 1269931.9 | F10: =+SUM(OFFSET(INDEX($AD10:$CL10,MATCH(F$8,$AD$8:$CL$8,0)),,,,-12)) -> 692611.46 | G10: =+SUM(OFFSET(INDEX($AD10:$CL10,MATCH(G$8,$AD$8:$CL$8,0)),,,,-12)) -> 1949466.7 | I10: =SUMIFS($AD10:$BT10,$AD$5:$BT$5,I$5) -> 11404.371 | J10: =SUMIFS($AD10:$BT10,$AD$5:$BT$5,J$5) -> 20207.816 | K10: =SUMIFS($AD10:$BT10,$AD$5:$BT$5,K$5) -> 96570.778 | L10: =SUMIFS($AD10:$BT10,$AD$5:$BT$5,L$5) -> 68146.375 | M10: =SUMIFS($AD10:$BT10,$AD$5:$BT$5,M$5) -> 35675.524 | N10: =SUMIFS($AD10:$BT10,$AD$5:$BT$5,N$5) -> 348450.22 | O10: =SUMIFS($AD10:$BT10,$AD$5:$BT$5,O$5) -> 160605.37 | P10: =SUMIFS($AD10:$BT10,$AD$5:$BT$5,P$5) -> 144787.01 | ... V10: =SUMIFS($AD10:$BT10,$AD$5:$BT$5,V$5) -> 312111.98 | W10: =SUMIFS($AD10:$BV10,$AD$5:$BV$5,W$5) -> 134400.33 | X10: =SUMIFS($AD10:$BY10,$AD$5:$BY$5,X$5) -> 125274.93 | Y10: =SUMIFS($AD10:$CL10,$AD$5:$CL$5,Y$5) -> 380719.42 | Z10: =SUMIFS($AD10:$CL10,$AD$5:$CL$5,Z$5) -> 485167.65 | AA10: =SUMIFS($AD10:$CL10,$AD$5:$CL$5,AA$5) -> 492210.13 | AB10: =SUMIFS($AD10:$CL10,$AD$5:$CL$5,AB$5) -> 591369.46 | AD10: =+'MRR Schedule Summary'!C26*12 -> 4783.6505 | AE10: =+'MRR Schedule Summary'!D26*12 -> 999.24216 | AF10: =+'MRR Schedule Summary'!E26*12 -> 5621.478 | AG10: =+'MRR Schedule Summary'!F26*12 -> 8264.4457 | AH10: =+'MRR Schedule Summary'!G26*12 -> 5986.5236 | AI10: =+'MRR Schedule Summary'!H26*12 -> 5956.8469 | AJ10: =+'MRR Schedule Summary'!I26*12 -> 4144.5983 | AK10: =+'MRR Schedule Summary'!J26*12 -> 20304.577 | ... CK10: =+'MRR Schedule Summary'!BJ26*12 -> 525504.14
B11: (+) Upsell | C11: =SUMIFS($I11:$W11,$I$7:$W$7,C$7) -> 180353.86 | D11: =+SUM(OFFSET(INDEX($AD11:$CL11,MATCH(D$8,$AD$8:$CL$8,0)),,,,-12)) -> 600387.39 | E11: =+SUM(OFFSET(INDEX($AD11:$CL11,MATCH(E$8,$AD$8:$CL$8,0)),,,,-12)) -> 932402.55 | F11: =+SUM(OFFSET(INDEX($AD11:$CL11,MATCH(F$8,$AD$8:$CL$8,0)),,,,-12)) -> 1268550.8 | G11: =+SUM(OFFSET(INDEX($AD11:$CL11,MATCH(G$8,$AD$8:$CL$8,0)),,,,-12)) -> 1537459.7 | I11: =SUMIFS($AD11:$BT11,$AD$5:$BT$5,I$5) -> 55671.846 | J11: =SUMIFS($AD11:$BT11,$AD$5:$BT$5,J$5) -> 6401.0345 | K11: =SUMIFS($AD11:$BT11,$AD$5:$BT$5,K$5) -> 58576.612 | L11: =SUMIFS($AD11:$BT11,$AD$5:$BT$5,L$5) -> 59704.365 | M11: =SUMIFS($AD11:$BT11,$AD$5:$BT$5,M$5) -> 138563.3 | N11: =SUMIFS($AD11:$BT11,$AD$5:$BT$5,N$5) -> 112465.68 | O11: =SUMIFS($AD11:$BT11,$AD$5:$BT$5,O$5) -> 114339.61 | P11: =SUMIFS($AD11:$BT11,$AD$5:$BT$5,P$5) -> 235018.8 | ... V11: =SUMIFS($AD11:$BT11,$AD$5:$BT$5,V$5) -> 184206.67 | W11: =SUMIFS($AD11:$BV11,$AD$5:$BV$5,W$5) -> 381415.94 | X11: =SUMIFS($AD11:$BY11,$AD$5:$BY$5,X$5) -> 475413.71 | Y11: =SUMIFS($AD11:$CL11,$AD$5:$CL$5,Y$5) -> 184680.81 | Z11: =SUMIFS($AD11:$CL11,$AD$5:$CL$5,Z$5) -> 309203.49 | AA11: =SUMIFS($AD11:$CL11,$AD$5:$CL$5,AA$5) -> 436051.26 | AB11: =SUMIFS($AD11:$CL11,$AD$5:$CL$5,AB$5) -> 607524.15 | AD11: =+'MRR Schedule Summary'!C27*12 -> 26921.853 | AE11: =+'MRR Schedule Summary'!D27*12 -> 10484.005 | AF11: =+'MRR Schedule Summary'!E27*12 -> 18265.988 | AG11: =+'MRR Schedule Summary'!F27*12 -> 554.06422 | AH11: =+'MRR Schedule Summary'!G27*12 -> 5681.5747 | AI11: =+'MRR Schedule Summary'!H27*12 -> 165.39552 | AJ11: =+'MRR Schedule Summary'!I27*12 -> 0 | AK11: =+'MRR Schedule Summary'!J27*12 -> 18774.807 | ... CK11: =+'MRR Schedule Summary'!BJ27*12 -> 306157.87
B12: (-) Downsell | C12: =SUMIFS($I12:$W12,$I$7:$W$7,C$7) -> -76852.426 | D12: =+SUM(OFFSET(INDEX($AD12:$CL12,MATCH(D$8,$AD$8:$CL$8,0)),,,,-12)) -> -117447.59 | E12: =+SUM(OFFSET(INDEX($AD12:$CL12,MATCH(E$8,$AD$8:$CL$8,0)),,,,-12)) -> -422849.7 | F12: =+SUM(OFFSET(INDEX($AD12:$CL12,MATCH(F$8,$AD$8:$CL$8,0)),,,,-12)) -> -692489.5 | G12: =+SUM(OFFSET(INDEX($AD12:$CL12,MATCH(G$8,$AD$8:$CL$8,0)),,,,-12)) -> -795946.71 | I12: =SUMIFS($AD12:$BT12,$AD$5:$BT$5,I$5) -> -499.27795 | J12: =SUMIFS($AD12:$BT12,$AD$5:$BT$5,J$5) -> -32701.271 | K12: =SUMIFS($AD12:$BT12,$AD$5:$BT$5,K$5) -> -8610.1241 | L12: =SUMIFS($AD12:$BT12,$AD$5:$BT$5,L$5) -> -35041.753 | M12: =SUMIFS($AD12:$BT12,$AD$5:$BT$5,M$5) -> -20235.908 | N12: =SUMIFS($AD12:$BT12,$AD$5:$BT$5,N$5) -> -4827.2256 | O12: =SUMIFS($AD12:$BT12,$AD$5:$BT$5,O$5) -> -36940.637 | P12: =SUMIFS($AD12:$BT12,$AD$5:$BT$5,P$5) -> -55443.819 | ... V12: =SUMIFS($AD12:$BT12,$AD$5:$BT$5,V$5) -> -161200.29 | W12: =SUMIFS($AD12:$BV12,$AD$5:$BV$5,W$5) -> -160646.5 | X12: =SUMIFS($AD12:$BY12,$AD$5:$BY$5,X$5) -> -255558.61 | Y12: =SUMIFS($AD12:$CL12,$AD$5:$CL$5,Y$5) -> -120526.72 | Z12: =SUMIFS($AD12:$CL12,$AD$5:$CL$5,Z$5) -> -373478.15 | AA12: =SUMIFS($AD12:$CL12,$AD$5:$CL$5,AA$5) -> -153389.81 | AB12: =SUMIFS($AD12:$CL12,$AD$5:$CL$5,AB$5) -> -148552.02 | AD12: =+'MRR Schedule Summary'!C28*12 -> 0 | AE12: =+'MRR Schedule Summary'!D28*12 -> -499.27795 | AF12: =+'MRR Schedule Summary'!E28*12 -> 0 | AG12: =+'MRR Schedule Summary'!F28*12 -> -9382.0784 | AH12: =+'MRR Schedule Summary'!G28*12 -> -7371.1291 | AI12: =+'MRR Schedule Summary'!H28*12 -> -15948.063 | AJ12: =+'MRR Schedule Summary'!I28*12 -> -7319.0261 | AK12: =+'MRR Schedule Summary'!J28*12 -> -1291.0552 | ... CK12: =+'MRR Schedule Summary'!BJ28*12 -> -55296.726
B13: (-) Churn | C13: =SUMIFS($I13:$W13,$I$7:$W$7,C$7) -> 0 | D13: =+SUM(OFFSET(INDEX($AD13:$CL13,MATCH(D$8,$AD$8:$CL$8,0)),,,,-12)) -> 243.0354 | E13: =+SUM(OFFSET(INDEX($AD13:$CL13,MATCH(E$8,$AD$8:$CL$8,0)),,,,-12)) -> -90.686478 | F13: =+SUM(OFFSET(INDEX($AD13:$CL13,MATCH(F$8,$AD$8:$CL$8,0)),,,,-12)) -> -43386.467 | G13: =+SUM(OFFSET(INDEX($AD13:$CL13,MATCH(G$8,$AD$8:$CL$8,0)),,,,-12)) -> -51718.687 | I13: =SUMIFS($AD13:$BT13,$AD$5:$BT$5,I$5) -> 0 | J13: =SUMIFS($AD13:$BT13,$AD$5:$BT$5,J$5) -> 0 | K13: =SUMIFS($AD13:$BT13,$AD$5:$BT$5,K$5) -> 0 | L13: =SUMIFS($AD13:$BT13,$AD$5:$BT$5,L$5) -> 0 | M13: =SUMIFS($AD13:$BT13,$AD$5:$BT$5,M$5) -> -55.938596 | N13: =SUMIFS($AD13:$BT13,$AD$5:$BT$5,N$5) -> 0 | O13: =SUMIFS($AD13:$BT13,$AD$5:$BT$5,O$5) -> 0 | P13: =SUMIFS($AD13:$BT13,$AD$5:$BT$5,P$5) -> 298.974 | ... V13: =SUMIFS($AD13:$BT13,$AD$5:$BT$5,V$5) -> -11542.33 | W13: =SUMIFS($AD13:$BV13,$AD$5:$BV$5,W$5) -> -19527.517 | X13: =SUMIFS($AD13:$BY13,$AD$5:$BY$5,X$5) -> -8653.5513 | Y13: =SUMIFS($AD13:$CL13,$AD$5:$CL$5,Y$5) -> -3998.2247 | Z13: =SUMIFS($AD13:$CL13,$AD$5:$CL$5,Z$5) -> -27953.71 | AA13: =SUMIFS($AD13:$CL13,$AD$5:$CL$5,AA$5) -> -10004.936 | AB13: =SUMIFS($AD13:$CL13,$AD$5:$CL$5,AB$5) -> -9761.8169 | AD13: =+SUM('MRR Schedule Summary'!C29:C30)*12 -> 0 | AE13: =+SUM('MRR Schedule Summary'!D29:D30)*12 -> 0 | AF13: =+SUM('MRR Schedule Summary'!E29:E30)*12 -> 0 | AG13: =+SUM('MRR Schedule Summary'!F29:F30)*12 -> 0 | AH13: =+SUM('MRR Schedule Summary'!G29:G30)*12 -> 0 | AI13: =+SUM('MRR Schedule Summary'!H29:H30)*12 -> 0 | AJ13: =+SUM('MRR Schedule Summary'!I29:I30)*12 -> 0 | AK13: =+SUM('MRR Schedule Summary'!J29:J30)*12 -> 0 | ... CK13: =+SUM('MRR Schedule Summary'!BJ29:BJ30)*12 -> -5050.1849
B14: Ending ARR | C14: =SUM(C9:C13) -> 1014969.7 | D14: =SUM(D9:D13) -> 2187670.7 | E14: =SUM(E9:E13) -> 3967064.8 | F14: =SUM(F9:F13) -> 5192351 | G14: =SUM(G9:G13) -> 7831612 | I14: =SUM(I9:I13) -> 781715.86 | J14: =SUM(J9:J13) -> 775623.44 | K14: =SUM(K9:K13) -> 922160.71 | L14: =SUM(L9:L13) -> 1014969.7 | M14: =SUM(M9:M13) -> 1168916.7 | N14: =SUM(N9:N13) -> 1625005.3 | O14: =SUM(O9:O13) -> 1863009.7 | P14: =SUM(P9:P13) -> 2187670.7 | ... AB14: =SUM(AB9:AB13) -> 7831612 | AD14: =SUM(AD9:AD13) -> 746844.43 | AE14: =SUM(AE9:AE13) -> 757828.4 | AF14: =SUM(AF9:AF13) -> 781715.86 | AG14: =SUM(AG9:AG13) -> 781152.3 | AH14: =SUM(AH9:AH13) -> 785449.27 | AI14: =SUM(AI9:AI13) -> 775623.44 | AJ14: =SUM(AJ9:AJ13) -> 772449.02 | AK14: =SUM(AK9:AK13) -> 810237.35 | ... CK14: =SUM(CK9:CK13) -> 7831612
B15: % YoY Growth | D15: =D14/C14-1 -> 1.1554049 | E15: =E14/D14-1 -> 0.81337385 | F15: =F14/E14-1 -> 0.30886471 | G15: =G14/G9-1 -> 0.50829787 | M15: =M14/I14-1 -> 0.49532167 | N15: =N14/J14-1 -> 1.0950957 | O15: =O14/K14-1 -> 1.0202657 | P15: =P14/L14-1 -> 1.1554049 | Q15: =Q14/M14-1 -> 0.96645628 | R15: =R14/N14-1 -> 0.66216196 | S15: =S14/O14-1 -> 0.89889119 | T15: =T14/P14-1 -> 0.81337385 | ... AB15: =AB14/X14-1 -> 0.50829787 | AP15: =AP14/AD14-1 -> 0.37779984 | AQ15: =AQ14/AE14-1 -> 0.40472056 | AR15: =AR14/AF14-1 -> 0.49532167 | AS15: =AS14/AG14-1 -> 0.69660208 | AT15: =AT14/AH14-1 -> 0.86610121 | AU15: =AU14/AI14-1 -> 1.0950957 | AV15: =AV14/AJ14-1 -> 1.2312077 | AW15: =AW14/AK14-1 -> 1.1558327 | ... CK15: =CK14/BY14-1 -> 0.50829787
B17: Gross Retention (c only) | C17: =1+C13/C9 -> 1 | D17: =1+D13/D9 -> 1.0002395 | E17: =1+E13/E9 -> 0.99995855 | F17: =1+F13/F9 -> 0.98906333 | G17: =1+G13/G9 -> 0.99003945 | I17: =1+I13*4/I9 -> 1 | J17: =1+J13*4/J9 -> 1 | K17: =1+K13*4/K9 -> 1 | L17: =1+L13*4/L9 -> 1 | M17: =1+M13*4/M9 -> 0.99977955 | N17: =1+N13*4/N9 -> 1 | O17: =1+O13*4/O9 -> 1 | P17: =1+P13*4/P9 -> 1.0006419 | ... AB17: =1+AB13*4/AB9 -> 0.99425017 | AE17: =1+AE13*12/AE9 -> 1 | AF17: =1+AF13*12/AF9 -> 1 | AG17: =1+AG13*12/AG9 -> 1 | AH17: =1+AH13*12/AH9 -> 1 | AI17: =1+AI13*12/AI9 -> 1 | AJ17: =1+AJ13*12/AJ9 -> 1 | AK17: =1+AK13*12/AK9 -> 1 | AL17: =1+AL13*12/AL9 -> 1 | ... CK17: =1+CK13*12/CK9 -> 0.99141648
B18: Gross Retention (c + d) | C18: =1+SUM(C12:C13)/C9 -> 0.89253497 | D18: =1+SUM(D12:D13)/D9 -> 0.88452409 | E18: =1+SUM(E12:E13)/E9 -> 0.8066709 | F18: =1+SUM(F12:F13)/F9 -> 0.81450367 | G18: =1+SUM(G12:G13)/G9 -> 0.83674729 | I18: =1+SUM(I12:I13)*4/I9 -> 0.99720738 | J18: =1+SUM(J12:J13)*4/J9 -> 0.83266928 | K18: =1+SUM(K12:K13)*4/K9 -> 0.95559637 | L18: =1+SUM(L12:L13)*4/L9 -> 0.84800153 | M18: =1+SUM(M12:M13)*4/M9 -> 0.92002974 | N18: =1+SUM(N12:N13)*4/N9 -> 0.98348137 | O18: =1+SUM(O12:O13)*4/O9 -> 0.9090695 | P18: =1+SUM(P12:P13)*4/P9 -> 0.88160052 | ... AB18: =1+SUM(AB12:AB13)*4/AB9 -> 0.90675124 | AE18: =1+SUM(AE12:AE13)*12/AE9 -> 0.9919778 | AF18: =1+SUM(AF12:AF13)*12/AF9 -> 1 | AG18: =1+SUM(AG12:AG13)*12/AG9 -> 0.85597716 | AH18: =1+SUM(AH12:AH13)*12/AH9 -> 0.8867653 | AI18: =1+SUM(AI12:AI13)*12/AI9 -> 0.7563474 | AJ18: =1+SUM(AJ12:AJ13)*12/AJ9 -> 0.88676424 | AK18: =1+SUM(AK12:AK13)*12/AK9 -> 0.97994345 | AL18: =1+SUM(AL12:AL13)*12/AL9 -> 0.99999937 | ... CK18: =1+SUM(CK12:CK13)*12/CK9 -> 0.89743166
B19: Net Retention | C19: =1+SUM(C11:C13)/C9 -> 1.1447291 | D19: =1+SUM(D11:D13)/D9 -> 1.4760564 | E19: =1+SUM(E11:E13)/E9 -> 1.2328788 | F19: =1+SUM(F11:F13)/F9 -> 1.1342743 | G19: =1+SUM(G11:G13)/G9 -> 1.1328482 | I19: =1+SUM(I11:I13)*4/I9 -> 1.3085978 | J19: =1+SUM(J11:J13)*4/J9 -> 0.86542304 | K19: =1+SUM(K11:K13)*4/K9 -> 1.2576843 | L19: =1+SUM(L11:L13)*4/L9 -> 1.1069775 | M19: =1+SUM(M11:M13)*4/M9 -> 1.4661083 | N19: =1+SUM(N11:N13)*4/N9 -> 1.3683358 | O19: =1+SUM(O11:O13)*4/O9 -> 1.1905199 | P19: =1+SUM(P11:P13)*4/P9 -> 1.3862008 | ... AB19: =1+SUM(AB11:AB13)*4/AB9 -> 1.2645903 | AE19: =1+SUM(AE11:AE13)*12/AE9 -> 1.1604306 | AF19: =1+SUM(AF11:AF13)*12/AF9 -> 1.2892368 | AG19: =1+SUM(AG11:AG13)*12/AG9 -> 0.86448251 | AH19: =1+SUM(AH11:AH13)*12/AH9 -> 0.9740452 | AI19: =1+SUM(AI11:AI13)*12/AI9 -> 0.75887429 | AJ19: =1+SUM(AJ11:AJ13)*12/AJ9 -> 0.88676424 | AK19: =1+SUM(AK11:AK13)*12/AK9 -> 1.2716102 | AL19: =1+SUM(AL11:AL13)*12/AL9 -> 1.589483 | ... CK19: =1+SUM(CK11:CK13)*12/CK9 -> 1.4177914
B21: Net New ARR | C21: =SUM(C10:C13) -> 299830.77 | D21: =SUM(D10:D13) -> 1172701 | E21: =SUM(E10:E13) -> 1779394.1 | F21: =SUM(F10:F13) -> 1225286.3 | G21: =SUM(G10:G13) -> 2639261 | I21: =SUM(I10:I13) -> 66576.938 | J21: =SUM(J10:J13) -> -6092.4199 | K21: =SUM(K10:K13) -> 146537.27 | L21: =SUM(L10:L13) -> 92808.986 | M21: =SUM(M10:M13) -> 153946.98 | N21: =SUM(N10:N13) -> 456088.67 | O21: =SUM(O10:O13) -> 238004.35 | P21: =SUM(P10:P13) -> 324660.96 | ... AB21: =SUM(AB10:AB13) -> 1040579.8 | AE21: =SUM(AE10:AE13) -> 10983.969 | AF21: =SUM(AF10:AF13) -> 23887.466 | AG21: =SUM(AG10:AG13) -> -563.56844 | AH21: =SUM(AH10:AH13) -> 4296.9692 | AI21: =SUM(AI10:AI13) -> -9825.8207 | AJ21: =SUM(AJ10:AJ13) -> -3174.4278 | AK21: =SUM(AK10:AK13) -> 37788.329 | AL21: =SUM(AL10:AL13) -> 111923.36 | ... CK21: =SUM(CK10:CK13) -> 771315.1
B22: New + Upsell | C22: =SUM(C10:C11) -> 376683.2 | D22: =SUM(D10:D11) -> 1289905.5 | E22: =SUM(E10:E11) -> 2202334.5 | F22: =SUM(F10:F11) -> 1961162.3 | G22: =SUM(G10:G11) -> 3486926.4 | I22: =SUM(I10:I11) -> 67076.216 | J22: =SUM(J10:J11) -> 26608.851 | K22: =SUM(K10:K11) -> 155147.39 | L22: =SUM(L10:L11) -> 127850.74 | M22: =SUM(M10:M11) -> 174238.83 | N22: =SUM(N10:N11) -> 460915.89 | O22: =SUM(O10:O11) -> 274944.98 | P22: =SUM(P10:P11) -> 379805.81 | ... AB22: =SUM(AB10:AB11) -> 1198893.6 | AE22: =SUM(AE10:AE11) -> 11483.247 | AF22: =SUM(AF10:AF11) -> 23887.466 | AG22: =SUM(AG10:AG11) -> 8818.5099 | AH22: =SUM(AH10:AH11) -> 11668.098 | AI22: =SUM(AI10:AI11) -> 6122.2424 | AJ22: =SUM(AJ10:AJ11) -> 4144.5983 | AK22: =SUM(AK10:AK11) -> 39079.384 | AL22: =SUM(AL10:AL11) -> 111923.41 | ... CK22: =SUM(CK10:CK11) -> 831662.01
B24: Customer Count
B25: Beginning Logos | C25: =I25 -> 25 | D25: =C28 -> 79 | E25: =D28 -> 155 | F25: =E28 -> 258 | G25: =+SUMIFS($AD$28:$CL$28,$AD$8:$CL$8,EOMONTH(G8,-12)) -> 333 | I25: =AD25 -> 25 | J25: =I28 -> 36 | K25: =J28 -> 45 | L25: =K28 -> 59 | M25: =L28 -> 79 | N25: =M28 -> 93 | O25: =N28 -> 115 | P25: =O28 -> 131 | Q25: =P28 -> 155 | ... AB25: =AA28 -> 383 | AD25: 25 | AE25: =AD28 -> 28 | AF25: =AE28 -> 31 | AG25: =AF28 -> 36 | AH25: =AG28 -> 39 | AI25: =AH28 -> 41 | AJ25: =AI28 -> 45 | AK25: =AJ28 -> 49 | AL25: =AK28 -> 53 | ... CK25: =CJ28 -> 385
B26: (+) New | C26: =SUMIFS($I26:$W26,$I$7:$W$7,C$7) -> 54 | D26: =SUMIFS($I26:$W26,$I$7:$W$7,D$7) -> 76 | E26: =SUMIFS($I26:$W26,$I$7:$W$7,E$7) -> 105 | F26: =SUMIFS($I26:$AC26,$I$7:$AC$7,F$7) -> 92 | G26: =+SUM(OFFSET(INDEX($AD26:$CL26,MATCH(G$8,$AD$8:$CL$8,0)),,,,-12)) -> 95 | I26: =SUMIFS($AD26:$BT26,$AD$5:$BT$5,I$5) -> 11 | J26: =SUMIFS($AD26:$BT26,$AD$5:$BT$5,J$5) -> 9 | K26: =SUMIFS($AD26:$BT26,$AD$5:$BT$5,K$5) -> 14 | L26: =SUMIFS($AD26:$BT26,$AD$5:$BT$5,L$5) -> 20 | M26: =SUMIFS($AD26:$BT26,$AD$5:$BT$5,M$5) -> 14 | N26: =SUMIFS($AD26:$BT26,$AD$5:$BT$5,N$5) -> 22 | O26: =SUMIFS($AD26:$BT26,$AD$5:$BT$5,O$5) -> 16 | P26: =SUMIFS($AD26:$BT26,$AD$5:$BT$5,P$5) -> 24 | ... V26: =SUMIFS($AD26:$BT26,$AD$5:$BT$5,V$5) -> 26 | W26: =SUMIFS($AD26:$BV26,$AD$5:$BV$5,W$5) -> 19 | X26: =SUMIFS($AD26:$BY26,$AD$5:$BY$5,X$5) -> 25 | Y26: =SUMIFS($AD26:$CL26,$AD$5:$CL$5,Y$5) -> 23 | Z26: =SUMIFS($AD26:$CL26,$AD$5:$CL$5,Z$5) -> 24 | AA26: =SUMIFS($AD26:$CL26,$AD$5:$CL$5,AA$5) -> 27 | AB26: =SUMIFS($AD26:$CL26,$AD$5:$CL$5,AB$5) -> 21 | AD26: =+SUM('MRR Schedule Summary'!C36:C37) -> 3 | AE26: =+SUM('MRR Schedule Summary'!D36:D37) -> 3 | AF26: =+SUM('MRR Schedule Summary'!E36:E37) -> 5 | AG26: =+SUM('MRR Schedule Summary'!F36:F37) -> 3 | AH26: =+SUM('MRR Schedule Summary'!G36:G37) -> 2 | AI26: =+SUM('MRR Schedule Summary'!H36:H37) -> 4 | AJ26: =+SUM('MRR Schedule Summary'!I36:I37) -> 4 | AK26: =+SUM('MRR Schedule Summary'!J36:J37) -> 4 | ... CK26: =+SUM('MRR Schedule Summary'!BJ36:BJ37) -> 13
B27: (-) Cancel | C27: =SUMIFS($I27:$W27,$I$7:$W$7,C$7) -> 0 | D27: =SUMIFS($I27:$W27,$I$7:$W$7,D$7) -> 0 | E27: =SUMIFS($I27:$W27,$I$7:$W$7,E$7) -> -2 | F27: =SUMIFS($I27:$AC27,$I$7:$AC$7,F$7) -> -17 | G27: =+SUM(OFFSET(INDEX($AD27:$CL27,MATCH(G$8,$AD$8:$CL$8,0)),,,,-12)) -> -36 | I27: =SUMIFS($AD27:$BT27,$AD$5:$BT$5,I$5) -> 0 | J27: =SUMIFS($AD27:$BT27,$AD$5:$BT$5,J$5) -> 0 | K27: =SUMIFS($AD27:$BT27,$AD$5:$BT$5,K$5) -> 0 | L27: =SUMIFS($AD27:$BT27,$AD$5:$BT$5,L$5) -> 0 | M27: =SUMIFS($AD27:$BT27,$AD$5:$BT$5,M$5) -> 0 | N27: =SUMIFS($AD27:$BT27,$AD$5:$BT$5,N$5) -> 0 | O27: =SUMIFS($AD27:$BT27,$AD$5:$BT$5,O$5) -> 0 | P27: =SUMIFS($AD27:$BT27,$AD$5:$BT$5,P$5) -> 0 | ... V27: =SUMIFS($AD27:$BT27,$AD$5:$BT$5,V$5) -> -3 | W27: =SUMIFS($AD27:$BV27,$AD$5:$BV$5,W$5) -> -4 | X27: =SUMIFS($AD27:$BY27,$AD$5:$BY$5,X$5) -> -7 | Y27: =SUMIFS($AD27:$CL27,$AD$5:$CL$5,Y$5) -> -7 | Z27: =SUMIFS($AD27:$CL27,$AD$5:$CL$5,Z$5) -> -11 | AA27: =SUMIFS($AD27:$CL27,$AD$5:$CL$5,AA$5) -> -6 | AB27: =SUMIFS($AD27:$CL27,$AD$5:$CL$5,AB$5) -> -12 | AD27: =+'MRR Schedule Summary'!C38 -> 0 | AE27: =+'MRR Schedule Summary'!D38 -> 0 | AF27: =+'MRR Schedule Summary'!E38 -> 0 | AG27: =+'MRR Schedule Summary'!F38 -> 0 | AH27: =+'MRR Schedule Summary'!G38 -> 0 | AI27: =+'MRR Schedule Summary'!H38 -> 0 | AJ27: =+'MRR Schedule Summary'!I38 -> 0 | AK27: =+'MRR Schedule Summary'!J38 -> 0 | ... CK27: =+'MRR Schedule Summary'!BJ38 -> -6
B28: Ending Logos | C28: =SUM(C25:C27) -> 79 | D28: =SUM(D25:D27) -> 155 | E28: =SUM(E25:E27) -> 258 | F28: =SUM(F25:F27) -> 333 | G28: =SUM(G25:G27) -> 392 | I28: =SUM(I25:I27) -> 36 | J28: =SUM(J25:J27) -> 45 | K28: =SUM(K25:K27) -> 59 | L28: =SUM(L25:L27) -> 79 | M28: =SUM(M25:M27) -> 93 | N28: =SUM(N25:N27) -> 115 | O28: =SUM(O25:O27) -> 131 | P28: =SUM(P25:P27) -> 155 | ... AB28: =SUM(AB25:AB27) -> 392 | AD28: =SUM(AD25:AD27) -> 28 | AE28: =SUM(AE25:AE27) -> 31 | AF28: =SUM(AF25:AF27) -> 36 | AG28: =SUM(AG25:AG27) -> 39 | AH28: =SUM(AH25:AH27) -> 41 | AI28: =SUM(AI25:AI27) -> 45 | AJ28: =SUM(AJ25:AJ27) -> 49 | AK28: =SUM(AK25:AK27) -> 53 | ... CK28: =SUM(CK25:CK27) -> 392
B30: Logo Retention | C30: =1+C27/C28 -> 1 | D30: =1+D27/D28 -> 1 | E30: =1+E27/E28 -> 0.99224806 | F30: =1+F27/F28 -> 0.94894895 | G30: =1+G27/G28 -> 0.90816327 | I30: =1+I27*4/I25 -> 1 | J30: =1+J27*4/J25 -> 1 | K30: =1+K27*4/K25 -> 1 | L30: =1+L27*4/L25 -> 1 | M30: =1+M27*4/M25 -> 1 | N30: =1+N27*4/N25 -> 1 | O30: =1+O27*4/O25 -> 1 | P30: =1+P27*4/P25 -> 1 | ... AB30: =1+AB27*4/AB25 -> 0.87467363 | AD30: =1+AD27*12/AD25 -> 1 | AE30: =1+AE27*12/AE25 -> 1 | AF30: =1+AF27*12/AF25 -> 1 | AG30: =1+AG27*12/AG25 -> 1 | AH30: =1+AH27*12/AH25 -> 1 | AI30: =1+AI27*12/AI25 -> 1 | AJ30: =1+AJ27*12/AJ25 -> 1 | AK30: =1+AK27*12/AK25 -> 1 | ... CK30: =1+CK27*12/CK25 -> 0.81298701
B32: Avg. ARR / Cust | C32: =C14/C28 -> 12847.718 | D32: =D14/D28 -> 14114.004 | E32: =E14/E28 -> 15376.22 | F32: =F14/F28 -> 15592.646 | G32: =G14/G28 -> 19978.602 | I32: =I14/I28 -> 21714.33 | J32: =J14/J28 -> 17236.077 | K32: =K14/K28 -> 15629.843 | L32: =L14/L28 -> 12847.718 | M32: =M14/M28 -> 12568.997 | N32: =N14/N28 -> 14130.481 | O32: =O14/O28 -> 14221.448 | P32: =P14/P28 -> 14114.004 | ... AB32: =AB14/AB28 -> 19978.602 | AE32: =AE14/AE28 -> 24446.077 | AF32: =AF14/AF28 -> 21714.33 | AG32: =AG14/AG28 -> 20029.546 | AH32: =AH14/AH28 -> 19157.299 | AI32: =AI14/AI28 -> 17236.077 | AJ32: =AJ14/AJ28 -> 15764.266 | AK32: =AK14/AK28 -> 15287.497 | AL32: =AL14/AL28 -> 15629.843 | ... CK32: =CK14/CK28 -> 19978.602
B33: Avg. ARR / New | C33: =C10/C26 -> 3635.7285 | D33: =D10/D26 -> 9072.6068 | E33: =E10/E26 -> 12094.59 | F33: =F10/F26 -> 7528.3854 | G33: =G10/G26 -> 20520.702 | I33: =I10/I26 -> 1036.761 | J33: =J10/J26 -> 2245.3129 | K33: =K10/K26 -> 6897.9127 | L33: =L10/L26 -> 3407.3187 | M33: =M10/M26 -> 2548.2517 | N33: =N10/N26 -> 15838.646 | O33: =O10/O26 -> 10037.836 | P33: =P10/P26 -> 6032.7921 | ... AB33: =AB10/AB26 -> 28160.45 | AE33: =AE10/AE26 -> 333.08072 | AF33: =AF10/AF26 -> 1124.2956 | AG33: =AG10/AG26 -> 2754.8152 | AH33: =AH10/AH26 -> 2993.2618 | AI33: =AI10/AI26 -> 1489.2117 | AJ33: =AJ10/AJ26 -> 1036.1496 | AK33: =AK10/AK26 -> 5076.1441 | AL33: =AL10/AL26 -> 12020.267 | ... CK33: =CK10/CK26 -> 40423.395
B34: Avg. ARR / Churn | C34: =IFERROR(C13/C27,"NA") -> NA | D34: =IFERROR(D13/D27,"NA") -> NA | E34: =IFERROR(E13/E27,"NA") -> 45.343239 | F34: =IFERROR(F13/F27,"NA") -> 2552.1451 | G34: =IFERROR(G13/G27,"NA") -> 1436.6302 | I34: =IFERROR(I13/I27,"NA") -> NA | J34: =IFERROR(J13/J27,"NA") -> NA | K34: =IFERROR(K13/K27,"NA") -> NA | L34: =IFERROR(L13/L27,"NA") -> NA | M34: =IFERROR(M13/M27,"NA") -> NA | N34: =IFERROR(N13/N27,"NA") -> NA | O34: =IFERROR(O13/O27,"NA") -> NA | P34: =IFERROR(P13/P27,"NA") -> NA | ... AB34: =IFERROR(AB13/AB27,"NA") -> 813.48474 | AE34: =IFERROR(AE13/AE27,"NA") -> NA | AF34: =IFERROR(AF13/AF27,"NA") -> NA | AG34: =IFERROR(AG13/AG27,"NA") -> NA | AH34: =IFERROR(AH13/AH27,"NA") -> NA | AI34: =IFERROR(AI13/AI27,"NA") -> NA | AJ34: =IFERROR(AJ13/AJ27,"NA") -> NA | AK34: =IFERROR(AK13/AK27,"NA") -> NA | AL34: =IFERROR(AL13/AL27,"NA") -> NA | ... CK34: =IFERROR(CK13/CK27,"NA") -> 841.69748
C36: =C37&" " &YEAR(C39) -> Q4 2021 | D36: =D37&" " &YEAR(D39) -> Q4 2022 | E36: =E37&" " &YEAR(E39) -> Q4 2023 | F36: =F37&" " &YEAR(F39) -> Q4 2024 | G36: =G37&" " &YEAR(G39) -> TTM 2025 | I36: =I37&" " &YEAR(I39) -> Q1 2021 | J36: =J37&" " &YEAR(J39) -> Q2 2021 | K36: =K37&" " &YEAR(K39) -> Q3 2021 | L36: =L37&" " &YEAR(L39) -> Q4 2021 | M36: =M37&" " &YEAR(M39) -> Q1 2022 | N36: =N37&" " &YEAR(N39) -> Q2 2022 | O36: =O37&" " &YEAR(O39) -> Q3 2022 | P36: =P37&" " &YEAR(P39) -> Q4 2022 | ... AB36: =AB37&" " &YEAR(AB39) -> Q4 2025 | AD36: =AD37&" " &YEAR(AD39) -> Q1 2021 | AE36: =AE37&" " &YEAR(AE39) -> Q1 2021 | AF36: =AF37&" " &YEAR(AF39) -> Q1 2021 | AG36: =AG37&" " &YEAR(AG39) -> Q2 2021 | AH36: =AH37&" " &YEAR(AH39) -> Q2 2021 | AI36: =AI37&" " &YEAR(AI39) -> Q2 2021 | AJ36: =AJ37&" " &YEAR(AJ39) -> Q3 2021 | AK36: =AK37&" " &YEAR(AK39) -> Q3 2021 | ... CK36: =CK37&" " &YEAR(CK39) -> Q4 2025
C37: Q4 | D37: Q4 | E37: Q4 | F37: Q4 | G37: TTM | I37: =+I6 -> Q1 | J37: =+J6 -> Q2 | K37: =+K6 -> Q3 | L37: =+L6 -> Q4 | M37: =+M6 -> Q1 | N37: =+N6 -> Q2 | O37: =+O6 -> Q3 | P37: =+P6 -> Q4 | ... AB37: =+AB6 -> Q4 | AD37: =+AD6 -> Q1 | AE37: =+AE6 -> Q1 | AF37: =+AF6 -> Q1 | AG37: =+AG6 -> Q2 | AH37: =+AH6 -> Q2 | AI37: =+AI6 -> Q2 | AJ37: =+AJ6 -> Q3 | AK37: =+AK6 -> Q3 | ... CK37: =+CK6 -> Q4
C38: =YEAR(C39) -> 2021 | D38: =YEAR(D39) -> 2022 | E38: =YEAR(E39) -> 2023 | F38: =YEAR(F39) -> 2024 | G38: =YEAR(G39) -> 2025 | I38: =YEAR(I39) -> 2021 | J38: =YEAR(J39) -> 2021 | K38: =YEAR(K39) -> 2021 | L38: =YEAR(L39) -> 2021 | M38: =YEAR(M39) -> 2022 | N38: =YEAR(N39) -> 2022 | O38: =YEAR(O39) -> 2022 | P38: =YEAR(P39) -> 2022 | ... AB38: =YEAR(AB39) -> 2025 | AD38: =YEAR(AD39) -> 2021 | AE38: =YEAR(AE39) -> 2021 | AF38: =YEAR(AF39) -> 2021 | AG38: =YEAR(AG39) -> 2021 | AH38: =YEAR(AH39) -> 2021 | AI38: =YEAR(AI39) -> 2021 | AJ38: =YEAR(AJ39) -> 2021 | AK38: =YEAR(AK39) -> 2021 | ... CK38: =YEAR(CK39) -> 2025
B39: Industrial Sales Efficiency | C39: 44561 | D39: =EOMONTH(C39,12) -> 44926 | E39: =EOMONTH(D39,12) -> 45291 | F39: =EOMONTH(E39,12) -> 45657 | G39: =+G8 -> 46022 | I39: =+I8 -> 44286 | J39: =+J8 -> 44377 | K39: =+K8 -> 44469 | L39: =+L8 -> 44561 | M39: =+M8 -> 44651 | N39: =+N8 -> 44742 | O39: =+O8 -> 44834 | P39: =+P8 -> 44926 | ... AB39: =+AB8 -> 46022 | AD39: =+AD8 -> 44227 | AE39: =+AE8 -> 44255 | AF39: =+AF8 -> 44286 | AG39: =+AG8 -> 44316 | AH39: =+AH8 -> 44347 | AI39: =+AI8 -> 44377 | AJ39: =+AJ8 -> 44408 | AK39: =+AK8 -> 44439 | ... CK39: =+CK8 -> 46022
B41: Customer Lifetime Value
B42: New + Upsell | C42: =SUM(C10:C11) -> 376683.2 | D42: =SUM(D10:D11) -> 1289905.5 | E42: =SUM(E10:E11) -> 2202334.5 | F42: =SUM(F10:F11) -> 1961162.3 | G42: =SUM(G10:G11) -> 3486926.4 | I42: =SUM(I10:I11) -> 67076.216 | J42: =SUM(J10:J11) -> 26608.851 | K42: =SUM(K10:K11) -> 155147.39 | L42: =SUM(L10:L11) -> 127850.74 | M42: =SUM(M10:M11) -> 174238.83 | N42: =SUM(N10:N11) -> 460915.89 | O42: =SUM(O10:O11) -> 274944.98 | P42: =SUM(P10:P11) -> 379805.81 | ... AB42: =SUM(AB10:AB11) -> 1198893.6 | AD42: =SUM(AD10:AD11) -> 31705.503 | AE42: =SUM(AE10:AE11) -> 11483.247 | AF42: =SUM(AF10:AF11) -> 23887.466 | AG42: =SUM(AG10:AG11) -> 8818.5099 | AH42: =SUM(AH10:AH11) -> 11668.098 | AI42: =SUM(AI10:AI11) -> 6122.2424 | AJ42: =SUM(AJ10:AJ11) -> 4144.5983 | AK42: =SUM(AK10:AK11) -> 39079.384 | ... CK42: =SUM(CK10:CK11) -> 831662.01
B43: Gross Margin | C43: 0.7049489 | D43: =+'Cons TrioMobil | Yearly'!E20 -> 0.72510895 | E43: =+'Cons TrioMobil | Yearly'!F20 -> 0.75651534 | F43: =+'Cons TrioMobil | Yearly'!G20 -> 0.77942405 | G43: =+'Cons TrioMobil | Monthly'!BX24 -> 0.75533729 | I43: =AVERAGEIFS($AD43:$BT43,$AD$36:$BT$36,I$36) -> 0.70331208 | J43: =AVERAGEIFS($AD43:$BT43,$AD$36:$BT$36,J$36) -> 0.75287296 | K43: =AVERAGEIFS($AD43:$BT43,$AD$36:$BT$36,K$36) -> 0.73170588 | L43: =AVERAGEIFS($AD43:$BT43,$AD$36:$BT$36,L$36) -> 0.76169227 | M43: =AVERAGEIFS($AD43:$BT43,$AD$36:$BT$36,M$36) -> 0.72432258 | N43: =AVERAGEIFS($AD43:$BT43,$AD$36:$BT$36,N$36) -> 0.70519993 | O43: =AVERAGEIFS($AD43:$BT43,$AD$36:$BT$36,O$36) -> 0.72702076 | P43: =AVERAGEIFS($AD43:$BT43,$AD$36:$BT$36,P$36) -> 0.73995139 | ... V43: =AVERAGEIFS($AD43:$BT43,$AD$36:$BT$36,V$36) -> 0.78066093 | W43: =AVERAGEIFS($AD43:$BV43,$AD$36:$BV$36,W$36) -> 0.77526965 | X43: =AVERAGEIFS($AD43:$BY43,$AD$36:$BY$36,X$36) -> 0.78768385 | Y43: =AVERAGEIFS($AD43:$CL43,$AD$36:$CL$36,Y$36) -> 0.76892265 | Z43: =AVERAGEIFS($AD43:$CL43,$AD$36:$CL$36,Z$36) -> 0.75446338 | AA43: =AVERAGEIFS($AD43:$CL43,$AD$36:$CL$36,AA$36) -> 0.75623831 | AB43: =AVERAGEIFS($AD43:$CL43,$AD$36:$CL$36,AB$36) -> 0.74171109 | AD43: =+'Cons TrioMobil | Monthly'!O24 -> 0.66228422 | AE43: =+'Cons TrioMobil | Monthly'!P24 -> 0.72075982 | AF43: =+'Cons TrioMobil | Monthly'!Q24 -> 0.72689219 | AG43: =+'Cons TrioMobil | Monthly'!R24 -> 0.78612543 | AH43: =+'Cons TrioMobil | Monthly'!S24 -> 0.74211799 | AI43: =+'Cons TrioMobil | Monthly'!T24 -> 0.73037545 | AJ43: =+'Cons TrioMobil | Monthly'!U24 -> 0.7471152 | AK43: =+'Cons TrioMobil | Monthly'!V24 -> 0.6971837 | ... CK43: =+'Cons TrioMobil | Monthly'!BV24 -> 0.72957513
B44: Gross Profit | C44: =C43*C42 -> 265542.41 | D44: =D43*D42 -> 935322.03 | E44: =E43*E42 -> 1666099.8 | F44: =F43*F42 -> 1528577 | G44: =G43*G42 -> 2633805.5 | I44: =I43*I42 -> 47175.513 | J44: =J43*J42 -> 20033.084 | K44: =K43*K42 -> 113522.26 | L44: =L43*L42 -> 97382.921 | M44: =M43*M42 -> 126205.12 | N44: =N43*N42 -> 325037.86 | O44: =O43*O42 -> 199890.71 | P44: =P43*P42 -> 281037.84 | ... AB44: =AB43*AB42 -> 889232.68 | AD44: =AD43*AD42 -> 20998.055 | AE44: =AE43*AE42 -> 8276.6632 | AF44: =AF43*AF42 -> 17363.612 | AG44: =AG43*AG42 -> 6932.4549 | AH44: =AH43*AH42 -> 8659.1056 | AI44: =AI43*AI42 -> 4471.5355 | AJ44: =AJ43*AJ42 -> 3096.4924 | AK44: =AK43*AK42 -> 27245.509 | ... CK44: =CK43*CK42 -> 606759.92
B46: Logo Retention | C46: =C30 -> 1 | D46: =D30 -> 1 | E46: =E30 -> 0.99224806 | F46: =F30 -> 0.94894895 | G46: =G30 -> 0.90816327 | I46: =I30 -> 1 | J46: =J30 -> 1 | K46: =K30 -> 1 | L46: =L30 -> 1 | M46: =M30 -> 1 | N46: =N30 -> 1 | O46: =O30 -> 1 | P46: =P30 -> 1 | ... AB46: =AB30 -> 0.87467363 | AD46: =AD30 -> 1 | AE46: =AE30 -> 1 | AF46: =AF30 -> 1 | AG46: =AG30 -> 1 | AH46: =AH30 -> 1 | AI46: =AI30 -> 1 | AJ46: =AJ30 -> 1 | AK46: =AK30 -> 1 | ... CK46: =CK30 -> 0.81298701
B47: Implied Customer Years (Calculated) | C47: =IF(C46=100%,100,IFERROR(1/(1-C46),"NA")) -> 100 | D47: =IF(D46=100%,100,IFERROR(1/(1-D46),"NA")) -> 100 | E47: =IF(E46=100%,100,IFERROR(1/(1-E46),"NA")) -> 129 | F47: =IF(F46=100%,100,IFERROR(1/(1-F46),"NA")) -> 19.588235 | G47: =IF(G46=100%,100,IFERROR(1/(1-G46),"NA")) -> 10.888889 | I47: =IF(I46=100%,100,IFERROR(1/(1-I46),"NA")) -> 100 | J47: =IF(J46=100%,100,IFERROR(1/(1-J46),"NA")) -> 100 | K47: =IF(K46=100%,100,IFERROR(1/(1-K46),"NA")) -> 100 | L47: =IF(L46=100%,100,IFERROR(1/(1-L46),"NA")) -> 100 | M47: =IF(M46=100%,100,IFERROR(1/(1-M46),"NA")) -> 100 | N47: =IF(N46=100%,100,IFERROR(1/(1-N46),"NA")) -> 100 | O47: =IF(O46=100%,100,IFERROR(1/(1-O46),"NA")) -> 100 | P47: =IF(P46=100%,100,IFERROR(1/(1-P46),"NA")) -> 100 | ... AB47: =IF(AB46=100%,100,IFERROR(1/(1-AB46),"NA")) -> 7.9791667 | AD47: =IF(AD46=100%,100,IFERROR(1/(1-AD46),"NA")) -> 100 | AE47: =IF(AE46=100%,100,IFERROR(1/(1-AE46),"NA")) -> 100 | AF47: =IF(AF46=100%,100,IFERROR(1/(1-AF46),"NA")) -> 100 | AG47: =IF(AG46=100%,100,IFERROR(1/(1-AG46),"NA")) -> 100 | AH47: =IF(AH46=100%,100,IFERROR(1/(1-AH46),"NA")) -> 100 | AI47: =IF(AI46=100%,100,IFERROR(1/(1-AI46),"NA")) -> 100 | AJ47: =IF(AJ46=100%,100,IFERROR(1/(1-AJ46),"NA")) -> 100 | AK47: =IF(AK46=100%,100,IFERROR(1/(1-AK46),"NA")) -> 100 | ... CK47: =IF(CK46=100%,100,IFERROR(1/(1-CK46),"NA")) -> 5.3472222
B48: Implied Customer Years (Capped) | C48: =MIN(C47,5) -> 5 | D48: =MIN(D47,5) -> 5 | E48: =MIN(E47,5) -> 5 | F48: =MIN(F47,5) -> 5 | G48: =MIN(G47,5) -> 5 | I48: =MIN(I47,5) -> 5 | J48: =MIN(J47,5) -> 5 | K48: =MIN(K47,5) -> 5 | L48: =MIN(L47,5) -> 5 | M48: =MIN(M47,5) -> 5 | N48: =MIN(N47,5) -> 5 | O48: =MIN(O47,5) -> 5 | P48: =MIN(P47,5) -> 5 | ... AB48: =MIN(AB47,5) -> 5 | AD48: =MIN(AD47,5) -> 5 | AE48: =MIN(AE47,5) -> 5 | AF48: =MIN(AF47,5) -> 5 | AG48: =MIN(AG47,5) -> 5 | AH48: =MIN(AH47,5) -> 5 | AI48: =MIN(AI47,5) -> 5 | AJ48: =MIN(AJ47,5) -> 5 | AK48: =MIN(AK47,5) -> 5 | ... CK48: =MIN(CK47,5) -> 5
B49: CLTV | C49: =C48*C44 -> 1327712 | D49: =D48*D44 -> 4676610.2 | E49: =E48*E44 -> 8330499.1 | F49: =F48*F44 -> 7642885.2 | G49: =G48*G44 -> 13169028 | I49: =I48*I44 -> 235877.57 | J49: =J48*J44 -> 100165.42 | K49: =K48*K44 -> 567611.29 | L49: =L48*L44 -> 486914.6 | M49: =M48*M44 -> 631025.58 | N49: =N48*N44 -> 1625189.3 | O49: =O48*O44 -> 999453.56 | P49: =P48*P44 -> 1405189.2 | ... AB49: =AB48*AB44 -> 4446163.4 | AD49: =AD48*AD44 -> 104990.27 | AE49: =AE48*AE44 -> 41383.316 | AF49: =AF48*AF44 -> 86818.062 | AG49: =AG48*AG44 -> 34662.275 | AH49: =AH48*AH44 -> 43295.528 | AI49: =AI48*AI44 -> 22357.678 | AJ49: =AJ48*AJ44 -> 15482.462 | AK49: =AK48*AK44 -> 136227.55 | ... CK49: =CK48*CK44 -> 3033799.6
B51: Industrial CAC % | C51: 0.23865822 | D51: ='Cons TrioMobil | Yearly'!E8/SUM('Cons TrioMobil | Yearly'!E7:E8) -> 0.37976456 | E51: ='Cons TrioMobil | Yearly'!F8/SUM('Cons TrioMobil | Yearly'!F7:F8) -> 0.4611257 | F51: ='Cons TrioMobil | Yearly'!G8/SUM('Cons TrioMobil | Yearly'!G7:G8) -> 0.44956661 | G51: =+'Cons TrioMobil | Monthly'!BX12/SUM('Cons TrioMobil | Monthly'!BX11:BX12) -> 0.4332689 | I51: =AVERAGEIFS($AD51:$BT51,$AD$5:$BT$5,I$5) -> 0.21665655 | J51: =AVERAGEIFS($AD51:$BT51,$AD$5:$BT$5,J$5) -> 0.22532044 | K51: =AVERAGEIFS($AD51:$BT51,$AD$5:$BT$5,K$5) -> 0.23877169 | L51: =AVERAGEIFS($AD51:$BT51,$AD$5:$BT$5,L$5) -> 0.27337009 | M51: =AVERAGEIFS($AD51:$BT51,$AD$5:$BT$5,M$5) -> 0.30544583 | N51: =AVERAGEIFS($AD51:$BT51,$AD$5:$BT$5,N$5) -> 0.36521765 | O51: =AVERAGEIFS($AD51:$BT51,$AD$5:$BT$5,O$5) -> 0.40156879 | P51: =AVERAGEIFS($AD51:$BT51,$AD$5:$BT$5,P$5) -> 0.42607924 | ... V51: =AVERAGEIFS($AD51:$BT51,$AD$5:$BT$5,V$5) -> 0.45371936 | W51: =AVERAGEIFS($AD51:$BV51,$AD$5:$BV$5,W$5) -> 0.44464522 | X51: =AVERAGEIFS($AD51:$BY51,$AD$5:$BY$5,X$5) -> 0.43626317 | Y51: =AVERAGEIFS($AD51:$CL51,$AD$5:$CL$5,Y$5) -> 0.41619093 | Z51: =AVERAGEIFS($AD51:$CL51,$AD$5:$CL$5,Z$5) -> 0.41680311 | AA51: =AVERAGEIFS($AD51:$CL51,$AD$5:$CL$5,AA$5) -> 0.4372046 | AB51: =AVERAGEIFS($AD51:$CL51,$AD$5:$CL$5,AB$5) -> 0.45739685 | AD51: ='Cons TrioMobil | Monthly'!O12/SUM('Cons TrioMobil | Monthly'!O11:O12) -> 0.21159583 | AE51: ='Cons TrioMobil | Monthly'!P12/SUM('Cons TrioMobil | Monthly'!P11:P12) -> 0.21476638 | AF51: ='Cons TrioMobil | Monthly'!Q12/SUM('Cons TrioMobil | Monthly'!Q11:Q12) -> 0.22360743 | AG51: ='Cons TrioMobil | Monthly'!R12/SUM('Cons TrioMobil | Monthly'!R11:R12) -> 0.2236082 | AH51: ='Cons TrioMobil | Monthly'!S12/SUM('Cons TrioMobil | Monthly'!S11:S12) -> 0.22769289 | AI51: ='Cons TrioMobil | Monthly'!T12/SUM('Cons TrioMobil | Monthly'!T11:T12) -> 0.22466023 | AJ51: ='Cons TrioMobil | Monthly'!U12/SUM('Cons TrioMobil | Monthly'!U11:U12) -> 0.22685228 | AK51: ='Cons TrioMobil | Monthly'!V12/SUM('Cons TrioMobil | Monthly'!V11:V12) -> 0.23172167 | ... CK51: ='Cons TrioMobil | Monthly'!BV12/SUM('Cons TrioMobil | Monthly'!BV11:BV12) -> 0.47018008
B52: CAC (S&M) | C52: =SUMIFS($AD52:$BT52,$AD$7:$BT$7,C$7) -> 413384.86 | D52: =+SUM(OFFSET(INDEX($AD52:$CL52,MATCH(D$8,$AD$8:$CL$8,0)),,,,-12)) -> 1177373.8 | E52: =+SUM(OFFSET(INDEX($AD52:$CL52,MATCH(E$8,$AD$8:$CL$8,0)),,,,-12)) -> 2254752.1 | F52: =+SUM(OFFSET(INDEX($AD52:$CL52,MATCH(F$8,$AD$8:$CL$8,0)),,,,-12)) -> 3460820.4 | G52: =+SUM(OFFSET(INDEX($AD52:$CL52,MATCH(G$8,$AD$8:$CL$8,0)),,,,-12)) -> 4050453.2 | I52: =SUMIFS($AD52:$BT52,$AD$5:$BT$5,I$5) -> 73239.39 | J52: =SUMIFS($AD52:$BT52,$AD$5:$BT$5,J$5) -> 76446.642 | K52: =SUMIFS($AD52:$BT52,$AD$5:$BT$5,K$5) -> 113758.17 | L52: =SUMIFS($AD52:$BT52,$AD$5:$BT$5,L$5) -> 149940.66 | M52: =SUMIFS($AD52:$BT52,$AD$5:$BT$5,M$5) -> 190770.6 | N52: =SUMIFS($AD52:$BT52,$AD$5:$BT$5,N$5) -> 268536.58 | O52: =SUMIFS($AD52:$BT52,$AD$5:$BT$5,O$5) -> 333348.31 | P52: =SUMIFS($AD52:$BT52,$AD$5:$BT$5,P$5) -> 384718.31 | ... V52: =SUMIFS($AD52:$BT52,$AD$5:$BT$5,V$5) -> 869887.18 | W52: =SUMIFS($AD52:$BV52,$AD$5:$BV$5,W$5) -> 837571.6 | X52: =SUMIFS($AD52:$BY52,$AD$5:$BY$5,X$5) -> 882079.45 | Y52: =SUMIFS($AD52:$CL52,$AD$5:$CL$5,Y$5) -> 854815.18 | Z52: =SUMIFS($AD52:$CL52,$AD$5:$CL$5,Z$5) -> 917902.36 | AA52: =SUMIFS($AD52:$CL52,$AD$5:$CL$5,AA$5) -> 994574.58 | AB52: =SUMIFS($AD52:$CL52,$AD$5:$CL$5,AB$5) -> 1283161.1 | AD52: ='Cons TrioMobil | Monthly'!O256*-1*AD51 -> 21591.952 | AE52: ='Cons TrioMobil | Monthly'!P256*-1*AE51 -> 23552.103 | AF52: ='Cons TrioMobil | Monthly'!Q256*-1*AF51 -> 28095.335 | AG52: ='Cons TrioMobil | Monthly'!R256*-1*AG51 -> 23758.913 | AH52: ='Cons TrioMobil | Monthly'!S256*-1*AH51 -> 23078.89 | AI52: ='Cons TrioMobil | Monthly'!T256*-1*AI51 -> 29608.84 | AJ52: ='Cons TrioMobil | Monthly'!U256*-1*AJ51 -> 27862.942 | AK52: ='Cons TrioMobil | Monthly'!V256*-1*AK51 -> 33818.945 | ... CK52: ='Cons TrioMobil | Monthly'!BV256*-1*CK51 -> 479829.41
B53: CAC / New Logo | C53: =C52/C26 -> 7655.2752 | D53: =D52/D26 -> 15491.76 | E53: =E52/E26 -> 21473.83 | F53: =F52/F26 -> 37617.613 | G53: =G52/G26 -> 42636.35 | I53: =I52/I26 -> 6658.1264 | J53: =J52/J26 -> 8494.0713 | K53: =K52/K26 -> 8125.5837 | L53: =L52/L26 -> 7497.0329 | M53: =M52/M26 -> 13626.471 | N53: =N52/N26 -> 12206.208 | O53: =O52/O26 -> 20834.27 | P53: =P52/P26 -> 16029.93 | ... AB53: =AB52/AB26 -> 61102.91 | AD53: =AD52/AD26 -> 7197.3172 | AE53: =AE52/AE26 -> 7850.7012 | AF53: =AF52/AF26 -> 5619.067 | AG53: =AG52/AG26 -> 7919.6376 | AH53: =AH52/AH26 -> 11539.445 | AI53: =AI52/AI26 -> 7402.2099 | AJ53: =AJ52/AJ26 -> 6965.7355 | AK53: =AK52/AK26 -> 8454.7361 | ... CK53: =CK52/CK26 -> 36909.955
B55: LTV-CAC | C55: =C49/C52 -> 3.2118061 | D55: =D49/D52 -> 3.9720692 | E55: =E49/E52 -> 3.6946408 | F55: =F49/F52 -> 2.2084027 | G55: =G49/G52 -> 3.2512479 | I55: =I49/I52 -> 3.220638 | J55: =J49/J52 -> 1.3102658 | K55: =K49/K52 -> 4.9896309 | L55: =L49/L52 -> 3.2473821 | M55: =M49/M52 -> 3.3077717 | N55: =N49/N52 -> 6.0520221 | O55: =O49/O52 -> 2.9982259 | P55: =P49/P52 -> 3.6525144 | ... AB55: =AB49/AB52 -> 3.4650079 | AD55: =AD49/AD52 -> 4.8624726 | AE55: =AE49/AE52 -> 1.7570964 | AF55: =AF49/AF52 -> 3.0901238 | AG55: =AG49/AG52 -> 1.4589167 | AH55: =AH49/AH52 -> 1.8759797 | AI55: =AI49/AI52 -> 0.75510145 | AJ55: =AJ49/AJ52 -> 0.55566501 | AK55: =AK49/AK52 -> 4.0281431 | ... CK55: =CK49/CK52 -> 6.3226629
B56: Payback (months) | C56: =C44/C52*12 -> 7.7083347 | D56: =(D52/D44)*12 -> 15.105477 | E56: =(E52/E44)*12 -> 16.239738 | F56: =(F52/F44)*12 -> 27.168958 | G56: =(G52/G44)*12 -> 18.454453 | I56: =(I52/I44)*12 -> 18.629849 | J56: =(J52/J44)*12 -> 45.792236 | K56: =(K52/K44)*12 -> 12.024938 | L56: =(L52/L44)*12 -> 18.476421 | M56: =(M52/M44)*12 -> 18.1391 | N56: =(N52/N44)*12 -> 9.9140419 | O56: =(O52/O44)*12 -> 20.011834 | P56: =(P52/P44)*12 -> 16.42704 | ... AB56: =(AB52/AB44)*12 -> 17.315978 | AD56: =AD52/AD44*12 -> 12.339401 | AE56: =AE52/AE44*12 -> 34.147245 | AF56: =AF52/AF44*12 -> 19.416698 | AG56: =AG52/AG44*12 -> 41.126406 | AH56: =AH52/AH44*12 -> 31.983289 | AI56: =AI52/AI44*12 -> 79.459522 | AJ56: =AJ52/AJ44*12 -> 107.97873 | AK56: =AK52/AK44*12 -> 14.895201 | ... CK56: =CK52/CK44*12 -> 9.4896725
B58: Check
B60: Ending ARR | C60: 0 | D60: =+INDEX('MRR Schedule Summary'!$B$31:$BK$31,MATCH(D$8,'MRR Schedule Summary'!$B$76:$BK$76,0))*12-D14 -> 0 | E60: =+INDEX('MRR Schedule Summary'!$B$31:$BK$31,MATCH(E$8,'MRR Schedule Summary'!$B$76:$BK$76,0))*12-E14 -> 0 | F60: =+INDEX('MRR Schedule Summary'!$B$31:$BK$31,MATCH(F$8,'MRR Schedule Summary'!$B$76:$BK$76,0))*12-F14 -> 0 | G60: =+INDEX('MRR Schedule Summary'!$B$31:$BK$31,MATCH(G$8,'MRR Schedule Summary'!$B$76:$BK$76,0))*12-G14 -> 0 | I60: =+INDEX('MRR Schedule Summary'!$B$31:$BK$31,MATCH(I$8,'MRR Schedule Summary'!$B$76:$BK$76,0))*12-I14 -> 0 | J60: =+INDEX('MRR Schedule Summary'!$B$31:$BK$31,MATCH(J$8,'MRR Schedule Summary'!$B$76:$BK$76,0))*12-J14 -> 0 | K60: =+INDEX('MRR Schedule Summary'!$B$31:$BK$31,MATCH(K$8,'MRR Schedule Summary'!$B$76:$BK$76,0))*12-K14 -> 0 | L60: =+INDEX('MRR Schedule Summary'!$B$31:$BK$31,MATCH(L$8,'MRR Schedule Summary'!$B$76:$BK$76,0))*12-L14 -> 0 | M60: =+INDEX('MRR Schedule Summary'!$B$31:$BK$31,MATCH(M$8,'MRR Schedule Summary'!$B$76:$BK$76,0))*12-M14 -> 0 | N60: =+INDEX('MRR Schedule Summary'!$B$31:$BK$31,MATCH(N$8,'MRR Schedule Summary'!$B$76:$BK$76,0))*12-N14 -> 0 | O60: =+INDEX('MRR Schedule Summary'!$B$31:$BK$31,MATCH(O$8,'MRR Schedule Summary'!$B$76:$BK$76,0))*12-O14 -> 0 | P60: =+INDEX('MRR Schedule Summary'!$B$31:$BK$31,MATCH(P$8,'MRR Schedule Summary'!$B$76:$BK$76,0))*12-P14 -> 0 | ... AB60: =+INDEX('MRR Schedule Summary'!$B$31:$BK$31,MATCH(AB$8,'MRR Schedule Summary'!$B$76:$BK$76,0))*12-AB14 -> 0 | AD60: =+INDEX('MRR Schedule Summary'!$B$31:$BK$31,MATCH(AD$8,'MRR Schedule Summary'!$B$76:$BK$76,0))*12-AD14 -> 0 | AE60: =+INDEX('MRR Schedule Summary'!$B$31:$BK$31,MATCH(AE$8,'MRR Schedule Summary'!$B$76:$BK$76,0))*12-AE14 -> 0 | AF60: =+INDEX('MRR Schedule Summary'!$B$31:$BK$31,MATCH(AF$8,'MRR Schedule Summary'!$B$76:$BK$76,0))*12-AF14 -> 0 | AG60: =+INDEX('MRR Schedule Summary'!$B$31:$BK$31,MATCH(AG$8,'MRR Schedule Summary'!$B$76:$BK$76,0))*12-AG14 -> 0 | AH60: =+INDEX('MRR Schedule Summary'!$B$31:$BK$31,MATCH(AH$8,'MRR Schedule Summary'!$B$76:$BK$76,0))*12-AH14 -> 0 | AI60: =+INDEX('MRR Schedule Summary'!$B$31:$BK$31,MATCH(AI$8,'MRR Schedule Summary'!$B$76:$BK$76,0))*12-AI14 -> 0 | AJ60: =+INDEX('MRR Schedule Summary'!$B$31:$BK$31,MATCH(AJ$8,'MRR Schedule Summary'!$B$76:$BK$76,0))*12-AJ14 -> 0 | AK60: =+INDEX('MRR Schedule Summary'!$B$31:$BK$31,MATCH(AK$8,'MRR Schedule Summary'!$B$76:$BK$76,0))*12-AK14 -> 0 | ... CK60: =+INDEX('MRR Schedule Summary'!$B$31:$BK$31,MATCH(CK$8,'MRR Schedule Summary'!$B$76:$BK$76,0))*12-CK14 -> 0
B61: Ending Logos | C61: 0 | D61: =+INDEX('MRR Schedule Summary'!$B$39:$BK$39,MATCH(D$8,'MRR Schedule Summary'!$B$76:$BK$76,0))-D28 -> 0 | E61: =+INDEX('MRR Schedule Summary'!$B$39:$BK$39,MATCH(E$8,'MRR Schedule Summary'!$B$76:$BK$76,0))-E28 -> 0 | F61: =+INDEX('MRR Schedule Summary'!$B$39:$BK$39,MATCH(F$8,'MRR Schedule Summary'!$B$76:$BK$76,0))-F28 -> 0 | G61: =+INDEX('MRR Schedule Summary'!$B$39:$BK$39,MATCH(G$8,'MRR Schedule Summary'!$B$76:$BK$76,0))-G28 -> 0 | I61: =+INDEX('MRR Schedule Summary'!$B$39:$BK$39,MATCH(I$8,'MRR Schedule Summary'!$B$76:$BK$76,0))-I28 -> 0 | J61: =+INDEX('MRR Schedule Summary'!$B$39:$BK$39,MATCH(J$8,'MRR Schedule Summary'!$B$76:$BK$76,0))-J28 -> 0 | K61: =+INDEX('MRR Schedule Summary'!$B$39:$BK$39,MATCH(K$8,'MRR Schedule Summary'!$B$76:$BK$76,0))-K28 -> 0 | L61: =+INDEX('MRR Schedule Summary'!$B$39:$BK$39,MATCH(L$8,'MRR Schedule Summary'!$B$76:$BK$76,0))-L28 -> 0 | M61: =+INDEX('MRR Schedule Summary'!$B$39:$BK$39,MATCH(M$8,'MRR Schedule Summary'!$B$76:$BK$76,0))-M28 -> 0 | N61: =+INDEX('MRR Schedule Summary'!$B$39:$BK$39,MATCH(N$8,'MRR Schedule Summary'!$B$76:$BK$76,0))-N28 -> 0 | O61: =+INDEX('MRR Schedule Summary'!$B$39:$BK$39,MATCH(O$8,'MRR Schedule Summary'!$B$76:$BK$76,0))-O28 -> 0 | P61: =+INDEX('MRR Schedule Summary'!$B$39:$BK$39,MATCH(P$8,'MRR Schedule Summary'!$B$76:$BK$76,0))-P28 -> 0 | ... AB61: =+INDEX('MRR Schedule Summary'!$B$39:$BK$39,MATCH(AB$8,'MRR Schedule Summary'!$B$76:$BK$76,0))-AB28 -> 0 | AD61: =+INDEX('MRR Schedule Summary'!$B$39:$BK$39,MATCH(AD$8,'MRR Schedule Summary'!$B$76:$BK$76,0))-AD28 -> 0 | AE61: =+INDEX('MRR Schedule Summary'!$B$39:$BK$39,MATCH(AE$8,'MRR Schedule Summary'!$B$76:$BK$76,0))-AE28 -> 0 | AF61: =+INDEX('MRR Schedule Summary'!$B$39:$BK$39,MATCH(AF$8,'MRR Schedule Summary'!$B$76:$BK$76,0))-AF28 -> 0 | AG61: =+INDEX('MRR Schedule Summary'!$B$39:$BK$39,MATCH(AG$8,'MRR Schedule Summary'!$B$76:$BK$76,0))-AG28 -> 0 | AH61: =+INDEX('MRR Schedule Summary'!$B$39:$BK$39,MATCH(AH$8,'MRR Schedule Summary'!$B$76:$BK$76,0))-AH28 -> 0 | AI61: =+INDEX('MRR Schedule Summary'!$B$39:$BK$39,MATCH(AI$8,'MRR Schedule Summary'!$B$76:$BK$76,0))-AI28 -> 0 | AJ61: =+INDEX('MRR Schedule Summary'!$B$39:$BK$39,MATCH(AJ$8,'MRR Schedule Summary'!$B$76:$BK$76,0))-AJ28 -> 0 | AK61: =+INDEX('MRR Schedule Summary'!$B$39:$BK$39,MATCH(AK$8,'MRR Schedule Summary'!$B$76:$BK$76,0))-AK28 -> 0 | ... CK61: =+INDEX('MRR Schedule Summary'!$B$39:$BK$39,MATCH(CK$8,'MRR Schedule Summary'!$B$76:$BK$76,0))-CK28 -> 0
B62: S&M | C62: =SUMIFS($I$52:$W$52,$I$38:$W$38,C$38)-C52 -> 0 | D62: =+SUM(OFFSET(INDEX($AD52:$CL52,MATCH(D$8,$AD$8:$CL$8,0)),,,,-12))-D52 -> 0 | E62: =+SUM(OFFSET(INDEX($AD52:$CL52,MATCH(E$8,$AD$8:$CL$8,0)),,,,-12))-E52 -> 0 | F62: =+SUM(OFFSET(INDEX($AD52:$CL52,MATCH(F$8,$AD$8:$CL$8,0)),,,,-12))-F52 -> 0 | G62: =+SUM(OFFSET(INDEX($AD52:$CL52,MATCH(G$8,$AD$8:$CL$8,0)),,,,-12))-G52 -> 0 | I62: =I52-SUMIFS($AD52:$BT52,$AD$36:$BT$36,I$36) -> 0 | J62: =J52-SUMIFS($AD52:$BT52,$AD$36:$BT$36,J$36) -> 0 | K62: =K52-SUMIFS($AD52:$BT52,$AD$36:$BT$36,K$36) -> 0 | L62: =L52-SUMIFS($AD52:$BT52,$AD$36:$BT$36,L$36) -> 0 | M62: =M52-SUMIFS($AD52:$BT52,$AD$36:$BT$36,M$36) -> 0 | N62: =N52-SUMIFS($AD52:$BT52,$AD$36:$BT$36,N$36) -> 0 | O62: =O52-SUMIFS($AD52:$BT52,$AD$36:$BT$36,O$36) -> 0 | P62: =P52-SUMIFS($AD52:$BT52,$AD$36:$BT$36,P$36) -> 0 | ... V62: =V52-SUMIFS($AD52:$BT52,$AD$36:$BT$36,V$36) -> 0 | W62: =W52-SUMIFS($AD52:$BV52,$AD$36:$BV$36,W$36) -> 0 | X62: =X52-SUMIFS($AD52:$BY52,$AD$36:$BY$36,X$36) -> 0 | Y62: =Y52-SUMIFS($AD52:$CL52,$AD$36:$CL$36,Y$36) -> 0 | Z62: =Z52-SUMIFS($AD52:$CL52,$AD$36:$CL$36,Z$36) -> 0 | AA62: =AA52-SUMIFS($AD52:$CL52,$AD$36:$CL$36,AA$36) -> 0 | AB62: =AB52-SUMIFS($AD52:$CL52,$AD$36:$CL$36,AB$36) -> 0 | AD62: =('Cons TrioMobil | Monthly'!O256*-1*AD51)-AD52 -> 0 | AE62: =('Cons TrioMobil | Monthly'!P256*-1*AE51)-AE52 -> 0 | AF62: =('Cons TrioMobil | Monthly'!Q256*-1*AF51)-AF52 -> 0 | AG62: =('Cons TrioMobil | Monthly'!R256*-1*AG51)-AG52 -> 0 | AH62: =('Cons TrioMobil | Monthly'!S256*-1*AH51)-AH52 -> 0 | AI62: =('Cons TrioMobil | Monthly'!T256*-1*AI51)-AI52 -> 0 | AJ62: =('Cons TrioMobil | Monthly'!U256*-1*AJ51)-AJ52 -> 0 | AK62: =('Cons TrioMobil | Monthly'!V256*-1*AK51)-AK52 -> 0 | ... CK62: =('Cons TrioMobil | Monthly'!BV256*-1*CK51)-CK52 -> 0
B63: Payback Period | D63: =((D44/12)*D56)-D52 -> 0 | E63: =((E44/12)*E56)-E52 -> 0 | F63: =((F44/12)*F56)-F52 -> 0 | G63: =((G44/12)*G56)-G52 -> 0 | I63: =((I44/12)*I56)-I52 -> 0 | J63: =((J44/12)*J56)-J52 -> 0 | K63: =((K44/12)*K56)-K52 -> 0 | L63: =((L44/12)*L56)-L52 -> 0 | M63: =((M44/12)*M56)-M52 -> 0 | N63: =((N44/12)*N56)-N52 -> 0 | O63: =((O44/12)*O56)-O52 -> 0 | P63: =((P44/12)*P56)-P52 -> 0 | ... AB63: =((AB44/12)*AB56)-AB52 -> 0 | AD63: =((AD44/12)*AD56)-AD52 -> 0 | AE63: =((AE44/12)*AE56)-AE52 -> 0 | AF63: =((AF44/12)*AF56)-AF52 -> 0 | AG63: =((AG44/12)*AG56)-AG52 -> 0 | AH63: =((AH44/12)*AH56)-AH52 -> 0 | AI63: =((AI44/12)*AI56)-AI52 -> 0 | AJ63: =((AJ44/12)*AJ56)-AJ52 -> 0 | AK63: =((AK44/12)*AK56)-AK52 -> 0 | ... CK63: =((CK44/12)*CK56)-CK52 -> 0

Sheet Fleet ARR Rollforward
B2: Trio Mobil
B3: Fleet ARR Rollforward
C5: =C6&" " &YEAR(C8) -> Q4 2021 | D5: =D6&" " &YEAR(D8) -> Q4 2022 | E5: =E6&" " &YEAR(E8) -> Q4 2023 | F5: =F6&" " &YEAR(F8) -> Q4 2024 | G5: =G6&" " &YEAR(G8) -> TTM 2025 | I5: =I6&" " &YEAR(I8) -> Q1 2021 | J5: =J6&" " &YEAR(J8) -> Q2 2021 | K5: =K6&" " &YEAR(K8) -> Q3 2021 | L5: =L6&" " &YEAR(L8) -> Q4 2021 | M5: =M6&" " &YEAR(M8) -> Q1 2022 | N5: =N6&" " &YEAR(N8) -> Q2 2022 | O5: =O6&" " &YEAR(O8) -> Q3 2022 | P5: =P6&" " &YEAR(P8) -> Q4 2022 | ... AB5: =AB6&" " &YEAR(AB8) -> Q4 2025 | AD5: =AD6&" " &YEAR(AD8) -> Q1 2021 | AE5: =AE6&" " &YEAR(AE8) -> Q1 2021 | AF5: =AF6&" " &YEAR(AF8) -> Q1 2021 | AG5: =AG6&" " &YEAR(AG8) -> Q2 2021 | AH5: =AH6&" " &YEAR(AH8) -> Q2 2021 | AI5: =AI6&" " &YEAR(AI8) -> Q2 2021 | AJ5: =AJ6&" " &YEAR(AJ8) -> Q3 2021 | AK5: =AK6&" " &YEAR(AK8) -> Q3 2021 | ... CK5: =CK6&" " &YEAR(CK8) -> Q4 2025
C6: Q4 | D6: Q4 | E6: Q4 | F6: Q4 | G6: TTM | I6: Q1 | J6: Q2 | K6: Q3 | L6: Q4 | M6: Q1 | N6: Q2 | O6: Q3 | P6: Q4 | Q6: Q1 | R6: Q2 | S6: Q3 | T6: Q4 | U6: Q1 | V6: Q2 | W6: Q3 | X6: Q4 | Y6: Q1 | Z6: Q2 | AA6: Q3 | AB6: Q4 | AD6: Q1 | AE6: Q1 | AF6: Q1 | AG6: Q2 | AH6: Q2 | AI6: Q2 | AJ6: Q3 | AK6: Q3 | AL6: Q3 | AM6: Q4 | AN6: Q4 | AO6: Q4 | AP6: Q1 | AQ6: Q1 | AR6: Q1 | AS6: Q2 | AT6: Q2 | AU6: Q2 | AV6: Q3 | AW6: Q3 | AX6: Q3 | AY6: Q4 | AZ6: Q4 | BA6: Q4 | BB6: Q1 | BC6: Q1 | BD6: Q1 | BE6: Q2 | BF6: Q2 | BG6: Q2 | BH6: Q3 | BI6: Q3 | BJ6: Q3 | BK6: Q4 | BL6: Q4 | BM6: Q4 | BN6: Q1 | BO6: Q1 | BP6: Q1 | BQ6: Q2 | BR6: Q2 | BS6: Q2 | BT6: Q3 | BU6: Q3 | BV6: Q3 | BW6: Q4 | BX6: Q4 | BY6: Q4 | BZ6: Q1 | CA6: Q1 | CB6: Q1 | CC6: Q2 | CD6: Q2 | CE6: Q2 | CF6: Q3 | CG6: Q3 | CH6: Q3 | CI6: Q4 | CJ6: Q4 | CK6: Q4
C7: =YEAR(C8) -> 2021 | D7: =YEAR(D8) -> 2022 | E7: =YEAR(E8) -> 2023 | F7: =YEAR(F8) -> 2024 | G7: =YEAR(G8) -> 2025 | I7: =YEAR(I8) -> 2021 | J7: =YEAR(J8) -> 2021 | K7: =YEAR(K8) -> 2021 | L7: =YEAR(L8) -> 2021 | M7: =YEAR(M8) -> 2022 | N7: =YEAR(N8) -> 2022 | O7: =YEAR(O8) -> 2022 | P7: =YEAR(P8) -> 2022 | ... AB7: =YEAR(AB8) -> 2025 | AD7: =YEAR(AD8) -> 2021 | AE7: =YEAR(AE8) -> 2021 | AF7: =YEAR(AF8) -> 2021 | AG7: =YEAR(AG8) -> 2021 | AH7: =YEAR(AH8) -> 2021 | AI7: =YEAR(AI8) -> 2021 | AJ7: =YEAR(AJ8) -> 2021 | AK7: =YEAR(AK8) -> 2021 | ... CK7: =YEAR(CK8) -> 2025
B8: Fleet ARR | C8: 44561 | D8: =EOMONTH(C8,12) -> 44926 | E8: =EOMONTH(D8,12) -> 45291 | F8: =EOMONTH(E8,12) -> 45657 | G8: =EOMONTH(F8,12) -> 46022 | I8: 44286 | J8: =EOMONTH(I8,3) -> 44377 | K8: =EOMONTH(J8,3) -> 44469 | L8: =EOMONTH(K8,3) -> 44561 | M8: =EOMONTH(L8,3) -> 44651 | N8: =EOMONTH(M8,3) -> 44742 | O8: =EOMONTH(N8,3) -> 44834 | P8: =EOMONTH(O8,3) -> 44926 | Q8: =EOMONTH(P8,3) -> 45016 | ... W8: =EOMONTH(V8,3) -> 45565 | X8: 45657 | Y8: 45747 | Z8: 45838 | AA8: 45930 | AB8: 46022 | AD8: 44227 | AE8: =EOMONTH(AD8,1) -> 44255 | AF8: =EOMONTH(AE8,1) -> 44286 | AG8: =EOMONTH(AF8,1) -> 44316 | AH8: =EOMONTH(AG8,1) -> 44347 | AI8: =EOMONTH(AH8,1) -> 44377 | AJ8: =EOMONTH(AI8,1) -> 44408 | AK8: =EOMONTH(AJ8,1) -> 44439 | AL8: =EOMONTH(AK8,1) -> 44469 | ... CK8: =EOMONTH(CJ8,1) -> 46022
B9: Beginning | C9: =I9 -> 0 | D9: =+SUMIFS($AD$14:$CL$14,$AD$8:$CL$8,EOMONTH(D8,-12)) -> 2492301.3 | E9: =+SUMIFS($AD$14:$CL$14,$AD$8:$CL$8,EOMONTH(E8,-12)) -> 2815257.9 | F9: =+SUMIFS($AD$14:$CL$14,$AD$8:$CL$8,EOMONTH(F8,-12)) -> 4142219.7 | G9: =+SUMIFS($AD$14:$CL$14,$AD$8:$CL$8,EOMONTH(G8,-12)) -> 6934540.8 | I9: =AD9 -> 0 | J9: =I14 -> 2714213.9 | K9: =J14 -> 2676805.3 | L9: =K14 -> 2655695.6 | M9: =L14 -> 2492301.3 | N9: =M14 -> 2463035.7 | O9: =N14 -> 2578275.9 | P9: =O14 -> 2686332.9 | Q9: =P14 -> 2815257.9 | ... AB9: =AA14 -> 8482172.6 | AD9: 0 | AE9: =AD14 -> 2782735.6 | AF9: =AE14 -> 2770789.1 | AG9: =AF14 -> 2714213.9 | AH9: =AG14 -> 2712245 | AI9: =AH14 -> 2664150.2 | AJ9: =AI14 -> 2676805.3 | AK9: =AJ14 -> 2632626 | AL9: =AK14 -> 2686359.9 | ... CK9: =CJ14 -> 8556763.6
B10: (+) New | C10: =SUMIFS($I10:$W10,$I$7:$W$7,C$7) -> 3203832.3 | D10: =+SUM(OFFSET(INDEX($AD10:$CL10,MATCH(D$8,$AD$8:$CL$8,0)),,,,-12)) -> 475847.05 | E10: =+SUM(OFFSET(INDEX($AD10:$CL10,MATCH(E$8,$AD$8:$CL$8,0)),,,,-12)) -> 684253.05 | F10: =+SUM(OFFSET(INDEX($AD10:$CL10,MATCH(F$8,$AD$8:$CL$8,0)),,,,-12)) -> 1271688.6 | G10: =+SUM(OFFSET(INDEX($AD10:$CL10,MATCH(G$8,$AD$8:$CL$8,0)),,,,-12)) -> 1607929.8 | I10: =SUMIFS($AD10:$BT10,$AD$5:$BT$5,I$5) -> 2858874.4 | J10: =SUMIFS($AD10:$BT10,$AD$5:$BT$5,J$5) -> 81613.826 | K10: =SUMIFS($AD10:$BT10,$AD$5:$BT$5,K$5) -> 137529.9 | L10: =SUMIFS($AD10:$BT10,$AD$5:$BT$5,L$5) -> 125814.25 | M10: =SUMIFS($AD10:$BT10,$AD$5:$BT$5,M$5) -> 115076.08 | N10: =SUMIFS($AD10:$BT10,$AD$5:$BT$5,N$5) -> 144784.88 | O10: =SUMIFS($AD10:$BT10,$AD$5:$BT$5,O$5) -> 112632.41 | P10: =SUMIFS($AD10:$BT10,$AD$5:$BT$5,P$5) -> 103353.67 | ... V10: =SUMIFS($AD10:$BT10,$AD$5:$BT$5,V$5) -> 232491.81 | W10: =SUMIFS($AD10:$BX10,$AD$5:$BX$5,W$5) -> 175814.5 | X10: =SUMIFS($AD10:$BY10,$AD$5:$BY$5,X$5) -> 562357.49 | Y10: =SUMIFS($AD10:$CL10,$AD$5:$CL$5,Y$5) -> 816768.1 | Z10: =SUMIFS($AD10:$CL10,$AD$5:$CL$5,Z$5) -> 236223.41 | AA10: =SUMIFS($AD10:$CL10,$AD$5:$CL$5,AA$5) -> 207940.69 | AB10: =SUMIFS($AD10:$CL10,$AD$5:$CL$5,AB$5) -> 346997.56 | AD10: =+'MRR Schedule Summary'!C7*12 -> 2782735.6 | AE10: =+'MRR Schedule Summary'!D7*12 -> 46146.564 | AF10: =+'MRR Schedule Summary'!E7*12 -> 29992.218 | AG10: =+'MRR Schedule Summary'!F7*12 -> 28460.112 | AH10: =+'MRR Schedule Summary'!G7*12 -> 17521.958 | AI10: =+'MRR Schedule Summary'!H7*12 -> 35631.755 | AJ10: =+'MRR Schedule Summary'!I7*12 -> 37348.595 | AK10: =+'MRR Schedule Summary'!J7*12 -> 49494.66 | ... CK10: =+'MRR Schedule Summary'!BJ7*12 -> 94934.438
B11: (+) Upsell | C11: =SUMIFS($I11:$W11,$I$7:$W$7,C$7) -> 600468.5 | D11: =+SUM(OFFSET(INDEX($AD11:$CL11,MATCH(D$8,$AD$8:$CL$8,0)),,,,-12)) -> 1030772.1 | E11: =+SUM(OFFSET(INDEX($AD11:$CL11,MATCH(E$8,$AD$8:$CL$8,0)),,,,-12)) -> 1804930.8 | F11: =+SUM(OFFSET(INDEX($AD11:$CL11,MATCH(F$8,$AD$8:$CL$8,0)),,,,-12)) -> 2797546.1 | G11: =+SUM(OFFSET(INDEX($AD11:$CL11,MATCH(G$8,$AD$8:$CL$8,0)),,,,-12)) -> 2438388.8 | I11: =SUMIFS($AD11:$BT11,$AD$5:$BT$5,I$5) -> 155028.31 | J11: =SUMIFS($AD11:$BT11,$AD$5:$BT$5,J$5) -> 193773.47 | K11: =SUMIFS($AD11:$BT11,$AD$5:$BT$5,K$5) -> 135352.11 | L11: =SUMIFS($AD11:$BT11,$AD$5:$BT$5,L$5) -> 116314.6 | M11: =SUMIFS($AD11:$BT11,$AD$5:$BT$5,M$5) -> 157760.19 | N11: =SUMIFS($AD11:$BT11,$AD$5:$BT$5,N$5) -> 269154.87 | O11: =SUMIFS($AD11:$BT11,$AD$5:$BT$5,O$5) -> 274789.62 | P11: =SUMIFS($AD11:$BT11,$AD$5:$BT$5,P$5) -> 329067.44 | ... V11: =SUMIFS($AD11:$BT11,$AD$5:$BT$5,V$5) -> 740995.61 | W11: =SUMIFS($AD11:$BX11,$AD$5:$BX$5,W$5) -> 811582.13 | X11: =SUMIFS($AD11:$BY11,$AD$5:$BY$5,X$5) -> 608239.2 | Y11: =SUMIFS($AD11:$CL11,$AD$5:$CL$5,Y$5) -> 619075.57 | Z11: =SUMIFS($AD11:$CL11,$AD$5:$CL$5,Z$5) -> 652598.04 | AA11: =SUMIFS($AD11:$CL11,$AD$5:$CL$5,AA$5) -> 495397.83 | AB11: =SUMIFS($AD11:$CL11,$AD$5:$CL$5,AB$5) -> 671317.37 | AD11: =+'MRR Schedule Summary'!C8*12 -> 0 | AE11: =+'MRR Schedule Summary'!D8*12 -> 87337.268 | AF11: =+'MRR Schedule Summary'!E8*12 -> 67691.046 | AG11: =+'MRR Schedule Summary'!F8*12 -> 62305.959 | AH11: =+'MRR Schedule Summary'!G8*12 -> 34724.176 | AI11: =+'MRR Schedule Summary'!H8*12 -> 96743.338 | AJ11: =+'MRR Schedule Summary'!I8*12 -> 35556.547 | AK11: =+'MRR Schedule Summary'!J8*12 -> 57256.183 | ... CK11: =+'MRR Schedule Summary'!BJ8*12 -> 397575.74
B12: (-) Downsell | C12: =SUMIFS($I12:$W12,$I$7:$W$7,C$7) -> -975163.15 | D12: =+SUM(OFFSET(INDEX($AD12:$CL12,MATCH(D$8,$AD$8:$CL$8,0)),,,,-12)) -> -942151.6 | E12: =+SUM(OFFSET(INDEX($AD12:$CL12,MATCH(E$8,$AD$8:$CL$8,0)),,,,-12)) -> -1008718.7 | F12: =+SUM(OFFSET(INDEX($AD12:$CL12,MATCH(F$8,$AD$8:$CL$8,0)),,,,-12)) -> -1053448.6 | G12: =+SUM(OFFSET(INDEX($AD12:$CL12,MATCH(G$8,$AD$8:$CL$8,0)),,,,-12)) -> -1776155.8 | I12: =SUMIFS($AD12:$BT12,$AD$5:$BT$5,I$5) -> -166409.79 | J12: =SUMIFS($AD12:$BT12,$AD$5:$BT$5,J$5) -> -214947.66 | K12: =SUMIFS($AD12:$BT12,$AD$5:$BT$5,K$5) -> -270598.04 | L12: =SUMIFS($AD12:$BT12,$AD$5:$BT$5,L$5) -> -323207.67 | M12: =SUMIFS($AD12:$BT12,$AD$5:$BT$5,M$5) -> -212514.21 | N12: =SUMIFS($AD12:$BT12,$AD$5:$BT$5,N$5) -> -264485.94 | O12: =SUMIFS($AD12:$BT12,$AD$5:$BT$5,O$5) -> -211253.52 | P12: =SUMIFS($AD12:$BT12,$AD$5:$BT$5,P$5) -> -253897.93 | ... V12: =SUMIFS($AD12:$BT12,$AD$5:$BT$5,V$5) -> -258409.29 | W12: =SUMIFS($AD12:$BX12,$AD$5:$BX$5,W$5) -> -303459.07 | X12: =SUMIFS($AD12:$BY12,$AD$5:$BY$5,X$5) -> -276760.03 | Y12: =SUMIFS($AD12:$CL12,$AD$5:$CL$5,Y$5) -> -372256.56 | Z12: =SUMIFS($AD12:$CL12,$AD$5:$CL$5,Z$5) -> -459086.5 | AA12: =SUMIFS($AD12:$CL12,$AD$5:$CL$5,AA$5) -> -388850.56 | AB12: =SUMIFS($AD12:$CL12,$AD$5:$CL$5,AB$5) -> -555962.22 | AD12: =+'MRR Schedule Summary'!C9*12 -> 0 | AE12: =+'MRR Schedule Summary'!D9*12 -> -86154.414 | AF12: =+'MRR Schedule Summary'!E9*12 -> -80255.371 | AG12: =+'MRR Schedule Summary'!F9*12 -> -71288.093 | AH12: =+'MRR Schedule Summary'!G9*12 -> -75787.672 | AI12: =+'MRR Schedule Summary'!H9*12 -> -67871.892 | AJ12: =+'MRR Schedule Summary'!I9*12 -> -87452.821 | AK12: =+'MRR Schedule Summary'!J9*12 -> -78649.663 | ... CK12: =+'MRR Schedule Summary'!BJ9*12 -> -164079.52
B13: (-) Churn | C13: =SUMIFS($I13:$W13,$I$7:$W$7,C$7) -> -336836.35 | D13: =+SUM(OFFSET(INDEX($AD13:$CL13,MATCH(D$8,$AD$8:$CL$8,0)),,,,-12)) -> -241511.02 | E13: =+SUM(OFFSET(INDEX($AD13:$CL13,MATCH(E$8,$AD$8:$CL$8,0)),,,,-12)) -> -153503.32 | F13: =+SUM(OFFSET(INDEX($AD13:$CL13,MATCH(F$8,$AD$8:$CL$8,0)),,,,-12)) -> -223464.99 | G13: =+SUM(OFFSET(INDEX($AD13:$CL13,MATCH(G$8,$AD$8:$CL$8,0)),,,,-12)) -> -379693.23 | I13: =SUMIFS($AD13:$BT13,$AD$5:$BT$5,I$5) -> -133279.02 | J13: =SUMIFS($AD13:$BT13,$AD$5:$BT$5,J$5) -> -97848.237 | K13: =SUMIFS($AD13:$BT13,$AD$5:$BT$5,K$5) -> -23393.674 | L13: =SUMIFS($AD13:$BT13,$AD$5:$BT$5,L$5) -> -82315.421 | M13: =SUMIFS($AD13:$BT13,$AD$5:$BT$5,M$5) -> -89587.71 | N13: =SUMIFS($AD13:$BT13,$AD$5:$BT$5,N$5) -> -34213.632 | O13: =SUMIFS($AD13:$BT13,$AD$5:$BT$5,O$5) -> -68111.496 | P13: =SUMIFS($AD13:$BT13,$AD$5:$BT$5,P$5) -> -49598.18 | ... V13: =SUMIFS($AD13:$BT13,$AD$5:$BT$5,V$5) -> -70438.503 | W13: =SUMIFS($AD13:$BX13,$AD$5:$BX$5,W$5) -> -43195.046 | X13: =SUMIFS($AD13:$BY13,$AD$5:$BY$5,X$5) -> -59558.848 | Y13: =SUMIFS($AD13:$CL13,$AD$5:$CL$5,Y$5) -> -63181.481 | Z13: =SUMIFS($AD13:$CL13,$AD$5:$CL$5,Z$5) -> -80490.154 | AA13: =SUMIFS($AD13:$CL13,$AD$5:$CL$5,AA$5) -> -116506.55 | AB13: =SUMIFS($AD13:$CL13,$AD$5:$CL$5,AB$5) -> -119515.05 | AD13: =+SUM('MRR Schedule Summary'!C10:C11)*12 -> 0 | AE13: =+SUM('MRR Schedule Summary'!D10:D11)*12 -> -59275.933 | AF13: =+SUM('MRR Schedule Summary'!E10:E11)*12 -> -74003.086 | AG13: =+SUM('MRR Schedule Summary'!F10:F11)*12 -> -21446.843 | AH13: =+SUM('MRR Schedule Summary'!G10:G11)*12 -> -24553.26 | AI13: =+SUM('MRR Schedule Summary'!H10:H11)*12 -> -51848.134 | AJ13: =+SUM('MRR Schedule Summary'!I10:I11)*12 -> -29631.607 | AK13: =+SUM('MRR Schedule Summary'!J10:J11)*12 -> 25632.697 | ... CK13: =+SUM('MRR Schedule Summary'!BJ10:BJ11)*12 -> -60183.998
B14: Ending ARR | C14: =SUM(C9:C13) -> 2492301.3 | D14: =SUM(D9:D13) -> 2815257.9 | E14: =SUM(E9:E13) -> 4142219.7 | F14: =SUM(F9:F13) -> 6934540.8 | G14: =SUM(G9:G13) -> 8825010.3 | I14: =SUM(I9:I13) -> 2714213.9 | J14: =SUM(J9:J13) -> 2676805.3 | K14: =SUM(K9:K13) -> 2655695.6 | L14: =SUM(L9:L13) -> 2492301.3 | M14: =SUM(M9:M13) -> 2463035.7 | N14: =SUM(N9:N13) -> 2578275.9 | O14: =SUM(O9:O13) -> 2686332.9 | P14: =SUM(P9:P13) -> 2815257.9 | ... AB14: =SUM(AB9:AB13) -> 8825010.3 | AD14: =SUM(AD9:AD13) -> 2782735.6 | AE14: =SUM(AE9:AE13) -> 2770789.1 | AF14: =SUM(AF9:AF13) -> 2714213.9 | AG14: =SUM(AG9:AG13) -> 2712245 | AH14: =SUM(AH9:AH13) -> 2664150.2 | AI14: =SUM(AI9:AI13) -> 2676805.3 | AJ14: =SUM(AJ9:AJ13) -> 2632626 | AK14: =SUM(AK9:AK13) -> 2686359.9 | ... CK14: =SUM(CK9:CK13) -> 8825010.3
B15: % YoY Growth | D15: =D14/D9-1 -> 0.12958166 | E15: =E14/E9-1 -> 0.47134646 | F15: =F14/F9-1 -> 0.67411225 | G15: =G14/G9-1 -> 0.27261639 | M15: =M14/I14-1 -> -0.092541783 | N15: =N14/J14-1 -> -0.036808584 | O15: =O14/K14-1 -> 0.011536449 | P15: =P14/L14-1 -> 0.12958166 | Q15: =Q14/M14-1 -> 0.24395406 | R15: =R14/N14-1 -> 0.29244438 | S15: =S14/O14-1 -> 0.35094345 | T15: =T14/P14-1 -> 0.47134646 | ... AB15: =AB14/X14-1 -> 0.27261639 | AP15: =AP14/AD14-1 -> -0.10905375 | AQ15: =AQ14/AE14-1 -> -0.10858227 | AR15: =AR14/AF14-1 -> -0.092541783 | AS15: =AS14/AG14-1 -> -0.079876403 | AT15: =AT14/AH14-1 -> -0.031177338 | AU15: =AU14/AI14-1 -> -0.036808584 | AV15: =AV14/AJ14-1 -> -0.00054542997 | AW15: =AW14/AK14-1 -> -0.022283439 | ... CK15: =CK14/BY14-1 -> 0.27261639
B17: Gross Retention (c only) | D17: =1+D13/D9 -> 0.90309718 | E17: =1+E13/E9 -> 0.94547451 | F17: =1+F13/F9 -> 0.94605187 | G17: =1+G13/G9 -> 0.94524609 | J17: =1+J13*4/J9 -> 0.85579878 | K17: =1+K13*4/K9 -> 0.9650424 | L17: =1+L13*4/L9 -> 0.87601678 | M17: =1+M13*4/M9 -> 0.85621689 | N17: =1+N13*4/N9 -> 0.94443664 | O17: =1+O13*4/O9 -> 0.89433017 | P17: =1+P13*4/P9 -> 0.92614738 | Q17: =1+Q13*4/Q9 -> 0.9829039 | ... AB17: =1+AB13*4/AB9 -> 0.94363942 | AE17: =1+AE13*12/AE9 -> 0.7443842 | AF17: =1+AF13*12/AF9 -> 0.67950031 | AG17: =1+AG13*12/AG9 -> 0.90517987 | AH17: =1+AH13*12/AH9 -> 0.89136707 | AI17: =1+AI13*12/AI9 -> 0.76646302 | AJ17: =1+AJ13*12/AJ9 -> 0.86716281 | AK17: =1+AK13*12/AK9 -> 1.1168386 | AL17: =1+AL13*12/AL9 -> 0.91336337 | ... CK17: =1+CK13*12/CK9 -> 0.915598
B18: Gross Retention (c + d) | D18: =1+SUM(D12:D13)/D9 -> 0.52507243 | E18: =1+SUM(E12:E13)/E9 -> 0.58717033 | F18: =1+SUM(F12:F13)/F9 -> 0.69173204 | G18: =1+SUM(G12:G13)/G9 -> 0.68911437 | J18: =1+SUM(J12:J13)*4/J9 -> 0.53902543 | K18: =1+SUM(K12:K13)*4/K9 -> 0.56068271 | L18: =1+SUM(L12:L13)*4/L9 -> 0.38920244 | M18: =1+SUM(M12:M13)*4/M9 -> 0.51514383 | N18: =1+SUM(N12:N13)*4/N9 -> 0.51490825 | O18: =1+SUM(O12:O13)*4/O9 -> 0.5665863 | P18: =1+SUM(P12:P13)*4/P9 -> 0.5480886 | Q18: =1+SUM(Q12:Q13)*4/Q9 -> 0.53254839 | ... AB18: =1+SUM(AB12:AB13)*4/AB9 -> 0.68146026 | AE18: =1+SUM(AE12:AE13)*12/AE9 -> 0.37286023 | AF18: =1+SUM(AF12:AF13)*12/AF9 -> 0.33192263 | AG18: =1+SUM(AG12:AG13)*12/AG9 -> 0.59000312 | AH18: =1+SUM(AH12:AH13)*12/AH9 -> 0.55605368 | AI18: =1+SUM(AI12:AI13)*12/AI9 -> 0.46075101 | AJ18: =1+SUM(AJ12:AJ13)*12/AJ9 -> 0.47511568 | AK18: =1+SUM(AK12:AK13)*12/AK9 -> 0.75833879 | AL18: =1+SUM(AL12:AL13)*12/AL9 -> 0.44658055 | ... CK18: =1+SUM(CK12:CK13)*12/CK9 -> 0.68549298
B19: Net Retention | D19: =1+SUM(D11:D13)/D9 -> 0.93865489 | E19: =1+SUM(E11:E13)/E9 -> 1.2282948 | F19: =1+SUM(F11:F13)/F9 -> 1.3671057 | G19: =1+SUM(G11:G13)/G9 -> 1.0407438 | J19: =1+SUM(J11:J13)*4/J9 -> 0.8245939 | K19: =1+SUM(K11:K13)*4/K9 -> 0.76294189 | L19: =1+SUM(L11:L13)*4/L9 -> 0.56439511 | M19: =1+SUM(M11:M13)*4/M9 -> 0.76833984 | N19: =1+SUM(N11:N13)*4/N9 -> 0.95201905 | O19: =1+SUM(O11:O13)*4/O9 -> 0.99290161 | P19: =1+SUM(P11:P13)*4/P9 -> 1.0380762 | Q19: =1+SUM(Q11:Q13)*4/Q9 -> 0.97266338 | ... AB19: =1+SUM(AB11:AB13)*4/AB9 -> 0.99803829 | AE19: =1+SUM(AE11:AE13)*12/AE9 -> 0.74948502 | AF19: =1+SUM(AF11:AF13)*12/AF9 -> 0.62508552 | AG19: =1+SUM(AG11:AG13)*12/AG9 -> 0.86546833 | AH19: =1+SUM(AH11:AH13)*12/AH9 -> 0.7096866 | AI19: =1+SUM(AI11:AI13)*12/AI9 -> 0.89650724 | AJ19: =1+SUM(AJ11:AJ13)*12/AJ9 -> 0.63451411 | AK19: =1+SUM(AK11:AK13)*12/AK9 -> 1.0193231 | AL19: =1+SUM(AL11:AL13)*12/AL9 -> 0.63660445 | ... CK19: =1+SUM(CK11:CK13)*12/CK9 -> 1.2430529
B21: Net New ARR | C21: =SUM(C10:C13) -> 2492301.3 | D21: =SUM(D10:D13) -> 322956.55 | E21: =SUM(E10:E13) -> 1326961.8 | F21: =SUM(F10:F13) -> 2792321.1 | G21: =SUM(G10:G13) -> 1890469.5 | I21: =SUM(I10:I13) -> 2714213.9 | J21: =SUM(J10:J13) -> -37408.595 | K21: =SUM(K10:K13) -> -21109.702 | L21: =SUM(L10:L13) -> -163394.25 | M21: =SUM(M10:M13) -> -29265.647 | N21: =SUM(N10:N13) -> 115240.18 | O21: =SUM(O10:O13) -> 108057.01 | P21: =SUM(P10:P13) -> 128925 | ... AB21: =SUM(AB10:AB13) -> 342837.66 | AD21: =SUM(AD10:AD13) -> 2782735.6 | AE21: =SUM(AE10:AE13) -> -11946.515 | AF21: =SUM(AF10:AF13) -> -56575.194 | AG21: =SUM(AG10:AG13) -> -1968.8643 | AH21: =SUM(AH10:AH13) -> -48094.798 | AI21: =SUM(AI10:AI13) -> 12655.067 | AJ21: =SUM(AJ10:AJ13) -> -44179.285 | AK21: =SUM(AK10:AK13) -> 53733.877 | ... CK21: =SUM(CK10:CK13) -> 268246.66
B22: New + Upsell | C22: =SUM(C10:C11) -> 3804300.8 | D22: =SUM(D10:D11) -> 1506619.2 | E22: =SUM(E10:E11) -> 2489183.8 | F22: =SUM(F10:F11) -> 4069234.7 | G22: =SUM(G10:G11) -> 4046318.6 | I22: =SUM(I10:I11) -> 3013902.7 | J22: =SUM(J10:J11) -> 275387.3 | K22: =SUM(K10:K11) -> 272882.01 | L22: =SUM(L10:L11) -> 242128.85 | M22: =SUM(M10:M11) -> 272836.27 | N22: =SUM(N10:N11) -> 413939.76 | O22: =SUM(O10:O11) -> 387422.03 | P22: =SUM(P10:P11) -> 432421.11 | ... AB22: =SUM(AB10:AB11) -> 1018314.9 | AD22: =SUM(AD10:AD11) -> 2782735.6 | AE22: =SUM(AE10:AE11) -> 133483.83 | AF22: =SUM(AF10:AF11) -> 97683.264 | AG22: =SUM(AG10:AG11) -> 90766.071 | AH22: =SUM(AH10:AH11) -> 52246.135 | AI22: =SUM(AI10:AI11) -> 132375.09 | AJ22: =SUM(AJ10:AJ11) -> 72905.143 | AK22: =SUM(AK10:AK11) -> 106750.84 | ... CK22: =SUM(CK10:CK11) -> 492510.18
B24: Customer Count
B25: Beginning Logos | C25: =I25 -> 0 | D25: =+SUMIFS($AD$28:$CL$28,$AD$8:$CL$8,EOMONTH(D8,-12)) -> 9525 | E25: =+SUMIFS($AD$28:$CL$28,$AD$8:$CL$8,EOMONTH(E8,-12)) -> 10450 | F25: =+SUMIFS($AD$28:$CL$28,$AD$8:$CL$8,EOMONTH(F8,-12)) -> 11204 | G25: =+SUMIFS($AD$28:$CL$28,$AD$8:$CL$8,EOMONTH(G8,-12)) -> 11739 | I25: =AD25 -> 0 | J25: =I28 -> 8867 | K25: =J28 -> 8932 | L25: =K28 -> 9195 | M25: =L28 -> 9525 | N25: =M28 -> 9732 | O25: =N28 -> 10127 | P25: =O28 -> 10289 | Q25: =P28 -> 10450 | ... AB25: =AA28 -> 11834 | AD25: 0 | AE25: =AD28 -> 8858 | AF25: =AE28 -> 8845 | AG25: =AF28 -> 8867 | AH25: =AG28 -> 8874 | AI25: =AH28 -> 8856 | AJ25: =AI28 -> 8932 | AK25: =AJ28 -> 8929 | AL25: =AK28 -> 9026 | ... CK25: =CJ28 -> 11821
B26: (+) New | C26: =SUMIFS($I26:$W26,$I$7:$W$7,C$7) -> 11004 | D26: =+SUM(OFFSET(INDEX($AD26:$CL26,MATCH(D$8,$AD$8:$CL$8,0)),,,,-12)) -> 2220 | E26: =+SUM(OFFSET(INDEX($AD26:$CL26,MATCH(E$8,$AD$8:$CL$8,0)),,,,-12)) -> 2125 | F26: =+SUM(OFFSET(INDEX($AD26:$CL26,MATCH(F$8,$AD$8:$CL$8,0)),,,,-12)) -> 2806 | G26: =+SUM(OFFSET(INDEX($AD26:$CL26,MATCH(G$8,$AD$8:$CL$8,0)),,,,-12)) -> 3061 | I26: =SUMIFS($AD26:$BT26,$AD$5:$BT$5,I$5) -> 9173 | J26: =SUMIFS($AD26:$BT26,$AD$5:$BT$5,J$5) -> 437 | K26: =SUMIFS($AD26:$BT26,$AD$5:$BT$5,K$5) -> 682 | L26: =SUMIFS($AD26:$BT26,$AD$5:$BT$5,L$5) -> 712 | M26: =SUMIFS($AD26:$BT26,$AD$5:$BT$5,M$5) -> 545 | N26: =SUMIFS($AD26:$BT26,$AD$5:$BT$5,N$5) -> 644 | O26: =SUMIFS($AD26:$BT26,$AD$5:$BT$5,O$5) -> 534 | P26: =SUMIFS($AD26:$BT26,$AD$5:$BT$5,P$5) -> 497 | ... V26: =SUMIFS($AD26:$BT26,$AD$5:$BT$5,V$5) -> 654 | W26: =SUMIFS($AD26:$BX26,$AD$5:$BX$5,W$5) -> 684 | X26: =SUMIFS($AD26:$BY26,$AD$5:$BY$5,X$5) -> 774 | Y26: =SUMIFS($AD26:$CL26,$AD$5:$CL$5,Y$5) -> 666 | Z26: =SUMIFS($AD26:$CL26,$AD$5:$CL$5,Z$5) -> 720 | AA26: =SUMIFS($AD26:$CL26,$AD$5:$CL$5,AA$5) -> 811 | AB26: =SUMIFS($AD26:$CL26,$AD$5:$CL$5,AB$5) -> 864 | AD26: =+SUM('MRR Schedule Summary'!C17:C18) -> 8858 | AE26: =+SUM('MRR Schedule Summary'!D17:D18) -> 149 | AF26: =+SUM('MRR Schedule Summary'!E17:E18) -> 166 | AG26: =+SUM('MRR Schedule Summary'!F17:F18) -> 143 | AH26: =+SUM('MRR Schedule Summary'!G17:G18) -> 101 | AI26: =+SUM('MRR Schedule Summary'!H17:H18) -> 193 | AJ26: =+SUM('MRR Schedule Summary'!I17:I18) -> 162 | AK26: =+SUM('MRR Schedule Summary'!J17:J18) -> 218 | ... CK26: =+SUM('MRR Schedule Summary'!BJ17:BJ18) -> 281
B27: (-) Cancel | C27: =SUMIFS($I27:$W27,$I$7:$W$7,C$7) -> -1479 | D27: =+SUM(OFFSET(INDEX($AD27:$CL27,MATCH(D$8,$AD$8:$CL$8,0)),,,,-12)) -> -1295 | E27: =+SUM(OFFSET(INDEX($AD27:$CL27,MATCH(E$8,$AD$8:$CL$8,0)),,,,-12)) -> -1371 | F27: =+SUM(OFFSET(INDEX($AD27:$CL27,MATCH(F$8,$AD$8:$CL$8,0)),,,,-12)) -> -2271 | G27: =+SUM(OFFSET(INDEX($AD27:$CL27,MATCH(G$8,$AD$8:$CL$8,0)),,,,-12)) -> -2985 | I27: =SUMIFS($AD27:$BT27,$AD$5:$BT$5,I$5) -> -306 | J27: =SUMIFS($AD27:$BT27,$AD$5:$BT$5,J$5) -> -372 | K27: =SUMIFS($AD27:$BT27,$AD$5:$BT$5,K$5) -> -419 | L27: =SUMIFS($AD27:$BT27,$AD$5:$BT$5,L$5) -> -382 | M27: =SUMIFS($AD27:$BT27,$AD$5:$BT$5,M$5) -> -338 | N27: =SUMIFS($AD27:$BT27,$AD$5:$BT$5,N$5) -> -249 | O27: =SUMIFS($AD27:$BT27,$AD$5:$BT$5,O$5) -> -372 | P27: =SUMIFS($AD27:$BT27,$AD$5:$BT$5,P$5) -> -336 | ... V27: =SUMIFS($AD27:$BT27,$AD$5:$BT$5,V$5) -> -457 | W27: =SUMIFS($AD27:$BX27,$AD$5:$BX$5,W$5) -> -644 | X27: =SUMIFS($AD27:$BY27,$AD$5:$BY$5,X$5) -> -790 | Y27: =SUMIFS($AD27:$CL27,$AD$5:$CL$5,Y$5) -> -716 | Z27: =SUMIFS($AD27:$CL27,$AD$5:$CL$5,Z$5) -> -631 | AA27: =SUMIFS($AD27:$CL27,$AD$5:$CL$5,AA$5) -> -755 | AB27: =SUMIFS($AD27:$CL27,$AD$5:$CL$5,AB$5) -> -883 | AD27: =+'MRR Schedule Summary'!C19 -> 0 | AE27: =+'MRR Schedule Summary'!D19 -> -162 | AF27: =+'MRR Schedule Summary'!E19 -> -144 | AG27: =+'MRR Schedule Summary'!F19 -> -136 | AH27: =+'MRR Schedule Summary'!G19 -> -119 | AI27: =+'MRR Schedule Summary'!H19 -> -117 | AJ27: =+'MRR Schedule Summary'!I19 -> -165 | AK27: =+'MRR Schedule Summary'!J19 -> -121 | ... CK27: =+'MRR Schedule Summary'!BJ19 -> -287
B28: Ending Logos | C28: =SUM(C25:C27) -> 9525 | D28: =SUM(D25:D27) -> 10450 | E28: =SUM(E25:E27) -> 11204 | F28: =SUM(F25:F27) -> 11739 | G28: =SUM(G25:G27) -> 11815 | I28: =SUM(I25:I27) -> 8867 | J28: =SUM(J25:J27) -> 8932 | K28: =SUM(K25:K27) -> 9195 | L28: =SUM(L25:L27) -> 9525 | M28: =SUM(M25:M27) -> 9732 | N28: =SUM(N25:N27) -> 10127 | O28: =SUM(O25:O27) -> 10289 | P28: =SUM(P25:P27) -> 10450 | ... AB28: =SUM(AB25:AB27) -> 11815 | AD28: =SUM(AD25:AD27) -> 8858 | AE28: =SUM(AE25:AE27) -> 8845 | AF28: =SUM(AF25:AF27) -> 8867 | AG28: =SUM(AG25:AG27) -> 8874 | AH28: =SUM(AH25:AH27) -> 8856 | AI28: =SUM(AI25:AI27) -> 8932 | AJ28: =SUM(AJ25:AJ27) -> 8929 | AK28: =SUM(AK25:AK27) -> 9026 | ... CK28: =SUM(CK25:CK27) -> 11815
B30: Logo Retention | C30: =1+C27/C28 -> 0.84472441 | D30: =1+D27/D28 -> 0.87607656 | E30: =1+E27/E28 -> 0.87763299 | F30: =1+F27/F28 -> 0.80654229 | G30: =1+G27/G28 -> 0.74735506 | J30: =1+J27*4/J25 -> 0.83218676 | K30: =1+K27*4/K25 -> 0.81236005 | L30: =1+L27*4/L25 -> 0.83382273 | M30: =1+M27*4/M25 -> 0.85805774 | N30: =1+N27*4/N25 -> 0.89765721 | O30: =1+O27*4/O25 -> 0.85306606 | P30: =1+P27*4/P25 -> 0.86937506 | Q30: =1+Q27*4/Q25 -> 0.87712919 | ... AB30: =1+AB27*4/AB25 -> 0.70153794 | AE30: =1+AE27*12/AE25 -> 0.78053737 | AF30: =1+AF27*12/AF25 -> 0.80463539 | AG30: =1+AG27*12/AG25 -> 0.81594677 | AH30: =1+AH27*12/AH25 -> 0.83908046 | AI30: =1+AI27*12/AI25 -> 0.84146341 | AJ30: =1+AJ27*12/AJ25 -> 0.77832512 | AK30: =1+AK27*12/AK25 -> 0.83738381 | AL30: =1+AL27*12/AL25 -> 0.82317749 | ... CK30: =1+CK27*12/CK25 -> 0.70865409
B32: Avg. ARR / Cust | C32: =C14/C28 -> 261.65893 | D32: =D14/D28 -> 269.40267 | E32: =E14/E28 -> 369.70901 | F32: =F14/F28 -> 590.7267 | G32: =G14/G28 -> 746.93274 | I32: =I14/I28 -> 306.10284 | J32: =J14/J28 -> 299.68711 | K32: =K14/K28 -> 288.81953 | L32: =L14/L28 -> 261.65893 | M32: =M14/M28 -> 253.08628 | N32: =N14/N28 -> 254.59424 | O32: =O14/O28 -> 261.08785 | P32: =P14/P28 -> 269.40267 | ... AB32: =AB14/AB28 -> 746.93274 | AE32: =AE14/AE28 -> 313.26049 | AF32: =AF14/AF28 -> 306.10284 | AG32: =AG14/AG28 -> 305.63951 | AH32: =AH14/AH28 -> 300.82997 | AI32: =AI14/AI28 -> 299.68711 | AJ32: =AJ14/AJ28 -> 294.83996 | AK32: =AK14/AK28 -> 297.62463 | AL32: =AL14/AL28 -> 288.81953 | ... CK32: =CK14/CK28 -> 746.93274
B33: Avg. ARR / New | C33: =C10/C26 -> 291.15161 | D33: =D10/D26 -> 214.34552 | E33: =E10/E26 -> 322.00143 | F33: =F10/F26 -> 453.20335 | G33: =G10/G26 -> 525.29557 | I33: =I10/I26 -> 311.66187 | J33: =J10/J26 -> 186.75933 | K33: =K10/K26 -> 201.65674 | L33: =L10/L26 -> 176.7054 | M33: =M10/M26 -> 211.14878 | N33: =N10/N26 -> 224.82125 | O33: =O10/O26 -> 210.92211 | P33: =P10/P26 -> 207.95508 | ... AB33: =AB10/AB26 -> 401.61755 | AE33: =AE10/AE26 -> 309.70848 | AF33: =AF10/AF26 -> 180.67601 | AG33: =AG10/AG26 -> 199.02177 | AH33: =AH10/AH26 -> 173.48474 | AI33: =AI10/AI26 -> 184.62049 | AJ33: =AJ10/AJ26 -> 230.54688 | AK33: =AK10/AK26 -> 227.03972 | AL33: =AL10/AL26 -> 167.83656 | ... CK33: =CK10/CK26 -> 337.84498
B34: Avg. ARR / Churn | C34: =IFERROR(C13/C27,"NA") -> 227.74601 | D34: =IFERROR(D13/D27,"NA") -> 186.495 | E34: =IFERROR(E13/E27,"NA") -> 111.96449 | F34: =IFERROR(F13/F27,"NA") -> 98.399379 | G34: =IFERROR(G13/G27,"NA") -> 127.20041 | I34: =IFERROR(I13/I27,"NA") -> 435.55235 | J34: =IFERROR(J13/J27,"NA") -> 263.03289 | K34: =IFERROR(K13/K27,"NA") -> 55.832157 | L34: =IFERROR(L13/L27,"NA") -> 215.48539 | M34: =IFERROR(M13/M27,"NA") -> 265.0524 | N34: =IFERROR(N13/N27,"NA") -> 137.40415 | O34: =IFERROR(O13/O27,"NA") -> 183.09542 | P34: =IFERROR(P13/P27,"NA") -> 147.61363 | ... AB34: =IFERROR(AB13/AB27,"NA") -> 135.35113 | AE34: =IFERROR(AE13/AE27,"NA") -> 365.90082 | AF34: =IFERROR(AF13/AF27,"NA") -> 513.91032 | AG34: =IFERROR(AG13/AG27,"NA") -> 157.69738 | AH34: =IFERROR(AH13/AH27,"NA") -> 206.32992 | AI34: =IFERROR(AI13/AI27,"NA") -> 443.14644 | AJ34: =IFERROR(AJ13/AJ27,"NA") -> 179.58549 | AK34: =IFERROR(AK13/AK27,"NA") -> -211.84047 | AL34: =IFERROR(AL13/AL27,"NA") -> 145.82529 | ... CK34: =IFERROR(CK13/CK27,"NA") -> 209.70034
C36: =C37&" " &YEAR(C39) -> Q4 2021 | D36: =D37&" " &YEAR(D39) -> Q4 2022 | E36: =E37&" " &YEAR(E39) -> Q4 2023 | F36: =F37&" " &YEAR(F39) -> Q4 2024 | G36: =G37&" " &YEAR(G39) -> TTM 2025 | I36: =I37&" " &YEAR(I39) -> Q1 2021 | J36: =J37&" " &YEAR(J39) -> Q2 2021 | K36: =K37&" " &YEAR(K39) -> Q3 2021 | L36: =L37&" " &YEAR(L39) -> Q4 2021 | M36: =M37&" " &YEAR(M39) -> Q1 2022 | N36: =N37&" " &YEAR(N39) -> Q2 2022 | O36: =O37&" " &YEAR(O39) -> Q3 2022 | P36: =P37&" " &YEAR(P39) -> Q4 2022 | ... AB36: =AB37&" " &YEAR(AB39) -> Q4 2025 | AD36: =AD37&" " &YEAR(AD39) -> Q1 2021 | AE36: =AE37&" " &YEAR(AE39) -> Q1 2021 | AF36: =AF37&" " &YEAR(AF39) -> Q1 2021 | AG36: =AG37&" " &YEAR(AG39) -> Q2 2021 | AH36: =AH37&" " &YEAR(AH39) -> Q2 2021 | AI36: =AI37&" " &YEAR(AI39) -> Q2 2021 | AJ36: =AJ37&" " &YEAR(AJ39) -> Q3 2021 | AK36: =AK37&" " &YEAR(AK39) -> Q3 2021 | ... CK36: =CK37&" " &YEAR(CK39) -> Q4 2025
C37: Q4 | D37: Q4 | E37: Q4 | F37: Q4 | G37: TTM | I37: =+I6 -> Q1 | J37: =+J6 -> Q2 | K37: =+K6 -> Q3 | L37: =+L6 -> Q4 | M37: =+M6 -> Q1 | N37: =+N6 -> Q2 | O37: =+O6 -> Q3 | P37: =+P6 -> Q4 | ... AB37: =+AB6 -> Q4 | AD37: =+AD6 -> Q1 | AE37: =+AE6 -> Q1 | AF37: =+AF6 -> Q1 | AG37: =+AG6 -> Q2 | AH37: =+AH6 -> Q2 | AI37: =+AI6 -> Q2 | AJ37: =+AJ6 -> Q3 | AK37: =+AK6 -> Q3 | ... CK37: =+CK6 -> Q4
C38: =YEAR(C39) -> 2021 | D38: =YEAR(D39) -> 2022 | E38: =YEAR(E39) -> 2023 | F38: =YEAR(F39) -> 2024 | G38: =YEAR(G39) -> 2025 | I38: =YEAR(I39) -> 2021 | J38: =YEAR(J39) -> 2021 | K38: =YEAR(K39) -> 2021 | L38: =YEAR(L39) -> 2021 | M38: =YEAR(M39) -> 2022 | N38: =YEAR(N39) -> 2022 | O38: =YEAR(O39) -> 2022 | P38: =YEAR(P39) -> 2022 | ... AB38: =YEAR(AB39) -> 2025 | AD38: =YEAR(AD39) -> 2021 | AE38: =YEAR(AE39) -> 2021 | AF38: =YEAR(AF39) -> 2021 | AG38: =YEAR(AG39) -> 2021 | AH38: =YEAR(AH39) -> 2021 | AI38: =YEAR(AI39) -> 2021 | AJ38: =YEAR(AJ39) -> 2021 | AK38: =YEAR(AK39) -> 2021 | ... CK38: =YEAR(CK39) -> 2025
B39: Fleet Sales Efficiency | C39: 44561 | D39: =EOMONTH(C39,12) -> 44926 | E39: =EOMONTH(D39,12) -> 45291 | F39: =EOMONTH(E39,12) -> 45657 | G39: =+G8 -> 46022 | I39: =+I8 -> 44286 | J39: =+J8 -> 44377 | K39: =+K8 -> 44469 | L39: =+L8 -> 44561 | M39: =+M8 -> 44651 | N39: =+N8 -> 44742 | O39: =+O8 -> 44834 | P39: =+P8 -> 44926 | ... AB39: =+AB8 -> 46022 | AD39: =+AD8 -> 44227 | AE39: =+AE8 -> 44255 | AF39: =+AF8 -> 44286 | AG39: =+AG8 -> 44316 | AH39: =+AH8 -> 44347 | AI39: =+AI8 -> 44377 | AJ39: =+AJ8 -> 44408 | AK39: =+AK8 -> 44439 | ... CK39: =+CK8 -> 46022
B41: Customer Lifetime Value
B42: New + Upsell | C42: =SUM(C10:C11) -> 3804300.8 | D42: =SUM(D10:D11) -> 1506619.2 | E42: =SUM(E10:E11) -> 2489183.8 | F42: =SUM(F10:F11) -> 4069234.7 | G42: =SUM(G10:G11) -> 4046318.6 | I42: =SUM(I10:I11) -> 3013902.7 | J42: =SUM(J10:J11) -> 275387.3 | K42: =SUM(K10:K11) -> 272882.01 | L42: =SUM(L10:L11) -> 242128.85 | M42: =SUM(M10:M11) -> 272836.27 | N42: =SUM(N10:N11) -> 413939.76 | O42: =SUM(O10:O11) -> 387422.03 | P42: =SUM(P10:P11) -> 432421.11 | ... AB42: =SUM(AB10:AB11) -> 1018314.9 | AD42: =SUM(AD10:AD11) -> 2782735.6 | AE42: =SUM(AE10:AE11) -> 133483.83 | AF42: =SUM(AF10:AF11) -> 97683.264 | AG42: =SUM(AG10:AG11) -> 90766.071 | AH42: =SUM(AH10:AH11) -> 52246.135 | AI42: =SUM(AI10:AI11) -> 132375.09 | AJ42: =SUM(AJ10:AJ11) -> 72905.143 | AK42: =SUM(AK10:AK11) -> 106750.84 | ... CK42: =SUM(CK10:CK11) -> 492510.18
B43: Gross Margin | C43: 0.7049489 | D43: =+'Industrial ARR Rollforward'!D43 -> 0.72510895 | E43: =+'Industrial ARR Rollforward'!E43 -> 0.75651534 | F43: =+'Industrial ARR Rollforward'!F43 -> 0.77942405 | G43: =+'Industrial ARR Rollforward'!G43 -> 0.75533729 | I43: =AVERAGEIFS($AD43:$BT43,$AD$36:$BT$36,I$36) -> 0.70331208 | J43: =AVERAGEIFS($AD43:$BT43,$AD$36:$BT$36,J$36) -> 0.75287296 | K43: =AVERAGEIFS($AD43:$BT43,$AD$36:$BT$36,K$36) -> 0.73170588 | L43: =AVERAGEIFS($AD43:$BT43,$AD$36:$BT$36,L$36) -> 0.76169227 | M43: =AVERAGEIFS($AD43:$BT43,$AD$36:$BT$36,M$36) -> 0.72432258 | N43: =AVERAGEIFS($AD43:$BT43,$AD$36:$BT$36,N$36) -> 0.70519993 | O43: =AVERAGEIFS($AD43:$BT43,$AD$36:$BT$36,O$36) -> 0.72702076 | P43: =AVERAGEIFS($AD43:$BT43,$AD$36:$BT$36,P$36) -> 0.73995139 | ... V43: =AVERAGEIFS($AD43:$BT43,$AD$36:$BT$36,V$36) -> 0.78066093 | W43: =AVERAGEIFS($AD43:$BX43,$AD$36:$BX$36,W$36) -> 0.77526965 | X43: =AVERAGEIFS($AD43:$BY43,$AD$36:$BY$36,X$36) -> 0.78768385 | Y43: =AVERAGEIFS($AD43:$CL43,$AD$36:$CL$36,Y$36) -> 0.76892265 | Z43: =AVERAGEIFS($AD43:$CL43,$AD$36:$CL$36,Z$36) -> 0.75446338 | AA43: =AVERAGEIFS($AD43:$CL43,$AD$36:$CL$36,AA$36) -> 0.75623831 | AB43: =AVERAGEIFS($AD43:$CL43,$AD$36:$CL$36,AB$36) -> 0.74171109 | AD43: =+'Cons TrioMobil | Monthly'!O24 -> 0.66228422 | AE43: =+'Cons TrioMobil | Monthly'!P24 -> 0.72075982 | AF43: =+'Cons TrioMobil | Monthly'!Q24 -> 0.72689219 | AG43: =+'Cons TrioMobil | Monthly'!R24 -> 0.78612543 | AH43: =+'Cons TrioMobil | Monthly'!S24 -> 0.74211799 | AI43: =+'Cons TrioMobil | Monthly'!T24 -> 0.73037545 | AJ43: =+'Cons TrioMobil | Monthly'!U24 -> 0.7471152 | AK43: =+'Cons TrioMobil | Monthly'!V24 -> 0.6971837 | ... CK43: =+'Cons TrioMobil | Monthly'!BV24 -> 0.72957513
B44: Gross Profit | C44: =C43*C42 -> 2681837.7 | D44: =D43*D42 -> 1092463 | E44: =E43*E42 -> 1883105.7 | F44: =F43*F42 -> 3171659.4 | G44: =G43*G42 -> 3056335.3 | I44: =I43*I42 -> 2119714.2 | J44: =J43*J42 -> 207331.65 | K44: =K43*K42 -> 199669.37 | L44: =L43*L42 -> 184427.67 | M44: =M43*M42 -> 197621.47 | N44: =N43*N42 -> 291910.29 | O44: =O43*O42 -> 281663.86 | P44: =P43*P42 -> 319970.61 | ... AB44: =AB43*AB42 -> 755295.47 | AD44: =AD43*AD42 -> 1842961.9 | AE44: =AE43*AE42 -> 96209.784 | AF44: =AF43*AF42 -> 71005.202 | AG44: =AG43*AG42 -> 71353.517 | AH44: =AH43*AH42 -> 38772.797 | AI44: =AI43*AI42 -> 96683.518 | AJ44: =AJ43*AJ42 -> 54468.541 | AK44: =AK43*AK42 -> 74424.948 | ... CK44: =CK43*CK42 -> 359323.18
B46: Logo Retention | C46: =C30 -> 0.84472441 | D46: =D30 -> 0.87607656 | E46: =E30 -> 0.87763299 | F46: =F30 -> 0.80654229 | G46: =G30 -> 0.74735506 | J46: =J30 -> 0.83218676 | K46: =K30 -> 0.81236005 | L46: =L30 -> 0.83382273 | M46: =M30 -> 0.85805774 | N46: =N30 -> 0.89765721 | O46: =O30 -> 0.85306606 | P46: =P30 -> 0.86937506 | Q46: =Q30 -> 0.87712919 | ... AB46: =AB30 -> 0.70153794 | AE46: =AE30 -> 0.78053737 | AF46: =AF30 -> 0.80463539 | AG46: =AG30 -> 0.81594677 | AH46: =AH30 -> 0.83908046 | AI46: =AI30 -> 0.84146341 | AJ46: =AJ30 -> 0.77832512 | AK46: =AK30 -> 0.83738381 | AL46: =AL30 -> 0.82317749 | ... CK46: =CK30 -> 0.70865409
B47: Implied Customer Years (Calculated) | C47: =IF(C46=100%,100,IFERROR(1/(1-C46),"NA")) -> 6.4401623 | D47: =IF(D46=100%,100,IFERROR(1/(1-D46),"NA")) -> 8.0694981 | E47: =IF(E46=100%,100,IFERROR(1/(1-E46),"NA")) -> 8.1721371 | F47: =IF(F46=100%,100,IFERROR(1/(1-F46),"NA")) -> 5.1690885 | G47: =IF(G46=100%,100,IFERROR(1/(1-G46),"NA")) -> 3.958124 | J47: =IF(J46=100%,100,IFERROR(1/(1-J46),"NA")) -> 5.9590054 | K47: =IF(K46=100%,100,IFERROR(1/(1-K46),"NA")) -> 5.3293556 | L47: =IF(L46=100%,100,IFERROR(1/(1-L46),"NA")) -> 6.0176702 | M47: =IF(M46=100%,100,IFERROR(1/(1-M46),"NA")) -> 7.0451183 | N47: =IF(N46=100%,100,IFERROR(1/(1-N46),"NA")) -> 9.7710843 | O47: =IF(O46=100%,100,IFERROR(1/(1-O46),"NA")) -> 6.8057796 | P47: =IF(P46=100%,100,IFERROR(1/(1-P46),"NA")) -> 7.655506 | Q47: =IF(Q46=100%,100,IFERROR(1/(1-Q46),"NA")) -> 8.1386293 | ... AB47: =IF(AB46=100%,100,IFERROR(1/(1-AB46),"NA")) -> 3.3505096 | AE47: =IF(AE46=100%,100,IFERROR(1/(1-AE46),"NA")) -> 4.5565844 | AF47: =IF(AF46=100%,100,IFERROR(1/(1-AF46),"NA")) -> 5.1186343 | AG47: =IF(AG46=100%,100,IFERROR(1/(1-AG46),"NA")) -> 5.4332108 | AH47: =IF(AH46=100%,100,IFERROR(1/(1-AH46),"NA")) -> 6.2142857 | AI47: =IF(AI46=100%,100,IFERROR(1/(1-AI46),"NA")) -> 6.3076923 | AJ47: =IF(AJ46=100%,100,IFERROR(1/(1-AJ46),"NA")) -> 4.5111111 | AK47: =IF(AK46=100%,100,IFERROR(1/(1-AK46),"NA")) -> 6.149449 | AL47: =IF(AL46=100%,100,IFERROR(1/(1-AL46),"NA")) -> 5.6553885 | ... CK47: =IF(CK46=100%,100,IFERROR(1/(1-CK46),"NA")) -> 3.4323461
B48: Implied Customer Years (Capped) | C48: =MIN(C47,5) -> 5 | D48: =MIN(D47,5) -> 5 | E48: =MIN(E47,5) -> 5 | F48: =MIN(F47,5) -> 5 | G48: =MIN(G47,5) -> 3.958124 | J48: =MIN(J47,5) -> 5 | K48: =MIN(K47,5) -> 5 | L48: =MIN(L47,5) -> 5 | M48: =MIN(M47,5) -> 5 | N48: =MIN(N47,5) -> 5 | O48: =MIN(O47,5) -> 5 | P48: =MIN(P47,5) -> 5 | Q48: =MIN(Q47,5) -> 5 | ... AB48: =MIN(AB47,5) -> 3.3505096 | AE48: =MIN(AE47,5) -> 4.5565844 | AF48: =MIN(AF47,5) -> 5 | AG48: =MIN(AG47,5) -> 5 | AH48: =MIN(AH47,5) -> 5 | AI48: =MIN(AI47,5) -> 5 | AJ48: =MIN(AJ47,5) -> 4.5111111 | AK48: =MIN(AK47,5) -> 5 | AL48: =MIN(AL47,5) -> 5 | ... CK48: =MIN(CK47,5) -> 3.4323461
B49: CLTV | C49: =C48*C44 -> 13409188 | D49: =D48*D44 -> 5462315.2 | E49: =E48*E44 -> 9415528.7 | F49: =F48*F44 -> 15858297 | G49: =G48*G44 -> 12097354 | J49: =J48*J44 -> 1036658.3 | K49: =K48*K44 -> 998346.85 | L49: =L48*L44 -> 922138.36 | M49: =M48*M44 -> 988107.35 | N49: =N48*N44 -> 1459551.4 | O49: =O48*O44 -> 1408319.3 | P49: =P48*P44 -> 1599853 | Q49: =Q48*Q44 -> 2132556.5 | ... AB49: =AB48*AB44 -> 2530624.8 | AE49: =AE48*AE44 -> 438388 | AF49: =AF48*AF44 -> 355026.01 | AG49: =AG48*AG44 -> 356767.59 | AH49: =AH48*AH44 -> 193863.98 | AI49: =AI48*AI44 -> 483417.59 | AJ49: =AJ48*AJ44 -> 245713.64 | AK49: =AK48*AK44 -> 372124.74 | AL49: =AL48*AL44 -> 349979.22 | ... CK49: =CK48*CK44 -> 1233321.5
B51: Fleet CAC % | C51: =1-'Industrial ARR Rollforward'!C51 -> 0.76134178 | D51: =1-'Industrial ARR Rollforward'!D51 -> 0.62023544 | E51: =1-'Industrial ARR Rollforward'!E51 -> 0.5388743 | F51: =1-'Industrial ARR Rollforward'!F51 -> 0.55043339 | G51: =1-'Industrial ARR Rollforward'!G51 -> 0.5667311 | J51: =AVERAGEIFS($AD51:$BT51,$AD$36:$BT$36,J$36) -> 0.77467956 | K51: =AVERAGEIFS($AD51:$BT51,$AD$36:$BT$36,K$36) -> 0.76122831 | L51: =AVERAGEIFS($AD51:$BT51,$AD$36:$BT$36,L$36) -> 0.72662991 | M51: =AVERAGEIFS($AD51:$BT51,$AD$36:$BT$36,M$36) -> 0.69455417 | N51: =AVERAGEIFS($AD51:$BT51,$AD$36:$BT$36,N$36) -> 0.63478235 | O51: =AVERAGEIFS($AD51:$BT51,$AD$36:$BT$36,O$36) -> 0.59843121 | P51: =AVERAGEIFS($AD51:$BT51,$AD$36:$BT$36,P$36) -> 0.57392076 | Q51: =AVERAGEIFS($AD51:$BT51,$AD$36:$BT$36,Q$36) -> 0.56869335 | ... V51: =AVERAGEIFS($AD51:$BT51,$AD$36:$BT$36,V$36) -> 0.54628064 | W51: =AVERAGEIFS($AD51:$BX51,$AD$36:$BX$36,W$36) -> 0.55535478 | X51: =AVERAGEIFS($AD51:$BY51,$AD$36:$BY$36,X$36) -> 0.56373683 | Y51: =AVERAGEIFS($AD51:$CL51,$AD$36:$CL$36,Y$36) -> 0.58380907 | Z51: =AVERAGEIFS($AD51:$CL51,$AD$36:$CL$36,Z$36) -> 0.58319689 | AA51: =AVERAGEIFS($AD51:$CL51,$AD$36:$CL$36,AA$36) -> 0.5627954 | AB51: =AVERAGEIFS($AD51:$CL51,$AD$36:$CL$36,AB$36) -> 0.54260315 | AE51: =1-'Industrial ARR Rollforward'!AE51 -> 0.78523362 | AF51: =1-'Industrial ARR Rollforward'!AF51 -> 0.77639257 | AG51: =1-'Industrial ARR Rollforward'!AG51 -> 0.7763918 | AH51: =1-'Industrial ARR Rollforward'!AH51 -> 0.77230711 | AI51: =1-'Industrial ARR Rollforward'!AI51 -> 0.77533977 | AJ51: =1-'Industrial ARR Rollforward'!AJ51 -> 0.77314772 | AK51: =1-'Industrial ARR Rollforward'!AK51 -> 0.76827833 | AL51: =1-'Industrial ARR Rollforward'!AL51 -> 0.74225887 | ... CK51: =1-'Industrial ARR Rollforward'!CK51 -> 0.52981992
B52: CAC (S&M) | C52: =SUMIFS($I52:$W52,$I$7:$W$7,C$7) -> 1017863.6 | D52: =+SUM(OFFSET(INDEX($AD52:$CL52,MATCH(D$8,$AD$8:$CL$8,0)),,,,-12)) -> 1900848 | E52: =+SUM(OFFSET(INDEX($AD52:$CL52,MATCH(E$8,$AD$8:$CL$8,0)),,,,-12)) -> 2647280.2 | F52: =+SUM(OFFSET(INDEX($AD52:$CL52,MATCH(F$8,$AD$8:$CL$8,0)),,,,-12)) -> 4222123.8 | G52: =+SUM(OFFSET(INDEX($AD52:$CL52,MATCH(G$8,$AD$8:$CL$8,0)),,,,-12)) -> 5281457.7 | J52: =SUMIFS($AD52:$BT52,$AD$5:$BT$5,J$5) -> 262959.37 | K52: =SUMIFS($AD52:$BT52,$AD$5:$BT$5,K$5) -> 357061.2 | L52: =SUMIFS($AD52:$BT52,$AD$5:$BT$5,L$5) -> 397843.07 | M52: =SUMIFS($AD52:$BT52,$AD$5:$BT$5,M$5) -> 430772.51 | N52: =SUMIFS($AD52:$BT52,$AD$5:$BT$5,N$5) -> 458663.27 | O52: =SUMIFS($AD52:$BT52,$AD$5:$BT$5,O$5) -> 495498.71 | P52: =SUMIFS($AD52:$BT52,$AD$5:$BT$5,P$5) -> 515913.5 | Q52: =SUMIFS($AD52:$BT52,$AD$5:$BT$5,Q$5) -> 568179.16 | ... V52: =SUMIFS($AD52:$BT52,$AD$5:$BT$5,V$5) -> 1047340.1 | W52: =SUMIFS($AD52:$BX52,$AD$5:$BX$5,W$5) -> 1045887.3 | X52: =SUMIFS($AD52:$BY52,$AD$5:$BY$5,X$5) -> 1141527 | Y52: =SUMIFS($AD52:$CL52,$AD$5:$CL$5,Y$5) -> 1200541.5 | Z52: =SUMIFS($AD52:$CL52,$AD$5:$CL$5,Z$5) -> 1283750 | AA52: =SUMIFS($AD52:$CL52,$AD$5:$CL$5,AA$5) -> 1278831.8 | AB52: =SUMIFS($AD52:$CL52,$AD$5:$CL$5,AB$5) -> 1518334.4 | AE52: ='Cons TrioMobil | Monthly'!P256*-1*AE51 -> 86111.726 | AF52: ='Cons TrioMobil | Monthly'!Q256*-1*AF51 -> 97550.467 | AG52: ='Cons TrioMobil | Monthly'!R256*-1*AG51 -> 82493.507 | AH52: ='Cons TrioMobil | Monthly'!S256*-1*AH51 -> 78280.841 | AI52: ='Cons TrioMobil | Monthly'!T256*-1*AI51 -> 102185.02 | AJ52: ='Cons TrioMobil | Monthly'!U256*-1*AJ51 -> 94961.226 | AK52: ='Cons TrioMobil | Monthly'!V256*-1*AK51 -> 112127.46 | AL52: ='Cons TrioMobil | Monthly'!W256*-1*AL51 -> 149972.52 | ... CK52: ='Cons TrioMobil | Monthly'!BV256*-1*CK51 -> 540693.22
B53: CAC / New Logo | C53: =C52/C26 -> 92.499422 | D53: =D52/D26 -> 856.23783 | E53: =E52/E26 -> 1245.7789 | F53: =F52/F26 -> 1504.6771 | G53: =G52/G26 -> 1725.4027 | J53: =J52/J26 -> 601.73769 | K53: =K52/K26 -> 523.55015 | L53: =L52/L26 -> 558.76836 | M53: =M52/M26 -> 790.40827 | N53: =N52/N26 -> 712.21005 | O53: =O52/O26 -> 927.90021 | P53: =P52/P26 -> 1038.0553 | Q53: =Q52/Q26 -> 1036.8233 | ... AB53: =AB52/AB26 -> 1757.3315 | AE53: =AE52/AE26 -> 577.93104 | AF53: =AF52/AF26 -> 587.65342 | AG53: =AG52/AG26 -> 576.87767 | AH53: =AH52/AH26 -> 775.05783 | AI53: =AI52/AI26 -> 529.45607 | AJ53: =AJ52/AJ26 -> 586.1804 | AK53: =AK52/AK26 -> 514.34615 | AL53: =AL52/AL26 -> 496.59774 | ... CK53: =CK52/CK26 -> 1924.1751
B55: LTV-CAC | D55: =D49/D52 -> 2.8736202 | E55: =E49/E52 -> 3.5566801 | F55: =F49/F52 -> 3.7559999 | G55: =G49/G52 -> 2.2905332 | J55: =J49/J52 -> 3.9422754 | K55: =K49/K52 -> 2.7960104 | L55: =L49/L52 -> 2.3178445 | M55: =M49/M52 -> 2.2938032 | N55: =N49/N52 -> 3.1821851 | O55: =O49/O52 -> 2.8422259 | P55: =P49/P52 -> 3.1010102 | Q55: =Q49/Q52 -> 3.753317 | ... AB55: =AB49/AB52 -> 1.6667111 | AE55: =AE49/AE52 -> 5.090921 | AF55: =AF49/AF52 -> 3.6394086 | AG55: =AG49/AG52 -> 4.3247959 | AH55: =AH49/AH52 -> 2.4765189 | AI55: =AI49/AI52 -> 4.7308067 | AJ55: =AJ49/AJ52 -> 2.5875155 | AK55: =AK49/AK52 -> 3.3187654 | AL55: =AL49/AL52 -> 2.3336224 | ... CK55: =CK49/CK52 -> 2.2810005
B56: Payback (months) | D56: =(D52/D44)*12 -> 20.879586 | E56: =(E52/E44)*12 -> 16.869664 | F56: =(F52/F44)*12 -> 15.974441 | G56: =(G52/G44)*12 -> 20.736433 | J56: =(J52/J44)*12 -> 15.219637 | K56: =(K52/K44)*12 -> 21.459147 | L56: =(L52/L44)*12 -> 25.88612 | M56: =(M52/M44)*12 -> 26.157431 | N56: =(N52/N44)*12 -> 18.854968 | O56: =(O52/O44)*12 -> 21.110215 | P56: =(P52/P44)*12 -> 19.348534 | Q56: =(Q52/Q44)*12 -> 15.98586 | ... AB56: =(AB52/AB44)*12 -> 24.123027 | AE56: =(AE52/AE44)*12 -> 10.740495 | AF56: =(AF52/AF44)*12 -> 16.486195 | AG56: =(AG52/AG44)*12 -> 13.873487 | AH56: =(AH52/AH44)*12 -> 24.227556 | AI56: =(AI52/AI44)*12 -> 12.682826 | AJ56: =(AJ52/AJ44)*12 -> 20.92097 | AK56: =(AK52/AK44)*12 -> 18.079012 | AL56: =(AL52/AL44)*12 -> 25.7111 | ... CK56: =(CK52/CK44)*12 -> 18.057055
B59: Check
B61: Ending ARR | C61: =+INDEX('MRR Schedule Summary'!$B$12:$BK$12,MATCH(C$8,'MRR Schedule Summary'!$B$76:$BK$76,0))*12-C14 -> 0 | D61: =+INDEX('MRR Schedule Summary'!$B$12:$BK$12,MATCH(D$8,'MRR Schedule Summary'!$B$76:$BK$76,0))*12-D14 -> 0 | E61: =+INDEX('MRR Schedule Summary'!$B$12:$BK$12,MATCH(E$8,'MRR Schedule Summary'!$B$76:$BK$76,0))*12-E14 -> 0 | F61: =+INDEX('MRR Schedule Summary'!$B$12:$BK$12,MATCH(F$8,'MRR Schedule Summary'!$B$76:$BK$76,0))*12-F14 -> 0 | G61: =+INDEX('MRR Schedule Summary'!$B$12:$BK$12,MATCH(G$8,'MRR Schedule Summary'!$B$76:$BK$76,0))*12-G14 -> 0 | I61: =+INDEX('MRR Schedule Summary'!$B$12:$BK$12,MATCH(I$8,'MRR Schedule Summary'!$B$76:$BK$76,0))*12-I14 -> 0 | J61: =+INDEX('MRR Schedule Summary'!$B$12:$BK$12,MATCH(J$8,'MRR Schedule Summary'!$B$76:$BK$76,0))*12-J14 -> 0 | K61: =+INDEX('MRR Schedule Summary'!$B$12:$BK$12,MATCH(K$8,'MRR Schedule Summary'!$B$76:$BK$76,0))*12-K14 -> 0 | L61: =+INDEX('MRR Schedule Summary'!$B$12:$BK$12,MATCH(L$8,'MRR Schedule Summary'!$B$76:$BK$76,0))*12-L14 -> 0 | M61: =+INDEX('MRR Schedule Summary'!$B$12:$BK$12,MATCH(M$8,'MRR Schedule Summary'!$B$76:$BK$76,0))*12-M14 -> 0 | N61: =+INDEX('MRR Schedule Summary'!$B$12:$BK$12,MATCH(N$8,'MRR Schedule Summary'!$B$76:$BK$76,0))*12-N14 -> 0 | O61: =+INDEX('MRR Schedule Summary'!$B$12:$BK$12,MATCH(O$8,'MRR Schedule Summary'!$B$76:$BK$76,0))*12-O14 -> 0 | P61: =+INDEX('MRR Schedule Summary'!$B$12:$BK$12,MATCH(P$8,'MRR Schedule Summary'!$B$76:$BK$76,0))*12-P14 -> 0 | ... AB61: =+INDEX('MRR Schedule Summary'!$B$12:$BK$12,MATCH(AB$8,'MRR Schedule Summary'!$B$76:$BK$76,0))*12-AB14 -> 0 | AD61: =+INDEX('MRR Schedule Summary'!$B$12:$BK$12,MATCH(AD$8,'MRR Schedule Summary'!$B$76:$BK$76,0))*12-AD14 -> 0 | AE61: =+INDEX('MRR Schedule Summary'!$B$12:$BK$12,MATCH(AE$8,'MRR Schedule Summary'!$B$76:$BK$76,0))*12-AE14 -> 0 | AF61: =+INDEX('MRR Schedule Summary'!$B$12:$BK$12,MATCH(AF$8,'MRR Schedule Summary'!$B$76:$BK$76,0))*12-AF14 -> 0 | AG61: =+INDEX('MRR Schedule Summary'!$B$12:$BK$12,MATCH(AG$8,'MRR Schedule Summary'!$B$76:$BK$76,0))*12-AG14 -> 0 | AH61: =+INDEX('MRR Schedule Summary'!$B$12:$BK$12,MATCH(AH$8,'MRR Schedule Summary'!$B$76:$BK$76,0))*12-AH14 -> 0 | AI61: =+INDEX('MRR Schedule Summary'!$B$12:$BK$12,MATCH(AI$8,'MRR Schedule Summary'!$B$76:$BK$76,0))*12-AI14 -> 0 | AJ61: =+INDEX('MRR Schedule Summary'!$B$12:$BK$12,MATCH(AJ$8,'MRR Schedule Summary'!$B$76:$BK$76,0))*12-AJ14 -> 0 | AK61: =+INDEX('MRR Schedule Summary'!$B$12:$BK$12,MATCH(AK$8,'MRR Schedule Summary'!$B$76:$BK$76,0))*12-AK14 -> 0 | ... CK61: =+INDEX('MRR Schedule Summary'!$B$12:$BK$12,MATCH(CK$8,'MRR Schedule Summary'!$B$76:$BK$76,0))*12-CK14 -> 0
B62: Ending Logos | C62: =+INDEX('MRR Schedule Summary'!$B$20:$BK$20,MATCH(C$8,'MRR Schedule Summary'!$B$76:$BK$76,0))-C28 -> 0 | D62: =+INDEX('MRR Schedule Summary'!$B$20:$BK$20,MATCH(D$8,'MRR Schedule Summary'!$B$76:$BK$76,0))-D28 -> 0 | E62: =+INDEX('MRR Schedule Summary'!$B$20:$BK$20,MATCH(E$8,'MRR Schedule Summary'!$B$76:$BK$76,0))-E28 -> 0 | F62: =+INDEX('MRR Schedule Summary'!$B$20:$BK$20,MATCH(F$8,'MRR Schedule Summary'!$B$76:$BK$76,0))-F28 -> 0 | G62: =+INDEX('MRR Schedule Summary'!$B$20:$BK$20,MATCH(G$8,'MRR Schedule Summary'!$B$76:$BK$76,0))-G28 -> 0 | I62: =+INDEX('MRR Schedule Summary'!$B$20:$BK$20,MATCH(I$8,'MRR Schedule Summary'!$B$76:$BK$76,0))-I28 -> 0 | J62: =+INDEX('MRR Schedule Summary'!$B$20:$BK$20,MATCH(J$8,'MRR Schedule Summary'!$B$76:$BK$76,0))-J28 -> 0 | K62: =+INDEX('MRR Schedule Summary'!$B$20:$BK$20,MATCH(K$8,'MRR Schedule Summary'!$B$76:$BK$76,0))-K28 -> 0 | L62: =+INDEX('MRR Schedule Summary'!$B$20:$BK$20,MATCH(L$8,'MRR Schedule Summary'!$B$76:$BK$76,0))-L28 -> 0 | M62: =+INDEX('MRR Schedule Summary'!$B$20:$BK$20,MATCH(M$8,'MRR Schedule Summary'!$B$76:$BK$76,0))-M28 -> 0 | N62: =+INDEX('MRR Schedule Summary'!$B$20:$BK$20,MATCH(N$8,'MRR Schedule Summary'!$B$76:$BK$76,0))-N28 -> 0 | O62: =+INDEX('MRR Schedule Summary'!$B$20:$BK$20,MATCH(O$8,'MRR Schedule Summary'!$B$76:$BK$76,0))-O28 -> 0 | P62: =+INDEX('MRR Schedule Summary'!$B$20:$BK$20,MATCH(P$8,'MRR Schedule Summary'!$B$76:$BK$76,0))-P28 -> 0 | ... AB62: =+INDEX('MRR Schedule Summary'!$B$20:$BK$20,MATCH(AB$8,'MRR Schedule Summary'!$B$76:$BK$76,0))-AB28 -> 0 | AD62: =+INDEX('MRR Schedule Summary'!$B$20:$BK$20,MATCH(AD$8,'MRR Schedule Summary'!$B$76:$BK$76,0))-AD28 -> 0 | AE62: =+INDEX('MRR Schedule Summary'!$B$20:$BK$20,MATCH(AE$8,'MRR Schedule Summary'!$B$76:$BK$76,0))-AE28 -> 0 | AF62: =+INDEX('MRR Schedule Summary'!$B$20:$BK$20,MATCH(AF$8,'MRR Schedule Summary'!$B$76:$BK$76,0))-AF28 -> 0 | AG62: =+INDEX('MRR Schedule Summary'!$B$20:$BK$20,MATCH(AG$8,'MRR Schedule Summary'!$B$76:$BK$76,0))-AG28 -> 0 | AH62: =+INDEX('MRR Schedule Summary'!$B$20:$BK$20,MATCH(AH$8,'MRR Schedule Summary'!$B$76:$BK$76,0))-AH28 -> 0 | AI62: =+INDEX('MRR Schedule Summary'!$B$20:$BK$20,MATCH(AI$8,'MRR Schedule Summary'!$B$76:$BK$76,0))-AI28 -> 0 | AJ62: =+INDEX('MRR Schedule Summary'!$B$20:$BK$20,MATCH(AJ$8,'MRR Schedule Summary'!$B$76:$BK$76,0))-AJ28 -> 0 | AK62: =+INDEX('MRR Schedule Summary'!$B$20:$BK$20,MATCH(AK$8,'MRR Schedule Summary'!$B$76:$BK$76,0))-AK28 -> 0 | ... CK62: =+INDEX('MRR Schedule Summary'!$B$20:$BK$20,MATCH(CK$8,'MRR Schedule Summary'!$B$76:$BK$76,0))-CK28 -> 0
B63: S&M | D63: =+SUM(OFFSET(INDEX($AD52:$CL52,MATCH(D$8,$AD$8:$CL$8,0)),,,,-12))-D52 -> 0 | E63: =+SUM(OFFSET(INDEX($AD52:$CL52,MATCH(E$8,$AD$8:$CL$8,0)),,,,-12))-E52 -> 0 | F63: =+SUM(OFFSET(INDEX($AD52:$CL52,MATCH(F$8,$AD$8:$CL$8,0)),,,,-12))-F52 -> 0 | G63: =+SUM(OFFSET(INDEX($AD52:$CL52,MATCH(G$8,$AD$8:$CL$8,0)),,,,-12))-G52 -> 0 | J63: =SUMIFS($AD$52:$BT$52,$AD$36:$BT$36,J$36)-J52 -> 0 | K63: =SUMIFS($AD$52:$BT$52,$AD$36:$BT$36,K$36)-K52 -> 0 | L63: =SUMIFS($AD$52:$BT$52,$AD$36:$BT$36,L$36)-L52 -> 0 | M63: =SUMIFS($AD$52:$BT$52,$AD$36:$BT$36,M$36)-M52 -> 0 | N63: =SUMIFS($AD$52:$BT$52,$AD$36:$BT$36,N$36)-N52 -> 0 | O63: =SUMIFS($AD$52:$BT$52,$AD$36:$BT$36,O$36)-O52 -> 0 | P63: =SUMIFS($AD$52:$BT$52,$AD$36:$BT$36,P$36)-P52 -> 0 | Q63: =SUMIFS($AD$52:$BT$52,$AD$36:$BT$36,Q$36)-Q52 -> 0 | ... V63: =SUMIFS($AD$52:$BT$52,$AD$36:$BT$36,V$36)-V52 -> 0 | W63: =SUMIFS($AD$52:$BX$52,$AD$36:$BX$36,W$36)-W52 -> 0 | X63: =SUMIFS($AD$52:$BY$52,$AD$36:$BY$36,X$36)-X52 -> 0 | Y63: =SUMIFS($AD$52:$CL$52,$AD$36:$CL$36,Y$36)-Y52 -> 0 | Z63: =SUMIFS($AD$52:$CL$52,$AD$36:$CL$36,Z$36)-Z52 -> 0 | AA63: =SUMIFS($AD$52:$CL$52,$AD$36:$CL$36,AA$36)-AA52 -> 0 | AB63: =SUMIFS($AD$52:$CL$52,$AD$36:$CL$36,AB$36)-AB52 -> 0 | AE63: =('Cons TrioMobil | Monthly'!P256*-1*AE51)-AE52 -> 0 | AF63: =('Cons TrioMobil | Monthly'!Q256*-1*AF51)-AF52 -> 0 | AG63: =('Cons TrioMobil | Monthly'!R256*-1*AG51)-AG52 -> 0 | AH63: =('Cons TrioMobil | Monthly'!S256*-1*AH51)-AH52 -> 0 | AI63: =('Cons TrioMobil | Monthly'!T256*-1*AI51)-AI52 -> 0 | AJ63: =('Cons TrioMobil | Monthly'!U256*-1*AJ51)-AJ52 -> 0 | AK63: =('Cons TrioMobil | Monthly'!V256*-1*AK51)-AK52 -> 0 | AL63: =('Cons TrioMobil | Monthly'!W256*-1*AL51)-AL52 -> 0 | ... CK63: =('Cons TrioMobil | Monthly'!BV256*-1*CK51)-CK52 -> 0
B64: Payback Period | D64: =((D44/12)*D56)-D52 -> 0 | E64: =((E44/12)*E56)-E52 -> 0 | F64: =((F44/12)*F56)-F52 -> 0 | G64: =((G44/12)*G56)-G52 -> 0 | J64: =((J44/12)*J56)-J52 -> 0 | K64: =((K44/12)*K56)-K52 -> 0 | L64: =((L44/12)*L56)-L52 -> 0 | M64: =((M44/12)*M56)-M52 -> 0 | N64: =((N44/12)*N56)-N52 -> 0 | O64: =((O44/12)*O56)-O52 -> 0 | P64: =((P44/12)*P56)-P52 -> 0 | Q64: =((Q44/12)*Q56)-Q52 -> 0 | ... AB64: =((AB44/12)*AB56)-AB52 -> 0 | AE64: =((AE44/12)*AE56)-AE52 -> 0 | AF64: =((AF44/12)*AF56)-AF52 -> 0 | AG64: =((AG44/12)*AG56)-AG52 -> 0 | AH64: =((AH44/12)*AH56)-AH52 -> 0 | AI64: =((AI44/12)*AI56)-AI52 -> 0 | AJ64: =((AJ44/12)*AJ56)-AJ52 -> 0 | AK64: =((AK44/12)*AK56)-AK52 -> 0 | AL64: =((AL44/12)*AL56)-AL52 -> 0 | ... CK64: =((CK44/12)*CK56)-CK52 -> 0

Sheet BS and CFS
B2: Trio Mobil
B3: BS and CFS
B5: Monthly Balance Sheet - Actuals | AN5: Quarterly BS | AW5: YTD, TTM, Annual BS
C7: Actuals | D7: Actuals | E7: Actuals | F7: Actuals | G7: Actuals | H7: Actuals | I7: Actuals | J7: Actuals | K7: Actuals | L7: Actuals | M7: Actuals | N7: Actuals | O7: Actuals | P7: Actuals | Q7: Actuals | R7: Actuals | S7: Actuals | T7: Actuals | U7: Actuals | V7: Actuals | W7: Actuals | X7: Actuals | Y7: Actuals | Z7: Actuals | AA7: Actuals | AB7: Actuals | AC7: Actuals | AD7: Actuals | AE7: Actuals | AF7: Actuals | AG7: Actuals | AH7: Actuals | AI7: Actuals | AJ7: Actuals | AK7: Actuals | AL7: Actuals | AN7: Actuals | AO7: Actuals | AP7: Actuals | AQ7: Actuals | AR7: Actuals | AS7: Actuals | AT7: Actuals | AU7: Actuals | AW7: Actuals | AX7: Actuals | AY7: Forecast
B8: Balance Sheet | C8: Q1 | D8: Q1 | E8: Q1 | F8: Q2 | G8: Q2 | H8: Q2 | I8: Q3 | J8: Q3 | K8: Q3 | L8: Q4 | M8: Q4 | N8: Q4 | O8: Q1 | P8: Q1 | Q8: Q1 | R8: Q2 | S8: Q2 | T8: Q2 | U8: Q3 | V8: Q3 | W8: Q3 | X8: Q4 | Y8: Q4 | Z8: Q4 | AA8: Q1 | AB8: Q1 | AC8: Q1 | AD8: Q2 | AE8: Q2 | AF8: Q2 | AG8: Q3 | AH8: Q3 | AI8: Q3 | AJ8: Q4 | AK8: Q4 | AL8: Q4 | AN8: Q1 | AO8: Q2 | AP8: Q3 | AQ8: Q4 | AR8: Q1 | AS8: Q2 | AT8: Q3 | AU8: Q4 | AW8: YTD | AX8: TTM | AY8: Annual
B9: ($ in USD) | C9: 44957 | D9: =EOMONTH(C9,1) -> 44985 | E9: =EOMONTH(D9,1) -> 45016 | F9: =EOMONTH(E9,1) -> 45046 | G9: =EOMONTH(F9,1) -> 45077 | H9: =EOMONTH(G9,1) -> 45107 | I9: =EOMONTH(H9,1) -> 45138 | J9: =EOMONTH(I9,1) -> 45169 | K9: =EOMONTH(J9,1) -> 45199 | ... N9: =EOMONTH(M9,1) -> 45291 | O9: 45322 | P9: =EOMONTH(O9,1) -> 45351 | Q9: =EOMONTH(P9,1) -> 45382 | R9: =EOMONTH(Q9,1) -> 45412 | S9: =EOMONTH(R9,1) -> 45443 | T9: =EOMONTH(S9,1) -> 45473 | U9: =EOMONTH(T9,1) -> 45504 | V9: =EOMONTH(U9,1) -> 45535 | W9: =EOMONTH(V9,1) -> 45565 | ... AL9: =EOMONTH(AK9,1) -> 46022 | AN9: 45382 | AO9: =EOMONTH(AN9,3) -> 45473 | AP9: =EOMONTH(AO9,3) -> 45565 | AQ9: =EOMONTH(AP9,3) -> 45657 | AR9: =EOMONTH(AQ9,3) -> 45747 | AS9: =EOMONTH(AR9,3) -> 45838 | AT9: =EOMONTH(AS9,3) -> 45930 | AU9: =EOMONTH(AT9,3) -> 46022 | AW9: 46022 | AX9: =+AW9 -> 46022 | AY9: 45657
B11: Assets
B12: Cash | C12: ='Cons TrioMobil | Monthly'!AM124 -> 2387044.7 | D12: ='Cons TrioMobil | Monthly'!AN124 -> 2347532.2 | E12: ='Cons TrioMobil | Monthly'!AO124 -> 2703909.1 | F12: ='Cons TrioMobil | Monthly'!AP124 -> 2462899.5 | G12: ='Cons TrioMobil | Monthly'!AQ124 -> 2260606.7 | H12: ='Cons TrioMobil | Monthly'!AR124 -> 2153664.8 | I12: ='Cons TrioMobil | Monthly'!AS124 -> 2054208.8 | J12: ='Cons TrioMobil | Monthly'!AT124 -> 2299634 | ... AL12: ='Cons TrioMobil | Monthly'!BV124 -> 8075653.4 | AN12: =INDEX($C12:$Z12,MATCH(AN$9,$C$9:$Z$9,0)) -> 2370694.1 | AO12: =INDEX($C12:$Z12,MATCH(AO$9,$C$9:$Z$9,0)) -> 2322322.5 | AP12: =INDEX($C12:$Z12,MATCH(AP$9,$C$9:$Z$9,0)) -> 15328047 | AQ12: =INDEX($C12:$Z12,MATCH(AQ$9,$C$9:$Z$9,0)) -> 13794875 | AR12: =INDEX($C12:$AM12,MATCH(AR$9,$C$9:$AM$9,0)) -> 12667611 | AS12: =INDEX($C12:$AM12,MATCH(AS$9,$C$9:$AM$9,0)) -> 10576120 | AT12: =INDEX($C12:$AM12,MATCH(AT$9,$C$9:$AM$9,0)) -> 8915850.5 | AU12: =INDEX($C12:$AM12,MATCH(AU$9,$C$9:$AM$9,0)) -> 8075653.4 | AW12: =INDEX($C12:$AM12,MATCH(AW$9,$C$9:$AM$9,0)) -> 8075653.4 | AX12: =INDEX($C12:$AM12,MATCH(AX$9,$C$9:$AM$9,0)) -> 8075653.4 | AY12: =INDEX($C12:$Z12,MATCH(AY$9,$C$9:$Z$9,0)) -> 13794875
B13: Receivables | C13: =SUM('Cons TrioMobil | Monthly'!AM128,'Cons TrioMobil | Monthly'!AM135) -> 1825627.9 | D13: =SUM('Cons TrioMobil | Monthly'!AN128,'Cons TrioMobil | Monthly'!AN135) -> 2075187.9 | E13: =SUM('Cons TrioMobil | Monthly'!AO128,'Cons TrioMobil | Monthly'!AO135) -> 1890834.3 | F13: =SUM('Cons TrioMobil | Monthly'!AP128,'Cons TrioMobil | Monthly'!AP135) -> 1939427.7 | G13: =SUM('Cons TrioMobil | Monthly'!AQ128,'Cons TrioMobil | Monthly'!AQ135) -> 2058171.4 | H13: =SUM('Cons TrioMobil | Monthly'!AR128,'Cons TrioMobil | Monthly'!AR135) -> 2517687.6 | I13: =SUM('Cons TrioMobil | Monthly'!AS128,'Cons TrioMobil | Monthly'!AS135) -> 2535163.6 | J13: =SUM('Cons TrioMobil | Monthly'!AT128,'Cons TrioMobil | Monthly'!AT135) -> 3288294.7 | ... AL13: =SUM('Cons TrioMobil | Monthly'!BV128,'Cons TrioMobil | Monthly'!BV135) -> 3926386.8 | AN13: =INDEX($C13:$Z13,MATCH(AN$9,$C$9:$Z$9,0)) -> 3384535.3 | AO13: =INDEX($C13:$Z13,MATCH(AO$9,$C$9:$Z$9,0)) -> 3832561.2 | AP13: =INDEX($C13:$Z13,MATCH(AP$9,$C$9:$Z$9,0)) -> 3885375.7 | AQ13: =INDEX($C13:$Z13,MATCH(AQ$9,$C$9:$Z$9,0)) -> 4977943 | AR13: =INDEX($C13:$AM13,MATCH(AR$9,$C$9:$AM$9,0)) -> 4690736.9 | AS13: =INDEX($C13:$AM13,MATCH(AS$9,$C$9:$AM$9,0)) -> 3827867.9 | AT13: =INDEX($C13:$AM13,MATCH(AT$9,$C$9:$AM$9,0)) -> 3759206.2 | AU13: =INDEX($C13:$AM13,MATCH(AU$9,$C$9:$AM$9,0)) -> 3926386.8 | AW13: =INDEX($C13:$AM13,MATCH(AW$9,$C$9:$AM$9,0)) -> 3926386.8 | AX13: =INDEX($C13:$AM13,MATCH(AX$9,$C$9:$AM$9,0)) -> 3926386.8 | AY13: =INDEX($C13:$Z13,MATCH(AY$9,$C$9:$Z$9,0)) -> 4977943
B14: Inventory | C14: ='Cons TrioMobil | Monthly'!AM134 -> 1424213.3 | D14: ='Cons TrioMobil | Monthly'!AN134 -> 1452820.2 | E14: ='Cons TrioMobil | Monthly'!AO134 -> 1472977.6 | F14: ='Cons TrioMobil | Monthly'!AP134 -> 1467995.5 | G14: ='Cons TrioMobil | Monthly'!AQ134 -> 1452011.4 | H14: ='Cons TrioMobil | Monthly'!AR134 -> 1161756.4 | I14: ='Cons TrioMobil | Monthly'!AS134 -> 1184034.6 | J14: ='Cons TrioMobil | Monthly'!AT134 -> 1208201.9 | ... AL14: ='Cons TrioMobil | Monthly'!BV134 -> 3170924.9 | AN14: =INDEX($C14:$Z14,MATCH(AN$9,$C$9:$Z$9,0)) -> 1586690.1 | AO14: =INDEX($C14:$Z14,MATCH(AO$9,$C$9:$Z$9,0)) -> 1892123.3 | AP14: =INDEX($C14:$Z14,MATCH(AP$9,$C$9:$Z$9,0)) -> 2220515.1 | AQ14: =INDEX($C14:$Z14,MATCH(AQ$9,$C$9:$Z$9,0)) -> 2297274.8 | AR14: =INDEX($C14:$AM14,MATCH(AR$9,$C$9:$AM$9,0)) -> 2244459.1 | AS14: =INDEX($C14:$AM14,MATCH(AS$9,$C$9:$AM$9,0)) -> 3070627.9 | AT14: =INDEX($C14:$AM14,MATCH(AT$9,$C$9:$AM$9,0)) -> 3062893.4 | AU14: =INDEX($C14:$AM14,MATCH(AU$9,$C$9:$AM$9,0)) -> 3170924.9 | AW14: =INDEX($C14:$AM14,MATCH(AW$9,$C$9:$AM$9,0)) -> 3170924.9 | AX14: =INDEX($C14:$AM14,MATCH(AX$9,$C$9:$AM$9,0)) -> 3170924.9 | AY14: =INDEX($C14:$Z14,MATCH(AY$9,$C$9:$Z$9,0)) -> 2297274.8
B15: Other | C15: ='Cons TrioMobil | Monthly'!AM138 -> 803165.06 | D15: ='Cons TrioMobil | Monthly'!AN138 -> 837164.54 | E15: ='Cons TrioMobil | Monthly'!AO138 -> 979857.86 | F15: ='Cons TrioMobil | Monthly'!AP138 -> 1083813.9 | G15: ='Cons TrioMobil | Monthly'!AQ138 -> 1096101.7 | H15: ='Cons TrioMobil | Monthly'!AR138 -> 1174948.9 | I15: ='Cons TrioMobil | Monthly'!AS138 -> 1189947.7 | J15: ='Cons TrioMobil | Monthly'!AT138 -> 1203107.6 | ... AL15: ='Cons TrioMobil | Monthly'!BV138 -> 2998839.2 | AN15: =INDEX($C15:$Z15,MATCH(AN$9,$C$9:$Z$9,0)) -> 1651970.8 | AO15: =INDEX($C15:$Z15,MATCH(AO$9,$C$9:$Z$9,0)) -> 1672962.5 | AP15: =INDEX($C15:$Z15,MATCH(AP$9,$C$9:$Z$9,0)) -> 1989116.2 | AQ15: =INDEX($C15:$Z15,MATCH(AQ$9,$C$9:$Z$9,0)) -> 2203270.1 | AR15: =INDEX($C15:$AM15,MATCH(AR$9,$C$9:$AM$9,0)) -> 2482818.8 | AS15: =INDEX($C15:$AM15,MATCH(AS$9,$C$9:$AM$9,0)) -> 2959722.1 | AT15: =INDEX($C15:$AM15,MATCH(AT$9,$C$9:$AM$9,0)) -> 2554990.5 | AU15: =INDEX($C15:$AM15,MATCH(AU$9,$C$9:$AM$9,0)) -> 2998839.2 | AW15: =INDEX($C15:$AM15,MATCH(AW$9,$C$9:$AM$9,0)) -> 2998839.2 | AX15: =INDEX($C15:$AM15,MATCH(AX$9,$C$9:$AM$9,0)) -> 2998839.2 | AY15: =INDEX($C15:$Z15,MATCH(AY$9,$C$9:$Z$9,0)) -> 2203270.1
B16: Non-Current | C16: =SUM('Cons TrioMobil | Monthly'!AM145:AM149) -> 1507171.6 | D16: =SUM('Cons TrioMobil | Monthly'!AN145:AN149) -> 1513178.2 | E16: =SUM('Cons TrioMobil | Monthly'!AO145:AO149) -> 1517538 | F16: =SUM('Cons TrioMobil | Monthly'!AP145:AP149) -> 1524485.5 | G16: =SUM('Cons TrioMobil | Monthly'!AQ145:AQ149) -> 1531686.8 | H16: =SUM('Cons TrioMobil | Monthly'!AR145:AR149) -> 1515879.5 | I16: =SUM('Cons TrioMobil | Monthly'!AS145:AS149) -> 1521460.5 | J16: =SUM('Cons TrioMobil | Monthly'!AT145:AT149) -> 1506852.4 | ... AL16: =SUM('Cons TrioMobil | Monthly'!BV145:BV149) -> 5751824.2 | AN16: =INDEX($C16:$Z16,MATCH(AN$9,$C$9:$Z$9,0)) -> 3700045 | AO16: =INDEX($C16:$Z16,MATCH(AO$9,$C$9:$Z$9,0)) -> 4792074.2 | AP16: =INDEX($C16:$Z16,MATCH(AP$9,$C$9:$Z$9,0)) -> 4476039.6 | AQ16: =INDEX($C16:$Z16,MATCH(AQ$9,$C$9:$Z$9,0)) -> 4748600.3 | AR16: =INDEX($C16:$AM16,MATCH(AR$9,$C$9:$AM$9,0)) -> 5235101.2 | AS16: =INDEX($C16:$AM16,MATCH(AS$9,$C$9:$AM$9,0)) -> 5307357.6 | AT16: =INDEX($C16:$AM16,MATCH(AT$9,$C$9:$AM$9,0)) -> 5394844.2 | AU16: =INDEX($C16:$AM16,MATCH(AU$9,$C$9:$AM$9,0)) -> 5751824.2 | AW16: =INDEX($C16:$AM16,MATCH(AW$9,$C$9:$AM$9,0)) -> 5751824.2 | AX16: =INDEX($C16:$AM16,MATCH(AX$9,$C$9:$AM$9,0)) -> 5751824.2 | AY16: =INDEX($C16:$Z16,MATCH(AY$9,$C$9:$Z$9,0)) -> 4748600.3
B17: Total | C17: =SUM(C12:C16) -> 7947222.6 | D17: =SUM(D12:D16) -> 8225883.1 | E17: =SUM(E12:E16) -> 8565116.9 | F17: =SUM(F12:F16) -> 8478622.1 | G17: =SUM(G12:G16) -> 8398578 | H17: =SUM(H12:H16) -> 8523937.1 | I17: =SUM(I12:I16) -> 8484815.3 | J17: =SUM(J12:J16) -> 9506090.7 | ... AL17: =SUM(AL12:AL16) -> 23923628 | AN17: =SUM(AN12:AN16) -> 12693935 | AO17: =SUM(AO12:AO16) -> 14512044 | AP17: =SUM(AP12:AP16) -> 27899094 | AQ17: =SUM(AQ12:AQ16) -> 28021963 | AR17: =SUM(AR12:AR16) -> 27320727 | AS17: =SUM(AS12:AS16) -> 25741696 | AT17: =SUM(AT12:AT16) -> 23687785 | AU17: =SUM(AU12:AU16) -> 23923628 | AW17: =SUM(AW12:AW16) -> 23923628 | AX17: =SUM(AX12:AX16) -> 23923628 | AY17: =SUM(AY12:AY16) -> 28021963
B19: Liabilities
B20: Bank Loans | C20: ='Cons TrioMobil | Monthly'!AM153 -> 356503.88 | D20: ='Cons TrioMobil | Monthly'!AN153 -> 583339.94 | E20: ='Cons TrioMobil | Monthly'!AO153 -> 830475.3 | F20: ='Cons TrioMobil | Monthly'!AP153 -> 805208.11 | G20: ='Cons TrioMobil | Monthly'!AQ153 -> 850910.08 | H20: ='Cons TrioMobil | Monthly'!AR153 -> 639493.36 | I20: ='Cons TrioMobil | Monthly'!AS153 -> 678463.03 | J20: ='Cons TrioMobil | Monthly'!AT153 -> 822064.19 | ... AL20: ='Cons TrioMobil | Monthly'!BV153 -> 2358610.3 | AN20: =INDEX($C20:$Z20,MATCH(AN$9,$C$9:$Z$9,0)) -> 948424.46 | AO20: =INDEX($C20:$Z20,MATCH(AO$9,$C$9:$Z$9,0)) -> 1705053.6 | AP20: =INDEX($C20:$Z20,MATCH(AP$9,$C$9:$Z$9,0)) -> 1405809.9 | AQ20: =INDEX($C20:$Z20,MATCH(AQ$9,$C$9:$Z$9,0)) -> 1582794.2 | AR20: =INDEX($C20:$AM20,MATCH(AR$9,$C$9:$AM$9,0)) -> 1514876.7 | AS20: =INDEX($C20:$AM20,MATCH(AS$9,$C$9:$AM$9,0)) -> 1131788.1 | AT20: =INDEX($C20:$AM20,MATCH(AT$9,$C$9:$AM$9,0)) -> 1539512.9 | AU20: =INDEX($C20:$AM20,MATCH(AU$9,$C$9:$AM$9,0)) -> 2358610.3 | AW20: =INDEX($C20:$AM20,MATCH(AW$9,$C$9:$AM$9,0)) -> 2358610.3 | AX20: =INDEX($C20:$AM20,MATCH(AX$9,$C$9:$AM$9,0)) -> 2358610.3 | AY20: =INDEX($C20:$Z20,MATCH(AY$9,$C$9:$Z$9,0)) -> 1582794.2
B21: Payables | C21: ='Cons TrioMobil | Monthly'!AM154+'Cons TrioMobil | Monthly'!AM155+'Cons TrioMobil | Monthly'!AM158+'Cons TrioMobil | Monthly'!AM159+'Cons TrioMobil | Monthly'!AM160+'Cons TrioMobil | Monthly'!AM162 -> 603014.51 | D21: ='Cons TrioMobil | Monthly'!AN154+'Cons TrioMobil | Monthly'!AN155+'Cons TrioMobil | Monthly'!AN158+'Cons TrioMobil | Monthly'!AN159+'Cons TrioMobil | Monthly'!AN160+'Cons TrioMobil | Monthly'!AN162 -> 832010.82 | E21: ='Cons TrioMobil | Monthly'!AO154+'Cons TrioMobil | Monthly'!AO155+'Cons TrioMobil | Monthly'!AO158+'Cons TrioMobil | Monthly'!AO159+'Cons TrioMobil | Monthly'!AO160+'Cons TrioMobil | Monthly'!AO162 -> 943322.29 | F21: ='Cons TrioMobil | Monthly'!AP154+'Cons TrioMobil | Monthly'!AP155+'Cons TrioMobil | Monthly'!AP158+'Cons TrioMobil | Monthly'!AP159+'Cons TrioMobil | Monthly'!AP160+'Cons TrioMobil | Monthly'!AP162 -> 933670.43 | G21: ='Cons TrioMobil | Monthly'!AQ154+'Cons TrioMobil | Monthly'!AQ155+'Cons TrioMobil | Monthly'!AQ158+'Cons TrioMobil | Monthly'!AQ159+'Cons TrioMobil | Monthly'!AQ160+'Cons TrioMobil | Monthly'!AQ162 -> 852894.99 | H21: ='Cons TrioMobil | Monthly'!AR154+'Cons TrioMobil | Monthly'!AR155+'Cons TrioMobil | Monthly'!AR158+'Cons TrioMobil | Monthly'!AR159+'Cons TrioMobil | Monthly'!AR160+'Cons TrioMobil | Monthly'!AR162 -> 776881.68 | I21: ='Cons TrioMobil | Monthly'!AS154+'Cons TrioMobil | Monthly'!AS155+'Cons TrioMobil | Monthly'!AS158+'Cons TrioMobil | Monthly'!AS159+'Cons TrioMobil | Monthly'!AS160+'Cons TrioMobil | Monthly'!AS162 -> 940425.94 | J21: ='Cons TrioMobil | Monthly'!AT154+'Cons TrioMobil | Monthly'!AT155+'Cons TrioMobil | Monthly'!AT158+'Cons TrioMobil | Monthly'!AT159+'Cons TrioMobil | Monthly'!AT160+'Cons TrioMobil | Monthly'!AT162 -> 1113948.4 | ... AL21: ='Cons TrioMobil | Monthly'!BV154+'Cons TrioMobil | Monthly'!BV155+'Cons TrioMobil | Monthly'!BV158+'Cons TrioMobil | Monthly'!BV159+'Cons TrioMobil | Monthly'!BV160+'Cons TrioMobil | Monthly'!BV162 -> 2668005.3 | AN21: =INDEX($C21:$Z21,MATCH(AN$9,$C$9:$Z$9,0)) -> 2725939.2 | AO21: =INDEX($C21:$Z21,MATCH(AO$9,$C$9:$Z$9,0)) -> 3073342.8 | AP21: =INDEX($C21:$Z21,MATCH(AP$9,$C$9:$Z$9,0)) -> 1587193.4 | AQ21: =INDEX($C21:$Z21,MATCH(AQ$9,$C$9:$Z$9,0)) -> 1796587.3 | AR21: =INDEX($C21:$AM21,MATCH(AR$9,$C$9:$AM$9,0)) -> 2237883.9 | AS21: =INDEX($C21:$AM21,MATCH(AS$9,$C$9:$AM$9,0)) -> 2315602 | AT21: =INDEX($C21:$AM21,MATCH(AT$9,$C$9:$AM$9,0)) -> 1952330.5 | AU21: =INDEX($C21:$AM21,MATCH(AU$9,$C$9:$AM$9,0)) -> 2668005.3 | AW21: =INDEX($C21:$AM21,MATCH(AW$9,$C$9:$AM$9,0)) -> 2668005.3 | AX21: =INDEX($C21:$AM21,MATCH(AX$9,$C$9:$AM$9,0)) -> 2668005.3 | AY21: =INDEX($C21:$Z21,MATCH(AY$9,$C$9:$Z$9,0)) -> 1796587.3
B22: Deferred Revenue | C22: ='Cons TrioMobil | Monthly'!AM161 -> 3758078.3 | D22: ='Cons TrioMobil | Monthly'!AN161 -> 3934957.1 | E22: ='Cons TrioMobil | Monthly'!AO161 -> 4185234 | F22: ='Cons TrioMobil | Monthly'!AP161 -> 4275630.9 | G22: ='Cons TrioMobil | Monthly'!AQ161 -> 4423455.5 | H22: ='Cons TrioMobil | Monthly'!AR161 -> 4561409.1 | I22: ='Cons TrioMobil | Monthly'!AS161 -> 4655140.5 | J22: ='Cons TrioMobil | Monthly'!AT161 -> 5331253.6 | ... AL22: ='Cons TrioMobil | Monthly'!BV161 -> 15009979 | AN22: =INDEX($C22:$Z22,MATCH(AN$9,$C$9:$Z$9,0)) -> 11276616 | AO22: =INDEX($C22:$Z22,MATCH(AO$9,$C$9:$Z$9,0)) -> 11959035 | AP22: =INDEX($C22:$Z22,MATCH(AP$9,$C$9:$Z$9,0)) -> 13038324 | AQ22: =INDEX($C22:$Z22,MATCH(AQ$9,$C$9:$Z$9,0)) -> 13960349 | AR22: =INDEX($C22:$AM22,MATCH(AR$9,$C$9:$AM$9,0)) -> 14509707 | AS22: =INDEX($C22:$AM22,MATCH(AS$9,$C$9:$AM$9,0)) -> 14694960 | AT22: =INDEX($C22:$AM22,MATCH(AT$9,$C$9:$AM$9,0)) -> 14668983 | AU22: =INDEX($C22:$AM22,MATCH(AU$9,$C$9:$AM$9,0)) -> 15009979 | AW22: =INDEX($C22:$AM22,MATCH(AW$9,$C$9:$AM$9,0)) -> 15009979 | AX22: =INDEX($C22:$AM22,MATCH(AX$9,$C$9:$AM$9,0)) -> 15009979 | AY22: =INDEX($C22:$Z22,MATCH(AY$9,$C$9:$Z$9,0)) -> 13960349
B23: Other | C23: ='Cons TrioMobil | Monthly'!AM163 -> 300821.88 | D23: ='Cons TrioMobil | Monthly'!AN163 -> 185044.48 | E23: ='Cons TrioMobil | Monthly'!AO163 -> 211872.11 | F23: ='Cons TrioMobil | Monthly'!AP163 -> 428654.19 | G23: ='Cons TrioMobil | Monthly'!AQ163 -> 453756.64 | H23: ='Cons TrioMobil | Monthly'!AR163 -> 479635.9 | I23: ='Cons TrioMobil | Monthly'!AS163 -> 376295.71 | J23: ='Cons TrioMobil | Monthly'!AT163 -> 616648.25 | ... AL23: ='Cons TrioMobil | Monthly'!BV163 -> 927264.76 | AN23: =INDEX($C23:$Z23,MATCH(AN$9,$C$9:$Z$9,0)) -> 799751.97 | AO23: =INDEX($C23:$Z23,MATCH(AO$9,$C$9:$Z$9,0)) -> 932936.46 | AP23: =INDEX($C23:$Z23,MATCH(AP$9,$C$9:$Z$9,0)) -> 542308.64 | AQ23: =INDEX($C23:$Z23,MATCH(AQ$9,$C$9:$Z$9,0)) -> 725691.3 | AR23: =INDEX($C23:$AM23,MATCH(AR$9,$C$9:$AM$9,0)) -> 777998.93 | AS23: =INDEX($C23:$AM23,MATCH(AS$9,$C$9:$AM$9,0)) -> 759395.07 | AT23: =INDEX($C23:$AM23,MATCH(AT$9,$C$9:$AM$9,0)) -> 810991.65 | AU23: =INDEX($C23:$AM23,MATCH(AU$9,$C$9:$AM$9,0)) -> 927264.76 | AW23: =INDEX($C23:$AM23,MATCH(AW$9,$C$9:$AM$9,0)) -> 927264.76 | AX23: =INDEX($C23:$AM23,MATCH(AX$9,$C$9:$AM$9,0)) -> 927264.76 | AY23: =INDEX($C23:$Z23,MATCH(AY$9,$C$9:$Z$9,0)) -> 725691.3
B24: Total Liabilies | C24: =SUM(C20:C23) -> 5018418.6 | D24: =SUM(D20:D23) -> 5535352.4 | E24: =SUM(E20:E23) -> 6170903.7 | F24: =SUM(F20:F23) -> 6443163.6 | G24: =SUM(G20:G23) -> 6581017.2 | H24: =SUM(H20:H23) -> 6457420.1 | I24: =SUM(I20:I23) -> 6650325.2 | J24: =SUM(J20:J23) -> 7883914.4 | ... AL24: =SUM(AL20:AL23) -> 20963859 | AN24: =SUM(AN20:AN23) -> 15750731 | AO24: =SUM(AO20:AO23) -> 17670368 | AP24: =SUM(AP20:AP23) -> 16573636 | AQ24: =SUM(AQ20:AQ23) -> 18065422 | AR24: =SUM(AR20:AR23) -> 19040466 | AS24: =SUM(AS20:AS23) -> 18901745 | AT24: =SUM(AT20:AT23) -> 18971818 | AU24: =SUM(AU20:AU23) -> 20963859 | AW24: =SUM(AW20:AW23) -> 20963859 | AX24: =SUM(AX20:AX23) -> 20963859 | AY24: =SUM(AY20:AY23) -> 18065422
B26: Equity
B27: Net Equity | C27: ='Cons TrioMobil | Monthly'!#REF! -> #REF! | D27: ='Cons TrioMobil | Monthly'!#REF! -> #REF! | E27: ='Cons TrioMobil | Monthly'!#REF! -> #REF! | F27: ='Cons TrioMobil | Monthly'!#REF! -> #REF! | G27: ='Cons TrioMobil | Monthly'!#REF! -> #REF! | H27: ='Cons TrioMobil | Monthly'!#REF! -> #REF! | I27: ='Cons TrioMobil | Monthly'!#REF! -> #REF! | J27: ='Cons TrioMobil | Monthly'!#REF! -> #REF! | ... AL27: ='Cons TrioMobil | Monthly'!#REF! -> #REF! | AN27: =INDEX($C27:$Z27,MATCH(AN$9,$C$9:$Z$9,0)) -> #REF! | AO27: =INDEX($C27:$Z27,MATCH(AO$9,$C$9:$Z$9,0)) -> #REF! | AP27: =INDEX($C27:$Z27,MATCH(AP$9,$C$9:$Z$9,0)) -> #REF! | AQ27: =INDEX($C27:$Z27,MATCH(AQ$9,$C$9:$Z$9,0)) -> #REF! | AR27: =INDEX($C27:$AM27,MATCH(AR$9,$C$9:$AM$9,0)) -> #REF! | AS27: =INDEX($C27:$AM27,MATCH(AS$9,$C$9:$AM$9,0)) -> #REF! | AT27: =INDEX($C27:$AM27,MATCH(AT$9,$C$9:$AM$9,0)) -> #REF! | AU27: =INDEX($C27:$AM27,MATCH(AU$9,$C$9:$AM$9,0)) -> #REF! | AW27: =INDEX($C27:$AM27,MATCH(AW$9,$C$9:$AM$9,0)) -> #REF! | AX27: =INDEX($C27:$AM27,MATCH(AX$9,$C$9:$AM$9,0)) -> #REF! | AY27: =INDEX($C27:$Z27,MATCH(AY$9,$C$9:$Z$9,0)) -> #REF!
B28: Total L+E | C28: =C24+C27 -> #REF! | D28: =D24+D27 -> #REF! | E28: =E24+E27 -> #REF! | F28: =F24+F27 -> #REF! | G28: =G24+G27 -> #REF! | H28: =H24+H27 -> #REF! | I28: =I24+I27 -> #REF! | J28: =J24+J27 -> #REF! | ... AL28: =AL24+AL27 -> #REF! | AN28: =AN24+AN27 -> #REF! | AO28: =AO24+AO27 -> #REF! | AP28: =AP24+AP27 -> #REF! | AQ28: =AQ24+AQ27 -> #REF! | AR28: =AR24+AR27 -> #REF! | AS28: =AS24+AS27 -> #REF! | AT28: =AT24+AT27 -> #REF! | AU28: =AU24+AU27 -> #REF! | AW28: =AW24+AW27 -> #REF! | AX28: =AX24+AX27 -> #REF! | AY28: =AY24+AY27 -> #REF!
B30: Balance | C30: =C28-C17 -> #REF! | D30: =D28-D17 -> #REF! | E30: =E28-E17 -> #REF! | F30: =F28-F17 -> #REF! | G30: =G28-G17 -> #REF! | H30: =H28-H17 -> #REF! | I30: =I28-I17 -> #REF! | J30: =J28-J17 -> #REF! | ... AL30: =AL28-AL17 -> #REF! | AN30: =AN28-AN17 -> #REF! | AO30: =AO28-AO17 -> #REF! | AP30: =AP28-AP17 -> #REF! | AQ30: =AQ28-AQ17 -> #REF! | AR30: =AR28-AR17 -> #REF! | AS30: =AS28-AS17 -> #REF! | AT30: =AT28-AT17 -> #REF! | AU30: =AU28-AU17 -> #REF! | AW30: =AW28-AW17 -> #REF! | AX30: =AX28-AX17 -> #REF! | AY30: =AY28-AY17 -> #REF!
B32: Check
B34: Monthly CFS - Actuals through August 2024 | AN34: Quarterly CFS | AW34: YTD, TTM, Annual CFS
C36: Actuals | D36: Actuals | E36: Actuals | F36: Actuals | G36: Actuals | H36: Actuals | I36: Actuals | J36: Actuals | K36: Actuals | L36: Actuals | M36: Actuals | N36: Actuals | O36: Actuals | P36: Actuals | Q36: Actuals | R36: Actuals | S36: Actuals | T36: Actuals | U36: Actuals | V36: Actuals | W36: Actuals | X36: Actuals | Y36: Actuals | Z36: Actuals | AA36: Actuals | AB36: Actuals | AC36: Actuals | AD36: Actuals | AE36: Actuals | AF36: Actuals | AG36: Actuals | AH36: Actuals | AI36: Actuals | AJ36: Actuals | AK36: Actuals | AL36: Actuals | AN36: Actuals | AO36: Actuals | AP36: Actuals | AQ36: Actuals | AR36: Actuals | AS36: Actuals | AT36: Actuals | AU36: Actuals | AW36: Actuals | AX36: Actuals | AY36: Forecast
B37: CFS | C37: Q1 | D37: Q1 | E37: Q1 | F37: Q2 | G37: Q2 | H37: Q2 | I37: Q3 | J37: Q3 | K37: Q3 | L37: Q4 | M37: Q4 | N37: Q4 | O37: Q1 | P37: Q1 | Q37: Q1 | R37: Q2 | S37: Q2 | T37: Q2 | U37: Q3 | V37: Q3 | W37: Q3 | X37: =+X8 -> Q4 | Y37: =+Y8 -> Q4 | Z37: =+Z8 -> Q4 | AA37: =+AA8 -> Q1 | AB37: =+AB8 -> Q1 | AC37: =+AC8 -> Q1 | AD37: =+AD8 -> Q2 | AE37: =+AE8 -> Q2 | ... AL37: =+AL8 -> Q4 | AN37: =+AN8 -> Q1 | AO37: =+AO8 -> Q2 | AP37: =+AP8 -> Q3 | AQ37: =+AQ8 -> Q4 | AR37: =+AR8 -> Q1 | AS37: =+AS8 -> Q2 | AT37: =+AT8 -> Q3 | AU37: =+AU8 -> Q4 | AW37: YTD | AX37: TTM | AY37: Annual
B38: ($ in USD) | C38: 44957 | D38: =EOMONTH(C38,1) -> 44985 | E38: =EOMONTH(D38,1) -> 45016 | F38: =EOMONTH(E38,1) -> 45046 | G38: =EOMONTH(F38,1) -> 45077 | H38: =EOMONTH(G38,1) -> 45107 | I38: =EOMONTH(H38,1) -> 45138 | J38: =EOMONTH(I38,1) -> 45169 | K38: =EOMONTH(J38,1) -> 45199 | ... N38: =EOMONTH(M38,1) -> 45291 | O38: 45322 | P38: =EOMONTH(O38,1) -> 45351 | Q38: =EOMONTH(P38,1) -> 45382 | R38: =EOMONTH(Q38,1) -> 45412 | S38: =EOMONTH(R38,1) -> 45443 | T38: =EOMONTH(S38,1) -> 45473 | U38: =EOMONTH(T38,1) -> 45504 | V38: =EOMONTH(U38,1) -> 45535 | W38: =EOMONTH(V38,1) -> 45565 | ... AL38: =EOMONTH(AK38,1) -> 46022 | AN38: 45382 | AO38: =EOMONTH(AN38,3) -> 45473 | AP38: =EOMONTH(AO38,3) -> 45565 | AQ38: =EOMONTH(AP38,3) -> 45657 | AR38: =EOMONTH(AQ38,3) -> 45747 | AS38: =EOMONTH(AR38,3) -> 45838 | AT38: =EOMONTH(AS38,3) -> 45930 | AU38: =EOMONTH(AT38,3) -> 46022 | AW38: =+AW9 -> 46022 | AX38: =+AX9 -> 46022 | AY38: 45657
B40: NET INCOME | C40: ='Cons TrioMobil | Monthly'!AM188 -> -227489.82 | D40: ='Cons TrioMobil | Monthly'!AN188 -> -234763.14 | E40: ='Cons TrioMobil | Monthly'!AO188 -> -283974.31 | F40: ='Cons TrioMobil | Monthly'!AP188 -> -352615.26 | G40: ='Cons TrioMobil | Monthly'!AQ188 -> -171031.8 | H40: ='Cons TrioMobil | Monthly'!AR188 -> -156824.96 | I40: ='Cons TrioMobil | Monthly'!AS188 -> -254390.3 | J40: ='Cons TrioMobil | Monthly'!AT188 -> -190381.66 | ... AL40: ='Cons TrioMobil | Monthly'!BV188 -> -650011.79 | AN40: =SUMIFS($O40:$Z40,$O$37:$Z$37,AN$37) -> -1224329.1 | AO40: =SUMIFS($O40:$Z40,$O$37:$Z$37,AO$37) -> -1138025.5 | AP40: =SUMIFS($O40:$Z40,$O$37:$Z$37,AP$37) -> -1115079.8 | AQ40: =SUMIFS($O40:$Z40,$O$37:$Z$37,AQ$37) -> -1383714.8 | AR40: =SUMIFS($AA40:$AM40,$AA$37:$AM$37,AR$37) -> -1380952.6 | AS40: =SUMIFS($AA40:$AM40,$AA$37:$AM$37,AS$37) -> -1223988.9 | AT40: =SUMIFS($AA40:$AM40,$AA$37:$AM$37,AT$37) -> -1274858.5 | AU40: =SUMIFS($AA40:$AM40,$AA$37:$AM$37,AU$37) -> -1315175.9 | AW40: =+SUM(OFFSET(INDEX($B40:$AM40,MATCH(AW$38,$B$38:$AM$38,0)),,,,-MONTH(AW$38))) -> -5194975.9 | AX40: =+SUM(OFFSET(INDEX($B40:$AM40,MATCH(AX$38,$B$38:$AM$38,0)),,,,-12)) -> -5194975.9 | AY40: =SUM(O40:Z40) -> -4861149.2
B41: (+ / -) ▲ NwC | C41: =SUM('Cons TrioMobil | Monthly'!AM189:AM201) -> -156298.03 | D41: =SUM('Cons TrioMobil | Monthly'!AN189:AN201) -> -21975.432 | E41: =SUM('Cons TrioMobil | Monthly'!AO189:AO201) -> 413267.34 | F41: =SUM('Cons TrioMobil | Monthly'!AP189:AP201) -> 152922.11 | G41: =SUM('Cons TrioMobil | Monthly'!AQ189:AQ201) -> -17014.598 | H41: =SUM('Cons TrioMobil | Monthly'!AR189:AR201) -> -160827.91 | I41: =SUM('Cons TrioMobil | Monthly'!AS189:AS201) -> 104256.72 | J41: =SUM('Cons TrioMobil | Monthly'!AT189:AT201) -> 316274.46 | ... AL41: =SUM('Cons TrioMobil | Monthly'!BV189:BV201) -> 993482.83 | AN41: =SUMIFS($O41:$Z41,$O$37:$Z$37,AN$37) -> 1063906.7 | AO41: =SUMIFS($O41:$Z41,$O$37:$Z$37,AO$37) -> 394794.49 | AP41: =SUMIFS($O41:$Z41,$O$37:$Z$37,AP$37) -> 26920.953 | AQ41: =SUMIFS($O41:$Z41,$O$37:$Z$37,AQ$37) -> -39647.426 | AR41: =SUMIFS($AA41:$AM41,$AA$37:$AM$37,AR$37) -> 1201552.2 | AS41: =SUMIFS($AA41:$AM41,$AA$37:$AM$37,AS$37) -> -91470.343 | AT41: =SUMIFS($AA41:$AM41,$AA$37:$AM$37,AT$37) -> 279815.7 | AU41: =SUMIFS($AA41:$AM41,$AA$37:$AM$37,AU$37) -> 652601.13 | AW41: =+SUM(OFFSET(INDEX($B41:$AM41,MATCH(AW$38,$B$38:$AM$38,0)),,,,-MONTH(AW$38))) -> 2042498.6 | AX41: =+SUM(OFFSET(INDEX($B41:$AM41,MATCH(AX$38,$B$38:$AM$38,0)),,,,-12)) -> 2042498.6 | AY41: =SUM(O41:Z41) -> 1445974.7
B42: CFO | C42: =SUM(C40:C41) -> -383787.84 | D42: =SUM(D40:D41) -> -256738.57 | E42: =SUM(E40:E41) -> 129293.03 | F42: =SUM(F40:F41) -> -199693.16 | G42: =SUM(G40:G41) -> -188046.4 | H42: =SUM(H40:H41) -> -317652.87 | I42: =SUM(I40:I41) -> -150133.57 | J42: =SUM(J40:J41) -> 125892.8 | ... AL42: =SUM(AL40:AL41) -> 343471.04 | AN42: =SUM(AN40:AN41) -> -160422.36 | AO42: =SUM(AO40:AO41) -> -743230.98 | AP42: =SUM(AP40:AP41) -> -1088158.9 | AQ42: =SUM(AQ40:AQ41) -> -1423362.3 | AR42: =SUM(AR40:AR41) -> -179400.46 | AS42: =SUM(AS40:AS41) -> -1315459.3 | AT42: =SUM(AT40:AT41) -> -995042.76 | AU42: =SUM(AU40:AU41) -> -662574.79 | AW42: =SUM(AW40:AW41) -> -3152477.3 | AX42: =SUM(AX40:AX41) -> -3152477.3 | AY42: =SUM(AY40:AY41) -> -3415174.5
B44: (-) CapEx | C44: ='Cons TrioMobil | Monthly'!AM206 -> -21140.756 | D44: ='Cons TrioMobil | Monthly'!AN206 -> -6099.8632 | E44: ='Cons TrioMobil | Monthly'!AO206 -> -7708.3241 | F44: ='Cons TrioMobil | Monthly'!AP206 -> -9909.8761 | G44: ='Cons TrioMobil | Monthly'!AQ206 -> -13082.352 | H44: ='Cons TrioMobil | Monthly'!AR206 -> 16346.41 | I44: ='Cons TrioMobil | Monthly'!AS206 -> -10655.408 | J44: ='Cons TrioMobil | Monthly'!AT206 -> -2136.569 | ... AL44: ='Cons TrioMobil | Monthly'!BV206 -> -196564.53 | AN44: =SUMIFS($O44:$Z44,$O$37:$Z$37,AN$37) -> 167462.68 | AO44: =SUMIFS($O44:$Z44,$O$37:$Z$37,AO$37) -> -1098266.8 | AP44: =SUMIFS($O44:$Z44,$O$37:$Z$37,AP$37) -> 294265.74 | AQ44: =SUMIFS($O44:$Z44,$O$37:$Z$37,AQ$37) -> -301592.64 | AR44: =SUMIFS($AA44:$AM44,$AA$37:$AM$37,AR$37) -> -584618.52 | AS44: =SUMIFS($AA44:$AM44,$AA$37:$AM$37,AS$37) -> -176621.69 | AT44: =SUMIFS($AA44:$AM44,$AA$37:$AM$37,AT$37) -> -223825.95 | AU44: =SUMIFS($AA44:$AM44,$AA$37:$AM$37,AU$37) -> -555698.68 | AW44: =+SUM(OFFSET(INDEX($B44:$AM44,MATCH(AW$38,$B$38:$AM$38,0)),,,,-MONTH(AW$38))) -> -1540764.8 | AX44: =+SUM(OFFSET(INDEX($B44:$AM44,MATCH(AX$38,$B$38:$AM$38,0)),,,,-12)) -> -1540764.8 | AY44: =SUM(O44:Z44) -> -938131.07
B45: CFI | C45: =SUM(C44) -> -21140.756 | D45: =SUM(D44) -> -6099.8632 | E45: =SUM(E44) -> -7708.3241 | F45: =SUM(F44) -> -9909.8761 | G45: =SUM(G44) -> -13082.352 | H45: =SUM(H44) -> 16346.41 | I45: =SUM(I44) -> -10655.408 | J45: =SUM(J44) -> -2136.569 | ... AL45: =SUM(AL44) -> -196564.53 | AN45: =SUM(AN44) -> 167462.68 | AO45: =SUM(AO44) -> -1098266.8 | AP45: =SUM(AP44) -> 294265.74 | AQ45: =SUM(AQ44) -> -301592.64 | AR45: =SUM(AR44) -> -584618.52 | AS45: =SUM(AS44) -> -176621.69 | AT45: =SUM(AT44) -> -223825.95 | AU45: =SUM(AU44) -> -555698.68 | AW45: =SUM(AW44) -> -1540764.8 | AX45: =SUM(AX44) -> -1540764.8 | AY45: =SUM(AY44) -> -938131.07
B47: (+ / -) Equity | C47: ='Cons TrioMobil | Monthly'!AM214-'Cons TrioMobil | Monthly'!AM206 -> 9294.4565 | D47: ='Cons TrioMobil | Monthly'!AN214-'Cons TrioMobil | Monthly'!AN206 -> -3510.1194 | E47: ='Cons TrioMobil | Monthly'!AO214-'Cons TrioMobil | Monthly'!AO206 -> -12343.249 | F47: ='Cons TrioMobil | Monthly'!AP214-'Cons TrioMobil | Monthly'!AP206 -> -6139.3681 | G47: ='Cons TrioMobil | Monthly'!AQ214-'Cons TrioMobil | Monthly'!AQ206 -> -46866.017 | H47: ='Cons TrioMobil | Monthly'!AR214-'Cons TrioMobil | Monthly'!AR206 -> -94218.713 | I47: ='Cons TrioMobil | Monthly'!AS214-'Cons TrioMobil | Monthly'!AS206 -> 22363.36 | J47: ='Cons TrioMobil | Monthly'!AT214-'Cons TrioMobil | Monthly'!AT206 -> -21932.206 | ... AL47: ='Cons TrioMobil | Monthly'!BV214-'Cons TrioMobil | Monthly'!BV206 -> -685224.14 | AN47: =SUMIFS($O47:$Z47,$O$37:$Z$37,AN$37) -> 1032858.3 | AO47: =SUMIFS($O47:$Z47,$O$37:$Z$37,AO$37) -> 1036497.1 | AP47: =SUMIFS($O47:$Z47,$O$37:$Z$37,AP$37) -> -11772266 | AQ47: =SUMIFS($O47:$Z47,$O$37:$Z$37,AQ$37) -> 14797.897 | AR47: =SUMIFS($AA47:$AM47,$AA$37:$AM$37,AR$37) -> -295326.9 | AS47: =SUMIFS($AA47:$AM47,$AA$37:$AM$37,AS$37) -> -216321.36 | AT47: =SUMIFS($AA47:$AM47,$AA$37:$AM$37,AT$37) -> -849125.79 | AU47: =SUMIFS($AA47:$AM47,$AA$37:$AM$37,AU$37) -> -441021.06 | AW47: =+SUM(OFFSET(INDEX($B47:$AM47,MATCH(AW$38,$B$38:$AM$38,0)),,,,-MONTH(AW$38))) -> -1801795.1 | AX47: =+SUM(OFFSET(INDEX($B47:$AM47,MATCH(AX$38,$B$38:$AM$38,0)),,,,-12)) -> -1801795.1 | AY47: =SUM(O47:Z47) -> -9688112.7
B48: (+ / -) Debt | C48: =SUM('Cons TrioMobil | Monthly'!AM218:AM220) -> 180375.02 | D48: =SUM('Cons TrioMobil | Monthly'!AN218:AN220) -> 226836.06 | E48: =SUM('Cons TrioMobil | Monthly'!AO218:AO220) -> 247135.35 | F48: =SUM('Cons TrioMobil | Monthly'!AP218:AP220) -> -25267.182 | G48: =SUM('Cons TrioMobil | Monthly'!AQ218:AQ220) -> 45701.967 | H48: =SUM('Cons TrioMobil | Monthly'!AR218:AR220) -> 288583.28 | I48: =SUM('Cons TrioMobil | Monthly'!AS218:AS220) -> 38969.668 | J48: =SUM('Cons TrioMobil | Monthly'!AT218:AT220) -> 143601.16 | ... AL48: =SUM('Cons TrioMobil | Monthly'!BV218:BV220) -> -108976.33 | AN48: =SUMIFS($O48:$Z48,$O$37:$Z$37,AN$37) -> -1997863.5 | AO48: =SUMIFS($O48:$Z48,$O$37:$Z$37,AO$37) -> 756629.11 | AP48: =SUMIFS($O48:$Z48,$O$37:$Z$37,AP$37) -> 25571884 | AQ48: =SUMIFS($O48:$Z48,$O$37:$Z$37,AQ$37) -> 176984.34 | AR48: =SUMIFS($AA48:$AM48,$AA$37:$AM$37,AR$37) -> -67917.558 | AS48: =SUMIFS($AA48:$AM48,$AA$37:$AM$37,AS$37) -> -383088.98 | AT48: =SUMIFS($AA48:$AM48,$AA$37:$AM$37,AT$37) -> 407725.26 | AU48: =SUMIFS($AA48:$AM48,$AA$37:$AM$37,AU$37) -> 819096.93 | AW48: =+SUM(OFFSET(INDEX($B48:$AM48,MATCH(AW$38,$B$38:$AM$38,0)),,,,-MONTH(AW$38))) -> 775815.65 | AX48: =+SUM(OFFSET(INDEX($B48:$AM48,MATCH(AX$38,$B$38:$AM$38,0)),,,,-12)) -> 775815.65 | AY48: =SUM(O48:Z48) -> 24507634
B49: CFF | C49: =SUM(C47:C48) -> 189669.48 | D49: =SUM(D47:D48) -> 223325.94 | E49: =SUM(E47:E48) -> 234792.1 | F49: =SUM(F47:F48) -> -31406.551 | G49: =SUM(G47:G48) -> -1164.0506 | H49: =SUM(H47:H48) -> 194364.57 | I49: =SUM(I47:I48) -> 61333.028 | J49: =SUM(J47:J48) -> 121668.95 | ... AL49: =SUM(AL47:AL48) -> -794200.47 | AN49: =SUM(AN47:AN48) -> -965005.22 | AO49: =SUM(AO47:AO48) -> 1793126.2 | AP49: =SUM(AP47:AP48) -> 13799618 | AQ49: =SUM(AQ47:AQ48) -> 191782.24 | AR49: =SUM(AR47:AR48) -> -363244.46 | AS49: =SUM(AS47:AS48) -> -599410.34 | AT49: =SUM(AT47:AT48) -> -441400.54 | AU49: =SUM(AU47:AU48) -> 378075.88 | AW49: =SUM(AW47:AW48) -> -1025979.5 | AX49: =SUM(AX47:AX48) -> -1025979.5 | AY49: =SUM(AY47:AY48) -> 14819521
B51: Beginning Cash | D51: =C53 -> 2387044.7 | E51: =D53 -> 2347532.2 | F51: =E53 -> 2703909.1 | G51: =F53 -> 2462899.5 | H51: =G53 -> 2260606.7 | I51: =H53 -> 2153664.8 | J51: =I53 -> 2054208.8 | K51: =J53 -> 2299634 | ... AL51: =AK53 -> 8722946.8 | AN51: =N53 -> 3328659 | AO51: =AN53 -> 2370694.1 | AP51: =AO53 -> 2322322.5 | AQ51: =AP53 -> 15328047 | AR51: =AQ53 -> 13794874 | AS51: =AR53 -> 12667611 | AT51: =AS53 -> 10576120 | AU51: =AT53 -> 8915850.4 | AW51: =Z53 -> 13794874 | AX51: =Z53 -> 13794874 | AY51: =N53 -> 3328659
B52: ▲ in Cash | D52: =+D42+D45+D49 -> -39512.493 | E52: =+E42+E45+E49 -> 356376.81 | F52: =+F42+F45+F49 -> -241009.58 | G52: =+G42+G45+G49 -> -202292.8 | H52: =+H42+H45+H49 -> -106941.89 | I52: =+I42+I45+I49 -> -99455.956 | J52: =+J42+J45+J49 -> 245425.19 | K52: =+K42+K45+K49 -> 72819.763 | ... AL52: =+AL42+AL45+AL49 -> -647293.96 | AN52: =+AN42+AN45+AN49 -> -957964.9 | AO52: =+AO42+AO45+AO49 -> -48371.648 | AP52: =+AP42+AP45+AP49 -> 13005725 | AQ52: =+AQ42+AQ45+AQ49 -> -1533172.7 | AR52: =SUMIFS($AA52:$AM52,$AA$37:$AM$37,AR$37) -> -1127263.4 | AS52: =SUMIFS($AA52:$AM52,$AA$37:$AM$37,AS$37) -> -2091491.3 | AT52: =SUMIFS($AA52:$AM52,$AA$37:$AM$37,AT$37) -> -1660269.3 | AU52: =SUMIFS($AA52:$AM52,$AA$37:$AM$37,AU$37) -> -840197.58 | AW52: =+AW42+AW45+AW49 -> -5719221.6 | AX52: =+SUM(OFFSET(INDEX($B52:$AM52,MATCH(AX$38,$B$38:$AM$38,0)),,,,-12)) -> -5719221.6 | AY52: =SUM(O52:Z52) -> 10466215
B53: Ending Cash | C53: =C12 -> 2387044.7 | D53: =SUM(D51:D52) -> 2347532.2 | E53: =SUM(E51:E52) -> 2703909.1 | F53: =SUM(F51:F52) -> 2462899.5 | G53: =SUM(G51:G52) -> 2260606.7 | H53: =SUM(H51:H52) -> 2153664.8 | I53: =SUM(I51:I52) -> 2054208.8 | J53: =SUM(J51:J52) -> 2299634 | K53: =SUM(K51:K52) -> 2372453.8 | ... AL53: =SUM(AL51:AL52) -> 8075652.8 | AN53: =SUM(AN51:AN52) -> 2370694.1 | AO53: =SUM(AO51:AO52) -> 2322322.5 | AP53: =SUM(AP51:AP52) -> 15328047 | AQ53: =SUM(AQ51:AQ52) -> 13794874 | AR53: =SUM(AR51:AR52) -> 12667611 | AS53: =SUM(AS51:AS52) -> 10576120 | AT53: =SUM(AT51:AT52) -> 8915850.4 | AU53: =SUM(AU51:AU52) -> 8075652.8 | AW53: =SUM(AW51:AW52) -> 8075652.8 | AX53: =SUM(AX51:AX52) -> 8075652.8 | AY53: =SUM(AY51:AY52) -> 13794874
B55: BS Check
B56: Assets | C56: =C17-'Cons TrioMobil | Monthly'!AM151 -> 0 | D56: =D17-'Cons TrioMobil | Monthly'!AN151 -> 0 | E56: =E17-'Cons TrioMobil | Monthly'!AO151 -> 0 | F56: =F17-'Cons TrioMobil | Monthly'!AP151 -> 0 | G56: =G17-'Cons TrioMobil | Monthly'!AQ151 -> 0 | H56: =H17-'Cons TrioMobil | Monthly'!AR151 -> 0 | I56: =I17-'Cons TrioMobil | Monthly'!AS151 -> 0 | J56: =J17-'Cons TrioMobil | Monthly'!AT151 -> 0 | ... AL56: =AL17-'Cons TrioMobil | Monthly'!BV151 -> 0 | AN56: =INDEX($C17:$Z17,MATCH(AN$9,$C$9:$Z$9,0))-AN17 -> 0 | AO56: =INDEX($C17:$Z17,MATCH(AO$9,$C$9:$Z$9,0))-AO17 -> 0 | AP56: =INDEX($C17:$Z17,MATCH(AP$9,$C$9:$Z$9,0))-AP17 -> 0 | AQ56: =INDEX($C17:$Z17,MATCH(AQ$9,$C$9:$Z$9,0))-AQ17 -> 0 | AR56: =INDEX($C17:$AM17,MATCH(AR$9,$C$9:$AM$9,0))-AR17 -> 0 | AS56: =INDEX($C17:$AM17,MATCH(AS$9,$C$9:$AM$9,0))-AS17 -> 0 | AT56: =INDEX($C17:$AM17,MATCH(AT$9,$C$9:$AM$9,0))-AT17 -> 0 | AU56: =INDEX($C17:$AM17,MATCH(AU$9,$C$9:$AM$9,0))-AU17 -> 0 | AW56: =INDEX($C17:$AM17,MATCH(AW$9,$C$9:$AM$9,0))-AW17 -> 0 | AX56: =INDEX($C17:$AM17,MATCH(AX$9,$C$9:$AM$9,0))-AX17 -> 0 | AY56: =INDEX($C17:$Z17,MATCH(AY$9,$C$9:$Z$9,0))-AY17 -> 0
B57: Liabilities | C57: =C24-'Cons TrioMobil | Monthly'!AM167 -> 0 | D57: =D24-'Cons TrioMobil | Monthly'!AN167 -> 0 | E57: =E24-'Cons TrioMobil | Monthly'!AO167 -> 0 | F57: =F24-'Cons TrioMobil | Monthly'!AP167 -> 0 | G57: =G24-'Cons TrioMobil | Monthly'!AQ167 -> 0 | H57: =H24-'Cons TrioMobil | Monthly'!AR167 -> 0 | I57: =I24-'Cons TrioMobil | Monthly'!AS167 -> 0 | J57: =J24-'Cons TrioMobil | Monthly'!AT167 -> 0 | ... AL57: =AL24-'Cons TrioMobil | Monthly'!BV167 -> 0 | AN57: =INDEX($C24:$Z24,MATCH(AN$9,$C$9:$Z$9,0))-AN24 -> 0 | AO57: =INDEX($C24:$Z24,MATCH(AO$9,$C$9:$Z$9,0))-AO24 -> 0 | AP57: =INDEX($C24:$Z24,MATCH(AP$9,$C$9:$Z$9,0))-AP24 -> 0 | AQ57: =INDEX($C24:$Z24,MATCH(AQ$9,$C$9:$Z$9,0))-AQ24 -> 0 | AR57: =INDEX($C18:$AM18,MATCH(AR$9,$C$9:$AM$9,0))-AR18 -> 0 | AS57: =INDEX($C18:$AM18,MATCH(AS$9,$C$9:$AM$9,0))-AS18 -> 0 | AT57: =INDEX($C18:$AM18,MATCH(AT$9,$C$9:$AM$9,0))-AT18 -> 0 | AU57: =INDEX($C18:$AM18,MATCH(AU$9,$C$9:$AM$9,0))-AU18 -> 0 | AW57: =INDEX($C24:$AM24,MATCH(AW$9,$C$9:$AM$9,0))-AW24 -> 0 | AX57: =INDEX($C24:$AM24,MATCH(AX$9,$C$9:$AM$9,0))-AX24 -> 0 | AY57: =INDEX($C24:$Z24,MATCH(AY$9,$C$9:$Z$9,0))-AY24 -> 0
B58: Equity | C58: =C27-'Cons TrioMobil | Monthly'!#REF! -> #REF! | D58: =D27-'Cons TrioMobil | Monthly'!#REF! -> #REF! | E58: =E27-'Cons TrioMobil | Monthly'!#REF! -> #REF! | F58: =F27-'Cons TrioMobil | Monthly'!#REF! -> #REF! | G58: =G27-'Cons TrioMobil | Monthly'!#REF! -> #REF! | H58: =H27-'Cons TrioMobil | Monthly'!#REF! -> #REF! | I58: =I27-'Cons TrioMobil | Monthly'!#REF! -> #REF! | J58: =J27-'Cons TrioMobil | Monthly'!#REF! -> #REF! | ... AL58: =AL27-'Cons TrioMobil | Monthly'!#REF! -> #REF! | AN58: =INDEX($C27:$Z27,MATCH(AN$9,$C$9:$Z$9,0))-AN27 -> #REF! | AO58: =INDEX($C27:$Z27,MATCH(AO$9,$C$9:$Z$9,0))-AO27 -> #REF! | AP58: =INDEX($C27:$Z27,MATCH(AP$9,$C$9:$Z$9,0))-AP27 -> #REF! | AQ58: =INDEX($C27:$Z27,MATCH(AQ$9,$C$9:$Z$9,0))-AQ27 -> #REF! | AR58: =INDEX($C19:$AM19,MATCH(AR$9,$C$9:$AM$9,0))-AR19 -> 0 | AS58: =INDEX($C19:$AM19,MATCH(AS$9,$C$9:$AM$9,0))-AS19 -> 0 | AT58: =INDEX($C19:$AM19,MATCH(AT$9,$C$9:$AM$9,0))-AT19 -> 0 | AU58: =INDEX($C19:$AM19,MATCH(AU$9,$C$9:$AM$9,0))-AU19 -> 0 | AW58: =INDEX($C27:$AM27,MATCH(AW$9,$C$9:$AM$9,0))-AW27 -> #REF! | AX58: =INDEX($C27:$AM27,MATCH(AX$9,$C$9:$AM$9,0))-AX27 -> #REF! | AY58: =INDEX($C27:$Z27,MATCH(AY$9,$C$9:$Z$9,0))-AY27 -> #REF!
B60: CFS Check
B61: CFO | C61: =C42-'Cons TrioMobil | Monthly'!AM202 -> 0 | D61: =D42-'Cons TrioMobil | Monthly'!AN202 -> 0 | E61: =E42-'Cons TrioMobil | Monthly'!AO202 -> 0 | F61: =F42-'Cons TrioMobil | Monthly'!AP202 -> 0 | G61: =G42-'Cons TrioMobil | Monthly'!AQ202 -> 0 | H61: =H42-'Cons TrioMobil | Monthly'!AR202 -> 0 | I61: =I42-'Cons TrioMobil | Monthly'!AS202 -> 0 | J61: =J42-'Cons TrioMobil | Monthly'!AT202 -> 0 | ... AL61: =AL42-'Cons TrioMobil | Monthly'!BV202 -> 0 | AN61: =SUMIFS($O42:$Z42,$O$37:$Z$37,AN$37)-AN42 -> 0 | AO61: =SUMIFS($O42:$Z42,$O$37:$Z$37,AO$37)-AO42 -> 0 | AP61: =SUMIFS($O42:$Z42,$O$37:$Z$37,AP$37)-AP42 -> 0 | AQ61: =SUMIFS($O42:$Z42,$O$37:$Z$37,AQ$37)-AQ42 -> 0 | AR61: =SUMIFS($AA42:$AM42,$AA$37:$AM$37,AR$37)-AR42 -> 2.910383e-10 | AS61: =SUMIFS($AA42:$AM42,$AA$37:$AM$37,AS$37)-AS42 -> 0 | AT61: =SUMIFS($AA42:$AM42,$AA$37:$AM$37,AT$37)-AT42 -> 0 | AU61: =SUMIFS($AA42:$AM42,$AA$37:$AM$37,AU$37)-AU42 -> 0 | AW61: =SUM(AA42:AL42)-AW42 -> 0 | AX61: =SUM(AA42:AL42)-AX42 -> 0
B62: CFI | C62: ='Cons TrioMobil | Monthly'!AM206-C45 -> 0 | D62: ='Cons TrioMobil | Monthly'!AN206-D45 -> 0 | E62: ='Cons TrioMobil | Monthly'!AO206-E45 -> 0 | F62: ='Cons TrioMobil | Monthly'!AP206-F45 -> 0 | G62: ='Cons TrioMobil | Monthly'!AQ206-G45 -> 0 | H62: ='Cons TrioMobil | Monthly'!AR206-H45 -> 0 | I62: ='Cons TrioMobil | Monthly'!AS206-I45 -> 0 | J62: ='Cons TrioMobil | Monthly'!AT206-J45 -> 0 | ... AL62: ='Cons TrioMobil | Monthly'!BV206-AL45 -> 0 | AN62: =SUMIFS($O45:$Z45,$O$37:$Z$37,AN$37)-AN45 -> 0 | AO62: =SUMIFS($O45:$Z45,$O$37:$Z$37,AO$37)-AO45 -> 0 | AP62: =SUMIFS($O45:$Z45,$O$37:$Z$37,AP$37)-AP45 -> 0 | AQ62: =SUMIFS($O45:$Z45,$O$37:$Z$37,AQ$37)-AQ45 -> 0 | AR62: =SUMIFS($AA43:$AM43,$AA$37:$AM$37,AR$37)-AR43 -> 0 | AS62: =SUMIFS($AA43:$AM43,$AA$37:$AM$37,AS$37)-AS43 -> 0 | AT62: =SUMIFS($AA43:$AM43,$AA$37:$AM$37,AT$37)-AT43 -> 0 | AU62: =SUMIFS($AA43:$AM43,$AA$37:$AM$37,AU$37)-AU43 -> 0 | AW62: =SUM(AA45:AL45)-AW45 -> 0 | AX62: =SUM(AA45:AL45)-AX45 -> 0
B63: CFF | C63: =+SUM('Cons TrioMobil | Monthly'!AM207:AM213,'Cons TrioMobil | Monthly'!AM221)-C49 -> 0 | D63: =+SUM('Cons TrioMobil | Monthly'!AN207:AN213,'Cons TrioMobil | Monthly'!AN221)-D49 -> 0 | E63: =+SUM('Cons TrioMobil | Monthly'!AO207:AO213,'Cons TrioMobil | Monthly'!AO221)-E49 -> 0 | F63: =+SUM('Cons TrioMobil | Monthly'!AP207:AP213,'Cons TrioMobil | Monthly'!AP221)-F49 -> 0 | G63: =+SUM('Cons TrioMobil | Monthly'!AQ207:AQ213,'Cons TrioMobil | Monthly'!AQ221)-G49 -> 0 | H63: =+SUM('Cons TrioMobil | Monthly'!AR207:AR213,'Cons TrioMobil | Monthly'!AR221)-H49 -> 0 | I63: =+SUM('Cons TrioMobil | Monthly'!AS207:AS213,'Cons TrioMobil | Monthly'!AS221)-I49 -> 0 | J63: =+SUM('Cons TrioMobil | Monthly'!AT207:AT213,'Cons TrioMobil | Monthly'!AT221)-J49 -> 0 | ... AL63: =+SUM('Cons TrioMobil | Monthly'!BV207:BV213,'Cons TrioMobil | Monthly'!BV221)-AL49 -> 0 | AN63: =SUMIFS($O49:$Z49,$O$37:$Z$37,AN$37)-AN49 -> 0 | AO63: =SUMIFS($O49:$Z49,$O$37:$Z$37,AO$37)-AO49 -> 0 | AP63: =SUMIFS($O49:$Z49,$O$37:$Z$37,AP$37)-AP49 -> 0 | AQ63: =SUMIFS($O49:$Z49,$O$37:$Z$37,AQ$37)-AQ49 -> 0 | AR63: =SUMIFS($AA44:$AM44,$AA$37:$AM$37,AR$37)-AR44 -> 0 | AS63: =SUMIFS($AA44:$AM44,$AA$37:$AM$37,AS$37)-AS44 -> 0 | AT63: =SUMIFS($AA44:$AM44,$AA$37:$AM$37,AT$37)-AT44 -> 0 | AU63: =SUMIFS($AA44:$AM44,$AA$37:$AM$37,AU$37)-AU44 -> 0 | AW63: =SUM(AA49:AL49)-AW49 -> 0 | AX63: =SUM(AA49:AL49)-AX49 -> 0
B64: Cash | C64: =C53-C12 -> 0 | D64: =D53-D12 -> 0 | E64: =E53-E12 -> 0 | F64: =F53-F12 -> 0 | G64: =G53-G12 -> 0 | H64: =H53-H12 -> 0 | I64: =I53-I12 -> 0 | J64: =J53-J12 -> 0 | ... AL64: =AL53-AL12 -> -0.54000001 | AN64: =AN53-AN12 -> 0 | AO64: =AO53-AO12 -> 0 | AP64: =AP53-AP12 -> 0 | AQ64: =AQ53-AQ12 -> -0.39000001 | AR64: =SUMIFS($AA45:$AM45,$AA$37:$AM$37,AR$37)-AR45 -> 0 | AS64: =SUMIFS($AA45:$AM45,$AA$37:$AM$37,AS$37)-AS45 -> 0 | AT64: =SUMIFS($AA45:$AM45,$AA$37:$AM$37,AT$37)-AT45 -> 0 | AU64: =SUMIFS($AA45:$AM45,$AA$37:$AM$37,AU$37)-AU45 -> 0 | AW64: =AW53-AW12 -> -0.54000001 | AX64: =AX53-AX12 -> -0.54000001

Sheet P&L
B2: Trio Mobil
B3: Monthly P&L
AN5: Quarterly P&L | BA5: YTD, TTM, Annual P&L
C7: Actuals | AN7: Actuals | BA7: Actuals | BC7: Forecast
C8: Q1 | D8: Q1 | E8: Q1 | F8: Q2 | G8: Q2 | H8: Q2 | I8: Q3 | J8: Q3 | K8: Q3 | L8: Q4 | M8: Q4 | N8: Q4 | O8: Q1 | P8: Q1 | Q8: Q1 | R8: Q2 | S8: Q2 | T8: Q2 | U8: Q3 | V8: Q3 | W8: Q3 | X8: Q4 | Y8: Q4 | Z8: Q4 | AA8: Q1 | AB8: Q1 | AC8: Q1 | AD8: Q2 | AE8: Q2 | AF8: Q2 | AG8: Q3 | AH8: Q3 | AI8: Q3 | AJ8: Q4 | AK8: Q4 | AL8: Q4 | AN8: Q1 | AO8: Q2 | AP8: Q3 | AQ8: Q4 | AR8: Q1 | AS8: Q2 | AT8: Q3 | AU8: Q4 | AV8: Q1 | AW8: Q2 | AX8: Q3 | AY8: Q4 | BA8: YTD | BB8: TTM | BC8: Annual
B9: ($ in USD) | C9: 44957 | D9: =+EOMONTH(C9,1) -> 44985 | E9: =+EOMONTH(D9,1) -> 45016 | F9: =+EOMONTH(E9,1) -> 45046 | G9: =+EOMONTH(F9,1) -> 45077 | H9: =+EOMONTH(G9,1) -> 45107 | I9: =+EOMONTH(H9,1) -> 45138 | J9: =+EOMONTH(I9,1) -> 45169 | K9: =+EOMONTH(J9,1) -> 45199 | ... N9: =+EOMONTH(M9,1) -> 45291 | O9: 45322 | P9: =EOMONTH(O9,1) -> 45351 | Q9: =EOMONTH(P9,1) -> 45382 | R9: =EOMONTH(Q9,1) -> 45412 | S9: =EOMONTH(R9,1) -> 45443 | T9: =EOMONTH(S9,1) -> 45473 | U9: =EOMONTH(T9,1) -> 45504 | V9: =EOMONTH(U9,1) -> 45535 | W9: =EOMONTH(V9,1) -> 45565 | ... AL9: =EOMONTH(AK9,1) -> 46022 | AN9: 45016 | AO9: =+EOMONTH(AN9,3) -> 45107 | AP9: =+EOMONTH(AO9,3) -> 45199 | AQ9: =+EOMONTH(AP9,3) -> 45291 | AR9: =+EOMONTH(AQ9,3) -> 45382 | AS9: =+EOMONTH(AR9,3) -> 45473 | AT9: =+EOMONTH(AS9,3) -> 45565 | AU9: =+EOMONTH(AT9,3) -> 45657 | AV9: =+EOMONTH(AU9,3) -> 45747 | ... AY9: =+EOMONTH(AX9,3) -> 46022 | BA9: 46022 | BB9: =+BA9 -> 46022 | BC9: 46022
B11: ARR
B12: Industrial | C12: =+'Cons TrioMobil | Monthly'!AM12*12 -> 2186598.7 | D12: =+'Cons TrioMobil | Monthly'!AN12*12 -> 2239128.4 | E12: =+'Cons TrioMobil | Monthly'!AO12*12 -> 2298623.5 | F12: =+'Cons TrioMobil | Monthly'!AP12*12 -> 2420322.1 | G12: =+'Cons TrioMobil | Monthly'!AQ12*12 -> 2530957.5 | H12: =+'Cons TrioMobil | Monthly'!AR12*12 -> 2701022.1 | I12: =+'Cons TrioMobil | Monthly'!AS12*12 -> 2787753.1 | J12: =+'Cons TrioMobil | Monthly'!AT12*12 -> 3365438 | ... AL12: =+'Cons TrioMobil | Monthly'!BV12*12 -> 7831612 | AN12: =+SUMIFS($B12:$AM12,$B$9:$AM$9,AN$9) -> 2298623.5 | AO12: =+SUMIFS($B12:$AM12,$B$9:$AM$9,AO$9) -> 2701022.1 | AP12: =+SUMIFS($B12:$AM12,$B$9:$AM$9,AP$9) -> 3537652.7 | AQ12: =+SUMIFS($B12:$AM12,$B$9:$AM$9,AQ$9) -> 3967064.8 | AR12: =+SUMIFS($B12:$AM12,$B$9:$AM$9,AR$9) -> 4196656.3 | AS12: =+SUMIFS($B12:$AM12,$B$9:$AM$9,AS$9) -> 4520232.3 | AT12: =+SUMIFS($B12:$AM12,$B$9:$AM$9,AT$9) -> 4855874.6 | AU12: =+SUMIFS($B12:$AM12,$B$9:$AM$9,AU$9) -> 5192351 | ... AY12: =+SUMIFS($B12:$AM12,$B$9:$AM$9,AY$9) -> 7831612 | BA12: =+SUMIFS($B12:$AM12,$B$9:$AM$9,BA$9) -> 7831612 | BB12: =BA12 -> 7831612 | BC12: 8308142.7
B13: Fleet | C13: =+'Cons TrioMobil | Monthly'!AM11*12 -> 2890212.5 | D13: =+'Cons TrioMobil | Monthly'!AN11*12 -> 2913372.6 | E13: =+'Cons TrioMobil | Monthly'!AO11*12 -> 3063903.3 | F13: =+'Cons TrioMobil | Monthly'!AP11*12 -> 3163283.7 | G13: =+'Cons TrioMobil | Monthly'!AQ11*12 -> 3242080.2 | H13: =+'Cons TrioMobil | Monthly'!AR11*12 -> 3332278.2 | I13: =+'Cons TrioMobil | Monthly'!AS11*12 -> 3469655.8 | J13: =+'Cons TrioMobil | Monthly'!AT11*12 -> 3575475.9 | ... AL13: =+'Cons TrioMobil | Monthly'!BV11*12 -> 8825010.3 | AN13: =+SUMIFS($B13:$AM13,$B$9:$AM$9,AN$9) -> 3063903.3 | AO13: =+SUMIFS($B13:$AM13,$B$9:$AM$9,AO$9) -> 3332278.2 | AP13: =+SUMIFS($B13:$AM13,$B$9:$AM$9,AP$9) -> 3629083.8 | AQ13: =+SUMIFS($B13:$AM13,$B$9:$AM$9,AQ$9) -> 4142219.7 | AR13: =+SUMIFS($B13:$AM13,$B$9:$AM$9,AR$9) -> 4814880.8 | AS13: =+SUMIFS($B13:$AM13,$B$9:$AM$9,AS$9) -> 5459520.4 | AT13: =+SUMIFS($B13:$AM13,$B$9:$AM$9,AT$9) -> 6100263 | AU13: =+SUMIFS($B13:$AM13,$B$9:$AM$9,AU$9) -> 6934540.8 | ... AY13: =+SUMIFS($B13:$AM13,$B$9:$AM$9,AY$9) -> 8825010.3 | BA13: =+SUMIFS($B13:$AM13,$B$9:$AM$9,BA$9) -> 8825010.3 | BB13: =BA13 -> 8825010.3 | BC13: 9995589.6
B14: Total | C14: =SUM(C12:C13) -> 5076811.2 | D14: =SUM(D12:D13) -> 5152501 | E14: =SUM(E12:E13) -> 5362526.8 | F14: =SUM(F12:F13) -> 5583605.8 | G14: =SUM(G12:G13) -> 5773037.7 | H14: =SUM(H12:H13) -> 6033300.2 | I14: =SUM(I12:I13) -> 6257408.9 | J14: =SUM(J12:J13) -> 6940913.8 | ... AL14: =SUM(AL12:AL13) -> 16656622 | AN14: =SUM(AN12:AN13) -> 5362526.8 | AO14: =SUM(AO12:AO13) -> 6033300.2 | AP14: =SUM(AP12:AP13) -> 7166736.5 | AQ14: =SUM(AQ12:AQ13) -> 8109284.5 | AR14: =SUM(AR12:AR13) -> 9011537.1 | AS14: =SUM(AS12:AS13) -> 9979752.8 | AT14: =SUM(AT12:AT13) -> 10956138 | AU14: =SUM(AU12:AU13) -> 12126892 | ... AY14: =SUM(AY12:AY13) -> 16656622 | BA14: =SUM(BA12:BA13) -> 16656622 | BB14: =BA14 -> 16656622 | BC14: =+SUM(BC12:BC13) -> 18303732
B15: % YoY Growth | C15: =C14/'Consolidated ARR Rollforward'!AP14-1 -> 0.44709821 | D15: =D14/'Consolidated ARR Rollforward'!AQ14-1 -> 0.457787 | E15: =E14/'Consolidated ARR Rollforward'!AR14-1 -> 0.47648599 | F15: =F14/'Consolidated ARR Rollforward'!AS14-1 -> 0.46133061 | G15: =G14/'Consolidated ARR Rollforward'!AT14-1 -> 0.42656261 | H15: =H14/'Consolidated ARR Rollforward'!AU14-1 -> 0.43537867 | I15: =I14/'Consolidated ARR Rollforward'!AV14-1 -> 0.43693744 | J15: =J14/'Consolidated ARR Rollforward'!AW14-1 -> 0.58713498 | ... AL15: =AL14/'Consolidated ARR Rollforward'!BY14-1 -> 0.37352774 | AN15: =AN14/INDEX('Consolidated ARR Rollforward'!$I$14:$W$14,MATCH(EOMONTH('P&L'!AN$9,-12),'Consolidated ARR Rollforward'!$I$8:$W$8,0))-1 -> 0.47648599 | AO15: =AO14/INDEX('Consolidated ARR Rollforward'!$I$14:$W$14,MATCH(EOMONTH('P&L'!AO$9,-12),'Consolidated ARR Rollforward'!$I$8:$W$8,0))-1 -> 0.43537867 | AP15: =AP14/INDEX('Consolidated ARR Rollforward'!$I$14:$W$14,MATCH(EOMONTH('P&L'!AP$9,-12),'Consolidated ARR Rollforward'!$I$8:$W$8,0))-1 -> 0.57533454 | AQ15: =AQ14/INDEX('Consolidated ARR Rollforward'!$I$14:$W$14,MATCH(EOMONTH('P&L'!AQ$9,-12),'Consolidated ARR Rollforward'!$I$8:$W$8,0))-1 -> 0.62090752 | AR15: =AR14/INDEX('Consolidated ARR Rollforward'!$I$14:$W$14,MATCH(EOMONTH('P&L'!AR$9,-12),'Consolidated ARR Rollforward'!$I$8:$W$8,0))-1 -> 0.68046472 | AS15: =AS14/INDEX('Consolidated ARR Rollforward'!$I$14:$W$14,MATCH(EOMONTH('P&L'!AS$9,-12),'Consolidated ARR Rollforward'!$I$8:$W$8,0))-1 -> 0.65411174 | AT15: =AT14/INDEX('Consolidated ARR Rollforward'!$I$14:$W$14,MATCH(EOMONTH('P&L'!AT$9,-12),'Consolidated ARR Rollforward'!$I$8:$W$8,0))-1 -> 0.52874848 | AU15: =AU14/INDEX('Consolidated ARR Rollforward'!$I$14:$W$14,MATCH(EOMONTH('P&L'!AU$9,-12),'Consolidated ARR Rollforward'!$I$8:$W$8,0))-1 -> 0.49543303 | ... AX15: =AX14/INDEX('Consolidated ARR Rollforward'!$I$14:$W$14,MATCH(EOMONTH('P&L'!AX$9,-12),'Consolidated ARR Rollforward'!$I$8:$W$8,0))-1 -> 0.39403187 | AY15: =AY14/INDEX('Consolidated ARR Rollforward'!$I$14:$AB$14,MATCH(EOMONTH('P&L'!AY$9,-12),'Consolidated ARR Rollforward'!$I$8:$AB$8,0))-1 -> 0.37352774 | BA15: =+BA14/INDEX('Consolidated ARR Rollforward'!$AD$14:$CL$14,MATCH(EOMONTH(BA9,-12),'Consolidated ARR Rollforward'!$AD$8:$CL$8,0))-1 -> 0.37352774 | BB15: =+BB14/INDEX('Consolidated ARR Rollforward'!$AD$14:$CL$14,MATCH(EOMONTH(BB9,-12),'Consolidated ARR Rollforward'!$AD$8:$CL$8,0))-1 -> 0.37352774
B16: % Industrial Growth | C16: =C12/'Industrial ARR Rollforward'!AP14-1 -> 1.12497 | D16: =D12/'Industrial ARR Rollforward'!AQ14-1 -> 1.1033822 | E16: =E12/'Industrial ARR Rollforward'!AR14-1 -> 0.96645628 | F16: =F12/'Industrial ARR Rollforward'!AS14-1 -> 0.82623833 | G16: =G12/'Industrial ARR Rollforward'!AT14-1 -> 0.72675821 | H16: =H12/'Industrial ARR Rollforward'!AU14-1 -> 0.66216196 | I16: =I12/'Industrial ARR Rollforward'!AV14-1 -> 0.61750071 | J16: =J12/'Industrial ARR Rollforward'!AW14-1 -> 0.92670077 | ... AL16: =AL12/'Industrial ARR Rollforward'!BY14-1 -> 0.50829787 | AN16: =AN12/INDEX('Industrial ARR Rollforward'!$I$14:$W$14,MATCH(EOMONTH('P&L'!AN$9,-12),'Industrial ARR Rollforward'!$I$8:$W$8,0))-1 -> 0.96645628 | AO16: =AO12/INDEX('Industrial ARR Rollforward'!$I$14:$W$14,MATCH(EOMONTH('P&L'!AO$9,-12),'Industrial ARR Rollforward'!$I$8:$W$8,0))-1 -> 0.66216196 | AP16: =AP12/INDEX('Industrial ARR Rollforward'!$I$14:$W$14,MATCH(EOMONTH('P&L'!AP$9,-12),'Industrial ARR Rollforward'!$I$8:$W$8,0))-1 -> 0.89889119 | AQ16: =AQ12/INDEX('Industrial ARR Rollforward'!$I$14:$W$14,MATCH(EOMONTH('P&L'!AQ$9,-12),'Industrial ARR Rollforward'!$I$8:$W$8,0))-1 -> 0.81337385 | AR16: =AR12/INDEX('Industrial ARR Rollforward'!$I$14:$W$14,MATCH(EOMONTH('P&L'!AR$9,-12),'Industrial ARR Rollforward'!$I$8:$W$8,0))-1 -> 0.82572579 | AS16: =AS12/INDEX('Industrial ARR Rollforward'!$I$14:$W$14,MATCH(EOMONTH('P&L'!AS$9,-12),'Industrial ARR Rollforward'!$I$8:$W$8,0))-1 -> 0.67352662 | AT16: =AT12/INDEX('Industrial ARR Rollforward'!$I$14:$W$14,MATCH(EOMONTH('P&L'!AT$9,-12),'Industrial ARR Rollforward'!$I$8:$W$8,0))-1 -> 0.37262614 | AU16: =AU12/INDEX('Industrial ARR Rollforward'!$I$14:$W$14,MATCH(EOMONTH('P&L'!AU$9,-12),'Industrial ARR Rollforward'!$I$8:$W$8,0))-1 -> 0.30886471 | ... AX16: =AX12/INDEX('Industrial ARR Rollforward'!$I$14:$W$14,MATCH(EOMONTH('P&L'!AX$9,-12),'Industrial ARR Rollforward'!$I$8:$W$8,0))-1 -> 0.39851888 | AY16: =AY12/INDEX('Industrial ARR Rollforward'!$I$14:$AB$14,MATCH(EOMONTH('P&L'!AY$9,-12),'Industrial ARR Rollforward'!$I$8:$AB$8,0))-1 -> 0.50829787 | BA16: =+BA12/INDEX('Industrial ARR Rollforward'!$AD$14:$CL$14,MATCH(EOMONTH(BA$9,-12),'Industrial ARR Rollforward'!$AD$8:$CL$8,0))-1 -> 0.50829787 | BB16: =+BB12/INDEX('Industrial ARR Rollforward'!$AD$14:$CL$14,MATCH(EOMONTH(BB$9,-12),'Industrial ARR Rollforward'!$AD$8:$CL$8,0))-1 -> 0.50829787
